Workbook

Sheet CMFA-CSCDA Grants
A1: Project ID | B1: Property Name | C1: Applicant / Entity | D1: City | E1: County | F1: Agency | G1: Grant Description | H1: Resolution | I1: Date | J1: DEAD? | K1: Investor 1 | L1: Investor 2 | M1: Nonprofit Partner | N1: Stale | O1: Total Unit Count | P1: Restricted Unit Count | Q1: Restricted Ratio | R1: Address | S1: City's Cut | T1: Parcel Identified | U1: Welfare Exemption On 2025 Roll | V1: Total Roll Value | W1: Confirmed Exemption | X1: Best Estimate Exemption | Y1: Confirmed or Best Estimate Exemption | Z1: Tax Rate | AA1: Confirmed Annual Revenue Loss | AB1: Best Estimate Annual Revenue Loss | AC1: Link | AD1: Leasing Link | AE1: New build? | AF1: Built | AG1: Acquisition Price (M) | AH1: Acquisition Date | AI1: Regulatory Term | AJ1: Closing Fee | AK1: CMFA Annual Fee | AL1: YEARS IN SERVICE | AM1: ANNUAL FEES PAID | AN1: SCC FILED?
A2: 238 | B2: Heritage Park Apartments Livermore | C2: Standard Heritage Livermore Owner LP | D2: Livermore | E2: Alameda | F2: CMFA | G2: Loan / $100,000 | I2: 44659 | K2: Standard Property Company | M2: Housing on Merit | N2: FALSE | O2: 167 | P2: 125 | R2: 900 E Stanley Blvd, Livermore, CA 94550 | AE2: NO | AF2: 1988 | AJ2: =if(F2="CMFA", if(O2<16,10000,O2*600),if(F2="CSCDA",if(33<O2<300, O2*600,if(O2>300,(180000+(O2-300)*300),20000)))) -> 100200 | AK2: =if(F2="CMFA", if(O2<26,4000,O2*150),if(F2="CSCDA",if(33<O2<300, O2*150,if(O2>300,(45000+(O2-300)*75),5000)))) -> 25050 | AL2: =if(AE2="YES",0,IF(AND(I2>=DATE(2022,7,1),I2<=DATE(2023,6,30)),3,IF(AND(I2>=DATE(2023,7,1),I2<=DATE(2024,6,30)),2,IF(AND(I2>=DATE(2024,7,1),I2<=DATE(2025,6,30)),1,IF(AND(I2>=DATE(2025,7,1),I2<=DATE(2026,6,30)),0,"-"))))) -> - | AM2: =AK2*AL2 -> #VALUE! | AN2: TRUE
A3: 192 | B3: Heritage Village Anaheim Apartments | C3: Standard Heritage Anaheim Owner LP | D3: Anaheim | E3: Orange | F3: CMFA | G3: Loan / $100,000 | I3: 44666 | K3: Standard Property Company | M3: Housing on Merit | N3: FALSE | O3: 196 | P3: 157 | Q3: =P3/O3 -> 0.80102041 | R3: 707 W Santa Ana Street, Anaheim CA 92805 | S3: 16850 | T3: =COUNTIF(Parcels!A:A, A3) > 0 -> TRUE | U3: =MAXIFS(Parcels!AC:AC, Parcels!A:A, A3) > 0 -> TRUE | V3: =SUMIF(Parcels!A:A, A3, Parcels!Z:Z) -> 67860998 | W3: =SUMIF(Parcels!$A:$A, $A3, Parcels!AC:AC) -> 67860998 | X3: =V3*P3/O3*0.9 -> 48922240 | Y3: =IF(W3=0, X3, W3) -> 67860998 | Z3: {=_xlfn.XLOOKUP( A3, Parcels!A:A, Parcels!AL:AL)} | AA3: =W3*Z3 -> 0 | AB3: =Y3*Z3 -> 0 | AJ3: =if(F3="CMFA", if(O3<16,10000,O3*600),if(F3="CSCDA",if(33<O3<300, O3*600,if(O3>300,(180000+(O3-300)*300),20000)))) -> 117600 | AK3: =if(F3="CMFA", if(O3<26,4000,O3*150),if(F3="CSCDA",if(33<O3<300, O3*150,if(O3>300,(45000+(O3-300)*75),5000)))) -> 29400 | AL3: =if(AE3="YES",0,IF(AND(I3>=DATE(2022,7,1),I3<=DATE(2023,6,30)),3,IF(AND(I3>=DATE(2023,7,1),I3<=DATE(2024,6,30)),2,IF(AND(I3>=DATE(2024,7,1),I3<=DATE(2025,6,30)),1,IF(AND(I3>=DATE(2025,7,1),I3<=DATE(2026,6,30)),0,"-"))))) -> - | AM3: =AK3*AL3 -> #VALUE! | AN3: TRUE
A4: 193 | B4: Heritage Park Escondido Apartments | C4: STANDARD HERITAGE ESCONDIDO OWNER LP | D4: Escondido | E4: San Diego | F4: CMFA | G4: Loan / $100,000 | I4: 44666 | K4: Standard Property Company | M4: Housing on Merit | N4: FALSE | O4: 196 | P4: 157 | Q4: =P4/O4 -> 0.80102041 | R4: 2549 E. Valley Parkway, Escondido, CA 92027 | S4: 15766 | T4: =COUNTIF(Parcels!A:A, A4) > 0 -> TRUE | U4: =MAXIFS(Parcels!AC:AC, Parcels!A:A, A4) > 0 -> TRUE | V4: =SUMIF(Parcels!A:A, A4, Parcels!Z:Z) -> 49668778 | W4: =SUMIF(Parcels!$A:$A, $A4, Parcels!AC:AC) -> 49157189 | X4: =V4*P4/O4*0.9 -> 35807134 | Y4: =IF(W4=0, X4, W4) -> 49157189 | Z4: {=_xlfn.XLOOKUP( A4, Parcels!A:A, Parcels!AL:AL)} | AA4: =W4*Z4 -> 0 | AJ4: =if(F4="CMFA", if(O4<16,10000,O4*600),if(F4="CSCDA",if(33<O4<300, O4*600,if(O4>300,(180000+(O4-300)*300),20000)))) -> 117600 | AK4: =if(F4="CMFA", if(O4<26,4000,O4*150),if(F4="CSCDA",if(33<O4<300, O4*150,if(O4>300,(45000+(O4-300)*75),5000)))) -> 29400 | AL4: =if(AE4="YES",0,IF(AND(I4>=DATE(2022,7,1),I4<=DATE(2023,6,30)),3,IF(AND(I4>=DATE(2023,7,1),I4<=DATE(2024,6,30)),2,IF(AND(I4>=DATE(2024,7,1),I4<=DATE(2025,6,30)),1,IF(AND(I4>=DATE(2025,7,1),I4<=DATE(2026,6,30)),0,"-"))))) -> - | AM4: =AK4*AL4 -> #VALUE! | AN4: {=_xlfn.xlookup(C4,'SCC Certificate Review'!C:C,'SCC Certificate Review'!F:F)} -> #N/A
A5: 1 | B5: Alvarado Streets Apartments | C5: Alvarado Affordable Associates, LP | D5: Los Angeles | E5: Los Angeles | F5: CMFA | G5: Grant up to $10,000 | H5: 23-204 | I5: 45121 | K5: Taylor Equities | M5: Kingdom Development, Inc. | N5: FALSE | O5: 24 | P5: 24 | Q5: =P5/O5 -> 1 | R5: 1136 S. Alvarado Street, Los Angeles, CA | S5: 3600 | T5: =COUNTIF(Parcels!A:A, A5) > 0 -> TRUE | U5: =MAXIFS(Parcels!AC:AC, Parcels!A:A, A5) > 0 -> TRUE | V5: =SUMIF(Parcels!A:A, A5, Parcels!Z:Z) -> 4447710 | W5: =SUMIF(Parcels!$A:$A, $A5, Parcels!AC:AC) -> 4262686 | X5: =V5*P5/O5*0.9 -> 4002939 | Y5: =IF(W5=0, X5, W5) -> 4262686 | Z5: {=_xlfn.XLOOKUP( A5, Parcels!A:A, Parcels!AL:AL)} -> 0.0118738 | AA5: =W5*Z5 -> 50614.281 | AB5: =Y5*Z5 -> 50614.281 | AJ5: =if(F5="CMFA", if(O5<16,10000,O5*600),if(F5="CSCDA",if(33<O5<300, O5*600,if(O5>300,(180000+(O5-300)*300),20000)))) -> 14400 | AK5: =if(F5="CMFA", if(O5<26,4000,O5*150),if(F5="CSCDA",if(33<O5<300, O5*150,if(O5>300,(45000+(O5-300)*75),5000)))) -> 4000 | AL5: =if(AE5="YES",0,IF(AND(I5>=DATE(2022,7,1),I5<=DATE(2023,6,30)),3,IF(AND(I5>=DATE(2023,7,1),I5<=DATE(2024,6,30)),2,IF(AND(I5>=DATE(2024,7,1),I5<=DATE(2025,6,30)),1,IF(AND(I5>=DATE(2025,7,1),I5<=DATE(2026,6,30)),0,"-"))))) -> 2 | AM5: =AK5*AL5 -> 8000 | AN5: {=_xlfn.xlookup(C5,'SCC Certificate Review'!C:C,'SCC Certificate Review'!F:F)} -> TRUE
A6: 4 | B6: Bernardine Apartments | C6: Castle Rock Bernardine Apartments, LP | D6: San Bernardino | E6: San Bernardino | F6: CMFA | G6: Grant up to $10,000 | H6: 23-222 | I6: 45142 | K6: Quest Capital Partners | M6: Affordable Rent Project | N6: FALSE | O6: 71 | P6: 70 | R6: 363 E. Gilbert St., San Bernardino, CA | S6: 10650 | T6: =COUNTIF(Parcels!A:A, A6) > 0 -> TRUE | U6: =MAXIFS(Parcels!AC:AC, Parcels!A:A, A6) > 0 -> TRUE | V6: =SUMIF(Parcels!A:A, A6, Parcels!Z:Z) -> 4156500 | W6: =SUMIF(Parcels!$A:$A, $A6, Parcels!AC:AC) -> 4156500 | X6: =V6*P6/O6*0.9 -> 3688162 | Y6: =IF(W6=0, X6, W6) -> 4156500 | Z6: {=_xlfn.XLOOKUP( A6, Parcels!A:A, Parcels!AL:AL)} -> 0.0113 | AA6: =W6*Z6 -> 46968.45 | AB6: =Y6*Z6 -> 46968.45 | AJ6: =if(F6="CMFA", if(O6<16,10000,O6*600),if(F6="CSCDA",if(33<O6<300, O6*600,if(O6>300,(180000+(O6-300)*300),20000)))) -> 42600 | AK6: =if(F6="CMFA", if(O6<26,4000,O6*150),if(F6="CSCDA",if(33<O6<300, O6*150,if(O6>300,(45000+(O6-300)*75),5000)))) -> 10650 | AL6: =if(AE6="YES",0,IF(AND(I6>=DATE(2022,7,1),I6<=DATE(2023,6,30)),3,IF(AND(I6>=DATE(2023,7,1),I6<=DATE(2024,6,30)),2,IF(AND(I6>=DATE(2024,7,1),I6<=DATE(2025,6,30)),1,IF(AND(I6>=DATE(2025,7,1),I6<=DATE(2026,6,30)),0,"-"))))) -> 2 | AM6: =AK6*AL6 -> 21300 | AN6: {=_xlfn.xlookup(C6,'SCC Certificate Review'!C:C,'SCC Certificate Review'!F:F)} -> TRUE
A7: 2 | B7: 2025 New Jersey Apartments | C7: 2025 NJ, LP | D7: Los Angeles | E7: Los Angeles | F7: CMFA | G7: Grant up to $10,000 | H7: 23-223 | I7: 45142 | K7: Eleos Ventures, LLC | M7: Step Forward Communities | N7: FALSE | O7: 15 | P7: 14 | Q7: =P7/O7 -> 0.93333333 | R7: 2025 New Jersey St, Los Angeles, CA | S7: 2250 | T7: =COUNTIF(Parcels!A:A, A7) > 0 -> TRUE | U7: =MAXIFS(Parcels!AC:AC, Parcels!A:A, A7) > 0 -> TRUE | V7: =SUMIF(Parcels!A:A, A7, Parcels!Z:Z) -> 527950 | W7: =SUMIF(Parcels!$A:$A, $A7, Parcels!AC:AC) -> 527950 | X7: =V7*P7/O7*0.9 -> 443478 | Y7: =IF(W7=0, X7, W7) -> 527950 | Z7: {=_xlfn.XLOOKUP( A7, Parcels!A:A, Parcels!AL:AL)} -> 0.0118738 | AA7: =W7*Z7 -> 6268.7727 | AB7: =Y7*Z7 -> 6268.7727 | AF7: 2023 | AJ7: =if(F7="CMFA", if(O7<16,10000,O7*600),if(F7="CSCDA",if(33<O7<300, O7*600,if(O7>300,(180000+(O7-300)*300),20000)))) -> 10000 | AK7: =if(F7="CMFA", if(O7<26,4000,O7*150),if(F7="CSCDA",if(33<O7<300, O7*150,if(O7>300,(45000+(O7-300)*75),5000)))) -> 4000 | AL7: =if(AE7="YES",0,IF(AND(I7>=DATE(2022,7,1),I7<=DATE(2023,6,30)),3,IF(AND(I7>=DATE(2023,7,1),I7<=DATE(2024,6,30)),2,IF(AND(I7>=DATE(2024,7,1),I7<=DATE(2025,6,30)),1,IF(AND(I7>=DATE(2025,7,1),I7<=DATE(2026,6,30)),0,"-"))))) -> 2 | AM7: =AK7*AL7 -> 8000 | AN7: {=_xlfn.xlookup(C7,'SCC Certificate Review'!C:C,'SCC Certificate Review'!F:F)} -> TRUE
A8: 3 | B8: Mariposa Club Apartments | C8: Mariposa Club Apartments I, LP | D8: Mountain View | E8: Santa Clara | F8: CMFA | G8: Grant up to $10,000 | H8: 23-224 | I8: 45142 | K8: Prometheus Real Estate Group | M8: Hearthstone Housing Foundation | N8: FALSE | O8: 48 | P8: 48 | R8: 660 Mariposa Ave., Mountain View, CA | S8: 7500 | T8: =COUNTIF(Parcels!A:A, A8) > 0 -> TRUE | U8: =MAXIFS(Parcels!AC:AC, Parcels!A:A, A8) > 0 -> TRUE | V8: =SUMIF(Parcels!A:A, A8, Parcels!Z:Z) -> 17059601 | W8: =SUMIF(Parcels!$A:$A, $A8, Parcels!AC:AC) -> 16718409 | X8: =V8*P8/O8*0.9 -> 15353641 | Y8: =IF(W8=0, X8, W8) -> 16718409 | Z8: {=_xlfn.XLOOKUP( A8, Parcels!A:A, Parcels!AL:AL)} -> 0.011211 | AA8: =W8*Z8 -> 187430.08 | AB8: =Y8*Z8 -> 187430.08 | AJ8: =if(F8="CMFA", if(O8<16,10000,O8*600),if(F8="CSCDA",if(33<O8<300, O8*600,if(O8>300,(180000+(O8-300)*300),20000)))) -> 28800 | AK8: =if(F8="CMFA", if(O8<26,4000,O8*150),if(F8="CSCDA",if(33<O8<300, O8*150,if(O8>300,(45000+(O8-300)*75),5000)))) -> 7200 | AL8: =if(AE8="YES",0,IF(AND(I8>=DATE(2022,7,1),I8<=DATE(2023,6,30)),3,IF(AND(I8>=DATE(2023,7,1),I8<=DATE(2024,6,30)),2,IF(AND(I8>=DATE(2024,7,1),I8<=DATE(2025,6,30)),1,IF(AND(I8>=DATE(2025,7,1),I8<=DATE(2026,6,30)),0,"-"))))) -> 2 | AM8: =AK8*AL8 -> 14400 | AN8: {=_xlfn.xlookup(C8,'SCC Certificate Review'!C:C,'SCC Certificate Review'!F:F)} -> TRUE
A9: 5 | B9: City View aka Outlook at Mission Valley Apartments | C9: Mission Valley Preservation LP | D9: San Diego | E9: San Diego | F9: CMFA | G9: Grant up to $10,000 | H9: 23-275 | I9: 45163 | K9: Securities Properties | M9: Las Palmas Housing & Development | N9: FALSE | O9: 56 | P9: 23 | R9: 840 17th St, San Diego, CA 92101 | S9: 8400 | T9: =COUNTIF(Parcels!A:A, A9) > 0 -> TRUE | U9: =MAXIFS(Parcels!AC:AC, Parcels!A:A, A9) > 0 -> FALSE | V9: =SUMIF(Parcels!A:A, A9, Parcels!Z:Z) -> 9316117 | W9: =SUMIF(Parcels!$A:$A, $A9, Parcels!AC:AC) -> 0 | X9: =V9*P9/O9*0.9 -> 3443636.1 | Y9: =IF(W9=0, X9, W9) -> 3443636.1 | Z9: {=_xlfn.XLOOKUP( A9, Parcels!A:A, Parcels!AL:AL)} -> 0.0125114 | AA9: =W9*Z9 -> 0 | AB9: =Y9*Z9 -> 43084.709 | AJ9: =if(F9="CMFA", if(O9<16,10000,O9*600),if(F9="CSCDA",if(33<O9<300, O9*600,if(O9>300,(180000+(O9-300)*300),20000)))) -> 33600 | AK9: =if(F9="CMFA", if(O9<26,4000,O9*150),if(F9="CSCDA",if(33<O9<300, O9*150,if(O9>300,(45000+(O9-300)*75),5000)))) -> 8400 | AL9: =if(AE9="YES",0,IF(AND(I9>=DATE(2022,7,1),I9<=DATE(2023,6,30)),3,IF(AND(I9>=DATE(2023,7,1),I9<=DATE(2024,6,30)),2,IF(AND(I9>=DATE(2024,7,1),I9<=DATE(2025,6,30)),1,IF(AND(I9>=DATE(2025,7,1),I9<=DATE(2026,6,30)),0,"-"))))) -> 2 | AM9: =AK9*AL9 -> 16800 | AN9: {=_xlfn.xlookup(C9,'SCC Certificate Review'!C:C,'SCC Certificate Review'!F:F)} -> TRUE
A10: 6 | B10: 381 Turk Street Apartment | C10: 381 Turk Street Associates | D10: San Francisco | E10: San Francisco | F10: CMFA | G10: Grant up to $10,000 | H10: 23-307 | I10: 45184 | J10: TRUE | K10: Mosser Capital, LLC | M10: Kingdom Development, Inc. | N10: FALSE | O10: 32 | P10: 13 | R10: 381 Turk St., San Francisco, CA | S10: 4800 | T10: =COUNTIF(Parcels!A:A, A10) > 0 -> TRUE | U10: =MAXIFS(Parcels!AC:AC, Parcels!A:A, A10) > 0 -> FALSE | V10: =SUMIF(Parcels!A:A, A10, Parcels!Z:Z) -> 7398189 | W10: =SUMIF(Parcels!$A:$A, $A10, Parcels!AC:AC) -> 0 | X10: =V10*P10/O10*0.9 -> 2704962.9 | Y10: =IF(W10=0, X10, W10) -> 2704962.9 | Z10: {=_xlfn.XLOOKUP( A10, Parcels!A:A, Parcels!AL:AL)} -> 0.012 | AA10: =W10*Z10 -> 0 | AB10: =Y10*Z10 -> 32459.554 | AJ10: =if(F10="CMFA", if(O10<16,10000,O10*600),if(F10="CSCDA",if(33<O10<300, O10*600,if(O10>300,(180000+(O10-300)*300),20000)))) -> 19200 | AK10: =if(F10="CMFA", if(O10<26,4000,O10*150),if(F10="CSCDA",if(33<O10<300, O10*150,if(O10>300,(45000+(O10-300)*75),5000)))) -> 4800 | AL10: =if(AE10="YES",0,IF(AND(I10>=DATE(2022,7,1),I10<=DATE(2023,6,30)),3,IF(AND(I10>=DATE(2023,7,1),I10<=DATE(2024,6,30)),2,IF(AND(I10>=DATE(2024,7,1),I10<=DATE(2025,6,30)),1,IF(AND(I10>=DATE(2025,7,1),I10<=DATE(2026,6,30)),0,"-"))))) -> 2 | AM10: =AK10*AL10 -> 9600 | AN10: {=_xlfn.xlookup(C10,'SCC Certificate Review'!C:C,'SCC Certificate Review'!F:F)}
A11: 7 | B11: Townhomes at Gading Apartments | C11: SFF 2, LLC | D11: Hayward | E11: Alameda | F11: CMFA | G11: Grant up to $10,000 | H11: 23-370 | I11: 45268 | K11: The Sobrato Organization | M11: Sobrato Foundation | N11: FALSE | O11: 61 | P11: 61 | R11: 26409 Gading Rd, Hayward, CA 94544 | S11: 9150 | T11: =COUNTIF(Parcels!A:A, A11) > 0 -> TRUE | U11: =MAXIFS(Parcels!AC:AC, Parcels!A:A, A11) > 0 -> FALSE | V11: =SUMIF(Parcels!A:A, A11, Parcels!Z:Z) -> 17313480 | W11: =SUMIF(Parcels!$A:$A, $A11, Parcels!AC:AC) -> 0 | X11: =V11*P11/O11*0.9 -> 15582132 | Y11: =IF(W11=0, X11, W11) -> 15582132 | Z11: {=_xlfn.XLOOKUP( A11, Parcels!A:A, Parcels!AL:AL)} -> 0.011724 | AA11: =W11*Z11 -> 0 | AB11: =Y11*Z11 -> 182684.92 | AD11: https://www.townhomesongadingapts.com/ | AJ11: =if(F11="CMFA", if(O11<16,10000,O11*600),if(F11="CSCDA",if(33<O11<300, O11*600,if(O11>300,(180000+(O11-300)*300),20000)))) -> 36600 | AK11: =if(F11="CMFA", if(O11<26,4000,O11*150),if(F11="CSCDA",if(33<O11<300, O11*150,if(O11>300,(45000+(O11-300)*75),5000)))) -> 9150 | AL11: =if(AE11="YES",0,IF(AND(I11>=DATE(2022,7,1),I11<=DATE(2023,6,30)),3,IF(AND(I11>=DATE(2023,7,1),I11<=DATE(2024,6,30)),2,IF(AND(I11>=DATE(2024,7,1),I11<=DATE(2025,6,30)),1,IF(AND(I11>=DATE(2025,7,1),I11<=DATE(2026,6,30)),0,"-"))))) -> 2 | AM11: =AK11*AL11 -> 18300 | AN11: {=_xlfn.xlookup(C11,'SCC Certificate Review'!C:C,'SCC Certificate Review'!F:F)}
A12: 8 | B12: 1317 S. Grand Apartments | C12: 1317 SGA QOZB, LP or an affiliate thereof | D12: Los Angeles | E12: Los Angeles | F12: CMFA | H12: 23-371 | I12: 45268 | K12: Housing Diversity Corporation | M12: PEP Housing | N12: FALSE | O12: 147 | P12: 147 | Q12: =P12/O12 -> 1 | R12: 1317 S. Grand St, Los Angeles, CA 90015 | S12: 22050 | T12: =COUNTIF(Parcels!A:A, A12) > 0 -> TRUE | U12: =MAXIFS(Parcels!AC:AC, Parcels!A:A, A12) > 0 -> FALSE | V12: =SUMIF(Parcels!A:A, A12, Parcels!Z:Z) -> 11783947 | W12: =SUMIF(Parcels!$A:$A, $A12, Parcels!AC:AC) -> 0 | X12: =V12*P12/O12*0.9 -> 10605552 | Y12: =IF(W12=0, X12, W12) -> 10605552 | Z12: {=_xlfn.XLOOKUP( A12, Parcels!A:A, Parcels!AL:AL)} -> 0.0118738 | AA12: =W12*Z12 -> 0 | AB12: =Y12*Z12 -> 125928.21 | AJ12: =if(F12="CMFA", if(O12<16,10000,O12*600),if(F12="CSCDA",if(33<O12<300, O12*600,if(O12>300,(180000+(O12-300)*300),20000)))) -> 88200 | AK12: =if(F12="CMFA", if(O12<26,4000,O12*150),if(F12="CSCDA",if(33<O12<300, O12*150,if(O12>300,(45000+(O12-300)*75),5000)))) -> 22050 | AL12: =if(AE12="YES",0,IF(AND(I12>=DATE(2022,7,1),I12<=DATE(2023,6,30)),3,IF(AND(I12>=DATE(2023,7,1),I12<=DATE(2024,6,30)),2,IF(AND(I12>=DATE(2024,7,1),I12<=DATE(2025,6,30)),1,IF(AND(I12>=DATE(2025,7,1),I12<=DATE(2026,6,30)),0,"-"))))) -> 2 | AM12: =AK12*AL12 -> 44100 | AN12: {=_xlfn.xlookup(C12,'SCC Certificate Review'!C:C,'SCC Certificate Review'!F:F)} -> TRUE
A13: 9 | B13: 1411 S. Flower Apartments | C13: Housing Diversity | D13: Los Angeles | E13: Los Angeles | F13: CMFA | H13: 23-372 | I13: 45268 | K13: Housing Diversity Corporation | L13: Arctaris Impact Investors | M13: PEP Housing | N13: FALSE | O13: 227 | P13: 227 | Q13: =P13/O13 -> 1 | R13: 1411 Flower St, Los Angeles, CA 90015 | S13: 34050 | T13: =COUNTIF(Parcels!A:A, A13) > 0 -> TRUE | U13: =MAXIFS(Parcels!AC:AC, Parcels!A:A, A13) > 0 -> FALSE | V13: =SUMIF(Parcels!A:A, A13, Parcels!Z:Z) -> 9142457 | W13: =SUMIF(Parcels!$A:$A, $A13, Parcels!AC:AC) -> 0 | X13: =V13*P13/O13*0.9 -> 8228211.3 | Y13: =IF(W13=0, X13, W13) -> 8228211.3 | Z13: {=_xlfn.XLOOKUP( A13, Parcels!A:A, Parcels!AL:AL)} -> 0.0118738 | AA13: =W13*Z13 -> 0 | AB13: =Y13*Z13 -> 97700.135 | AJ13: =if(F13="CMFA", if(O13<16,10000,O13*600),if(F13="CSCDA",if(33<O13<300, O13*600,if(O13>300,(180000+(O13-300)*300),20000)))) -> 136200 | AK13: =if(F13="CMFA", if(O13<26,4000,O13*150),if(F13="CSCDA",if(33<O13<300, O13*150,if(O13>300,(45000+(O13-300)*75),5000)))) -> 34050 | AL13: =if(AE13="YES",0,IF(AND(I13>=DATE(2022,7,1),I13<=DATE(2023,6,30)),3,IF(AND(I13>=DATE(2023,7,1),I13<=DATE(2024,6,30)),2,IF(AND(I13>=DATE(2024,7,1),I13<=DATE(2025,6,30)),1,IF(AND(I13>=DATE(2025,7,1),I13<=DATE(2026,6,30)),0,"-"))))) -> 2 | AM13: =AK13*AL13 -> 68100 | AN13: {=_xlfn.xlookup(C13,'SCC Certificate Review'!C:C,'SCC Certificate Review'!F:F)}
A14: 10 | B14: 7518 Hoover St. Apartments | C14: BIF NON OZ 7518 S Hoover St, LP | D14: Los Angeles | E14: Los Angeles | F14: CMFA | G14: Grant up to $10,000 | H14: 24-041 | I14: 45324 | K14: SoLa Impact, LLC | L14: Black Impact Group | M14: Housing on Merit | N14: FALSE | O14: 79 | P14: 48 | Q14: =P14/O14 -> 0.60759494 | R14: 7518 S. Hoover, Los Angeles, CA 90044 | S14: 11850 | T14: =COUNTIF(Parcels!A:A, A14) > 0 -> TRUE | U14: =MAXIFS(Parcels!AC:AC, Parcels!A:A, A14) > 0 -> FALSE | V14: =SUMIF(Parcels!A:A, A14, Parcels!Z:Z) -> 2856000 | W14: =SUMIF(Parcels!$A:$A, $A14, Parcels!AC:AC) -> 0 | X14: =V14*P14/O14*0.9 -> 1561762 | Y14: =IF(W14=0, X14, W14) -> 1561762 | Z14: {=_xlfn.XLOOKUP( A14, Parcels!A:A, Parcels!AL:AL)} -> 0.0118738 | AA14: =W14*Z14 -> 0 | AB14: =Y14*Z14 -> 18544.05 | AJ14: =if(F14="CMFA", if(O14<16,10000,O14*600),if(F14="CSCDA",if(33<O14<300, O14*600,if(O14>300,(180000+(O14-300)*300),20000)))) -> 47400 | AK14: =if(F14="CMFA", if(O14<26,4000,O14*150),if(F14="CSCDA",if(33<O14<300, O14*150,if(O14>300,(45000+(O14-300)*75),5000)))) -> 11850 | AL14: =if(AE14="YES",0,IF(AND(I14>=DATE(2022,7,1),I14<=DATE(2023,6,30)),3,IF(AND(I14>=DATE(2023,7,1),I14<=DATE(2024,6,30)),2,IF(AND(I14>=DATE(2024,7,1),I14<=DATE(2025,6,30)),1,IF(AND(I14>=DATE(2025,7,1),I14<=DATE(2026,6,30)),0,"-"))))) -> 2 | AM14: =AK14*AL14 -> 23700 | AN14: {=_xlfn.xlookup(C14,'SCC Certificate Review'!C:C,'SCC Certificate Review'!F:F)} -> TRUE
A15: 11 | B15: 820 MacArthur Apartments | C15: 2019 Ozone Affordable Housing | D15: Oakland | E15: Alameda | F15: CMFA | G15: Grant up to $10,000 | H15: 24-052 | I15: 45345 | K15: Riaz, Inc. | M15: AOF Pacific | N15: FALSE | O15: 166 | P15: 166 | R15: 820 W MacArthur Blvd, Oakland, CA 94608 | S15: 24900 | T15: =COUNTIF(Parcels!A:A, A15) > 0 -> TRUE | U15: =MAXIFS(Parcels!AC:AC, Parcels!A:A, A15) > 0 -> TRUE | V15: =SUMIF(Parcels!A:A, A15, Parcels!Z:Z) -> 2013882 | W15: =SUMIF(Parcels!$A:$A, $A15, Parcels!AC:AC) -> 7089890 | X15: =V15*P15/O15*0.9 -> 1812493.8 | Y15: =IF(W15=0, X15, W15) -> 7089890 | Z15: {=_xlfn.XLOOKUP( A15, Parcels!A:A, Parcels!AL:AL)} -> 0.012779 | AA15: =W15*Z15 -> 90601.704 | AB15: =Y15*Z15 -> 90601.704 | AE15: YES | AJ15: =if(F15="CMFA", if(O15<16,10000,O15*600),if(F15="CSCDA",if(33<O15<300, O15*600,if(O15>300,(180000+(O15-300)*300),20000)))) -> 99600 | AK15: =if(F15="CMFA", if(O15<26,4000,O15*150),if(F15="CSCDA",if(33<O15<300, O15*150,if(O15>300,(45000+(O15-300)*75),5000)))) -> 24900 | AL15: =if(AE15="YES",0,IF(AND(I15>=DATE(2022,7,1),I15<=DATE(2023,6,30)),3,IF(AND(I15>=DATE(2023,7,1),I15<=DATE(2024,6,30)),2,IF(AND(I15>=DATE(2024,7,1),I15<=DATE(2025,6,30)),1,IF(AND(I15>=DATE(2025,7,1),I15<=DATE(2026,6,30)),0,"-"))))) -> 0 | AM15: =AK15*AL15 -> 0 | AN15: {=_xlfn.xlookup(C15,'SCC Certificate Review'!C:C,'SCC Certificate Review'!F:F)} -> TRUE
A16: 12 | B16: The Waterloo Apartments | C16: 801 Waterloo Partners, LP | D16: Los Angeles | E16: Los Angeles | F16: CMFA | G16: Grant up to $10,000 | H16: 24-053 | I16: 45345 | K16: The Greg Scott Company | M16: Kingdom Development, Inc. | N16: FALSE | O16: 154 | P16: 154 | Q16: =P16/O16 -> 1 | R16: 801-809 Waterloo Street, Los Angeles, CA | S16: 23250 | T16: =COUNTIF(Parcels!A:A, A16) > 0 -> TRUE | U16: =MAXIFS(Parcels!AC:AC, Parcels!A:A, A16) > 0 -> FALSE | V16: =SUMIF(Parcels!A:A, A16, Parcels!Z:Z) -> 1360000 | W16: =SUMIF(Parcels!$A:$A, $A16, Parcels!AC:AC) -> 0 | X16: =V16*P16/O16*0.9 -> 1224000 | Y16: =IF(W16=0, X16, W16) -> 1224000 | Z16: {=_xlfn.XLOOKUP( A16, Parcels!A:A, Parcels!AL:AL)} -> 0.0118738 | AA16: =W16*Z16 -> 0 | AB16: =Y16*Z16 -> 14533.531 | AJ16: =if(F16="CMFA", if(O16<16,10000,O16*600),if(F16="CSCDA",if(33<O16<300, O16*600,if(O16>300,(180000+(O16-300)*300),20000)))) -> 92400 | AK16: =if(F16="CMFA", if(O16<26,4000,O16*150),if(F16="CSCDA",if(33<O16<300, O16*150,if(O16>300,(45000+(O16-300)*75),5000)))) -> 23100 | AL16: =if(AE16="YES",0,IF(AND(I16>=DATE(2022,7,1),I16<=DATE(2023,6,30)),3,IF(AND(I16>=DATE(2023,7,1),I16<=DATE(2024,6,30)),2,IF(AND(I16>=DATE(2024,7,1),I16<=DATE(2025,6,30)),1,IF(AND(I16>=DATE(2025,7,1),I16<=DATE(2026,6,30)),0,"-"))))) -> 2 | AM16: =AK16*AL16 -> 46200 | AN16: {=_xlfn.xlookup(C16,'SCC Certificate Review'!C:C,'SCC Certificate Review'!F:F)} -> TRUE
A17: 14 | B17: Electric Lofts Apartments | C17: Electric Lofts, LP | D17: Oakland | E17: Alameda | F17: CMFA | G17: Grant up to $10,000 | H17: 24-074 | I17: 45366 | K17: Trestle Development LLC | M17: AOF / Pacific Affordable Housing Corp | N17: FALSE | O17: 89 | P17: 40 | R17: 2415 Valdez St, Oakland, CA 94612 | S17: 13350 | T17: =COUNTIF(Parcels!A:A, A17) > 0 -> TRUE | U17: =MAXIFS(Parcels!AC:AC, Parcels!A:A, A17) > 0 -> FALSE | V17: =SUMIF(Parcels!A:A, A17, Parcels!Z:Z) -> 24257157 | W17: =SUMIF(Parcels!$A:$A, $A17, Parcels!AC:AC) -> 0 | X17: =V17*P17/O17*0.9 -> 9811883.7 | Y17: =IF(W17=0, X17, W17) -> 9811883.7 | Z17: {=_xlfn.XLOOKUP( A17, Parcels!A:A, Parcels!AL:AL)} -> 0.012779 | AA17: =W17*Z17 -> 0 | AB17: =Y17*Z17 -> 125386.06 | AD17: https://www.electriclofts.com/ | AJ17: =if(F17="CMFA", if(O17<16,10000,O17*600),if(F17="CSCDA",if(33<O17<300, O17*600,if(O17>300,(180000+(O17-300)*300),20000)))) -> 53400 | AK17: =if(F17="CMFA", if(O17<26,4000,O17*150),if(F17="CSCDA",if(33<O17<300, O17*150,if(O17>300,(45000+(O17-300)*75),5000)))) -> 13350 | AL17: =if(AE17="YES",0,IF(AND(I17>=DATE(2022,7,1),I17<=DATE(2023,6,30)),3,IF(AND(I17>=DATE(2023,7,1),I17<=DATE(2024,6,30)),2,IF(AND(I17>=DATE(2024,7,1),I17<=DATE(2025,6,30)),1,IF(AND(I17>=DATE(2025,7,1),I17<=DATE(2026,6,30)),0,"-"))))) -> 2 | AM17: =AK17*AL17 -> 26700 | AN17: {=_xlfn.xlookup(C17,'SCC Certificate Review'!C:C,'SCC Certificate Review'!F:F)} -> TRUE
A18: 13 | B18: 275 Turk Street Apartments | C18: RHI-Mosser 275 Turk LP | D18: San Francisco | E18: San Francisco | F18: CMFA | G18: Grant up to $10,000 | H18: 24-076 | I18: 45366 | J18: TRUE | K18: Mosser Capital, LLC | L18: Stars Real Estate Investment | M18: Kingdom Development, Inc. | N18: FALSE | O18: 66 | P18: 27 | R18: 275 Turk St, San Francisco, CA | S18: 9900 | T18: =COUNTIF(Parcels!A:A, A18) > 0 -> TRUE | U18: =MAXIFS(Parcels!AC:AC, Parcels!A:A, A18) > 0 -> FALSE | V18: =SUMIF(Parcels!A:A, A18, Parcels!Z:Z) -> 17116303 | W18: =SUMIF(Parcels!$A:$A, $A18, Parcels!AC:AC) -> 0 | X18: =V18*P18/O18*0.9 -> 6301911.6 | Y18: =IF(W18=0, X18, W18) -> 6301911.6 | Z18: {=_xlfn.XLOOKUP( A18, Parcels!A:A, Parcels!AL:AL)} -> 0.012 | AA18: =W18*Z18 -> 0 | AB18: =Y18*Z18 -> 75622.939 | AJ18: =if(F18="CMFA", if(O18<16,10000,O18*600),if(F18="CSCDA",if(33<O18<300, O18*600,if(O18>300,(180000+(O18-300)*300),20000)))) -> 39600 | AK18: =if(F18="CMFA", if(O18<26,4000,O18*150),if(F18="CSCDA",if(33<O18<300, O18*150,if(O18>300,(45000+(O18-300)*75),5000)))) -> 9900 | AL18: =if(AE18="YES",0,IF(AND(I18>=DATE(2022,7,1),I18<=DATE(2023,6,30)),3,IF(AND(I18>=DATE(2023,7,1),I18<=DATE(2024,6,30)),2,IF(AND(I18>=DATE(2024,7,1),I18<=DATE(2025,6,30)),1,IF(AND(I18>=DATE(2025,7,1),I18<=DATE(2026,6,30)),0,"-"))))) -> 2 | AM18: =AK18*AL18 -> 19800 | AN18: {=_xlfn.xlookup(C18,'SCC Certificate Review'!C:C,'SCC Certificate Review'!F:F)}
A19: 15 | B19: Premiere Hollywood Apartments | C19: OODB2, LP | D19: Los Angeles | E19: Los Angeles | F19: CMFA | G19: Grant up to $10,000 | H19: 24-178 | I19: 45408 | J19: TRUE | K19: Housing Diversity Corporation | M19: PEP Housing | N19: FALSE | O19: 69 | P19: 69 | Q19: =P19/O19 -> 1 | R19: 6762 Hawthorn Ave, Los Angeles, CA 90028 | S19: 10350 | T19: =COUNTIF(Parcels!A:A, A19) > 0 -> TRUE | U19: =MAXIFS(Parcels!AC:AC, Parcels!A:A, A19) > 0 -> FALSE | V19: =SUMIF(Parcels!A:A, A19, Parcels!Z:Z) -> 8706757 | W19: =SUMIF(Parcels!$A:$A, $A19, Parcels!AC:AC) -> 0 | X19: =V19*P19/O19*0.9 -> 7836081.3 | Y19: =IF(W19=0, X19, W19) -> 7836081.3 | Z19: {=_xlfn.XLOOKUP( A19, Parcels!A:A, Parcels!AL:AL)} -> 0.0118738 | AA19: =W19*Z19 -> 0 | AB19: =Y19*Z19 -> 93044.062 | AF19: 2023 | AJ19: =if(F19="CMFA", if(O19<16,10000,O19*600),if(F19="CSCDA",if(33<O19<300, O19*600,if(O19>300,(180000+(O19-300)*300),20000)))) -> 41400 | AK19: =if(F19="CMFA", if(O19<26,4000,O19*150),if(F19="CSCDA",if(33<O19<300, O19*150,if(O19>300,(45000+(O19-300)*75),5000)))) -> 10350 | AL19: =if(AE19="YES",0,IF(AND(I19>=DATE(2022,7,1),I19<=DATE(2023,6,30)),3,IF(AND(I19>=DATE(2023,7,1),I19<=DATE(2024,6,30)),2,IF(AND(I19>=DATE(2024,7,1),I19<=DATE(2025,6,30)),1,IF(AND(I19>=DATE(2025,7,1),I19<=DATE(2026,6,30)),0,"-"))))) -> 2 | AM19: =AK19*AL19 -> 20700 | AN19: {=_xlfn.xlookup(C19,'SCC Certificate Review'!C:C,'SCC Certificate Review'!F:F)}
A20: 17 | B20: 4252 Crenshaw Apartments | C20: 4252 Crenshaw LP | D20: Los Angeles | E20: Los Angeles | F20: CMFA | G20: Grant up to $10,000 | H20: 24-199 | I20: 45429 | K20: Thrive Living | L20: Magnum Real Estate Group | M20: Kingdom Development, Inc. | N20: FALSE | O20: 111 | P20: 111 | Q20: =P20/O20 -> 1 | R20: 4252 S CRENSHAW BLVD LOS ANGELES CA 90008 | S20: 16650 | T20: =COUNTIF(Parcels!A:A, A20) > 0 -> TRUE | U20: =MAXIFS(Parcels!AC:AC, Parcels!A:A, A20) > 0 -> TRUE | V20: =SUMIF(Parcels!A:A, A20, Parcels!Z:Z) -> 26914860 | W20: =SUMIF(Parcels!$A:$A, $A20, Parcels!AC:AC) -> 26914860 | X20: =V20*P20/O20*0.9 -> 24223374 | Y20: =IF(W20=0, X20, W20) -> 26914860 | Z20: {=_xlfn.XLOOKUP( A20, Parcels!A:A, Parcels!AL:AL)} -> 0.0118738 | AA20: =W20*Z20 -> 319581.66 | AB20: =Y20*Z20 -> 319581.66 | AE20: NO | AF20: 2020 | AJ20: =if(F20="CMFA", if(O20<16,10000,O20*600),if(F20="CSCDA",if(33<O20<300, O20*600,if(O20>300,(180000+(O20-300)*300),20000)))) -> 66600 | AK20: =if(F20="CMFA", if(O20<26,4000,O20*150),if(F20="CSCDA",if(33<O20<300, O20*150,if(O20>300,(45000+(O20-300)*75),5000)))) -> 16650 | AL20: =if(AE20="YES",0,IF(AND(I20>=DATE(2022,7,1),I20<=DATE(2023,6,30)),3,IF(AND(I20>=DATE(2023,7,1),I20<=DATE(2024,6,30)),2,IF(AND(I20>=DATE(2024,7,1),I20<=DATE(2025,6,30)),1,IF(AND(I20>=DATE(2025,7,1),I20<=DATE(2026,6,30)),0,"-"))))) -> 2 | AM20: =AK20*AL20 -> 33300 | AN20: {=_xlfn.xlookup(C20,'SCC Certificate Review'!C:C,'SCC Certificate Review'!F:F)} -> TRUE
A21: 16 | B21: Montessa Apartments | C21: Affordable Housing Alliance II, Inc. dba Integrity Housing | D21: Vacaville | E21: Solano | F21: CMFA | G21: Grant up to $10,000 | H21: 24-200 | I21: 45429 | K21: Ascenda Capital | M21: Integrity Housing | N21: FALSE | O21: 169 | P21: 58 | R21: 343 Moon River Pl, Vacaville, CA 95687 | S21: 8700 | T21: =COUNTIF(Parcels!A:A, A21) > 0 -> TRUE | U21: =MAXIFS(Parcels!AC:AC, Parcels!A:A, A21) > 0 -> FALSE | V21: =SUMIF(Parcels!A:A, A21, Parcels!Z:Z) -> 1333447 | W21: =SUMIF(Parcels!$A:$A, $A21, Parcels!AC:AC) -> 0 | X21: =V21*P21/O21*0.9 -> 411869.43 | Y21: =IF(W21=0, X21, W21) -> 411869.43 | Z21: {=_xlfn.XLOOKUP( A21, Parcels!A:A, Parcels!AL:AL)} -> 0.0117033 | AA21: =W21*Z21 -> 0 | AB21: =Y21*Z21 -> 4820.2315 | AE21: YES | AJ21: =if(F21="CMFA", if(O21<16,10000,O21*600),if(F21="CSCDA",if(33<O21<300, O21*600,if(O21>300,(180000+(O21-300)*300),20000)))) -> 101400 | AK21: =if(F21="CMFA", if(O21<26,4000,O21*150),if(F21="CSCDA",if(33<O21<300, O21*150,if(O21>300,(45000+(O21-300)*75),5000)))) -> 25350 | AL21: =if(AE21="YES",0,IF(AND(I21>=DATE(2022,7,1),I21<=DATE(2023,6,30)),3,IF(AND(I21>=DATE(2023,7,1),I21<=DATE(2024,6,30)),2,IF(AND(I21>=DATE(2024,7,1),I21<=DATE(2025,6,30)),1,IF(AND(I21>=DATE(2025,7,1),I21<=DATE(2026,6,30)),0,"-"))))) -> 0 | AM21: =AK21*AL21 -> 0 | AN21: {=_xlfn.xlookup(C21,'SCC Certificate Review'!C:C,'SCC Certificate Review'!F:F)}
A22: 18 | B22: Fallbrook Trail Apartments | C22: 1735 South Mission LP | D22: San Diego | E22: San Diego | F22: CMFA | G22: Grant up to $10,000 | H22: 24-219 | I22: 45450 | K22: AOF | L22: Pacific Affordable Housing Corp | M22: Pacific Affordable Housing Corp | N22: FALSE | O22: 103 | P22: 102 | R22: 1735 S Mission Rd, Fallbrook, CA 92028 | S22: 15300 | T22: =COUNTIF(Parcels!A:A, A22) > 0 -> TRUE | U22: =MAXIFS(Parcels!AC:AC, Parcels!A:A, A22) > 0 -> FALSE | V22: =SUMIF(Parcels!A:A, A22, Parcels!Z:Z) -> 32460480 | W22: =SUMIF(Parcels!$A:$A, $A22, Parcels!AC:AC) -> 0 | X22: =V22*P22/O22*0.9 -> 28930797 | Y22: =IF(W22=0, X22, W22) -> 28930797 | Z22: {=_xlfn.XLOOKUP( A22, Parcels!A:A, Parcels!AL:AL)} -> 0.010783 | AA22: =W22*Z22 -> 0 | AB22: =Y22*Z22 -> 311960.78 | AF22: 2021 | AJ22: =if(F22="CMFA", if(O22<16,10000,O22*600),if(F22="CSCDA",if(33<O22<300, O22*600,if(O22>300,(180000+(O22-300)*300),20000)))) -> 61800 | AK22: =if(F22="CMFA", if(O22<26,4000,O22*150),if(F22="CSCDA",if(33<O22<300, O22*150,if(O22>300,(45000+(O22-300)*75),5000)))) -> 15450 | AL22: =if(AE22="YES",0,IF(AND(I22>=DATE(2022,7,1),I22<=DATE(2023,6,30)),3,IF(AND(I22>=DATE(2023,7,1),I22<=DATE(2024,6,30)),2,IF(AND(I22>=DATE(2024,7,1),I22<=DATE(2025,6,30)),1,IF(AND(I22>=DATE(2025,7,1),I22<=DATE(2026,6,30)),0,"-"))))) -> 2 | AM22: =AK22*AL22 -> 30900 | AN22: {=_xlfn.xlookup(C22,'SCC Certificate Review'!C:C,'SCC Certificate Review'!F:F)} -> TRUE
A23: 20 | B23: Pinetree Terrace Apartments | C23: Hacienda Investors LP | D23: Los Angeles | E23: Los Angeles | F23: CMFA | G23: Grant up to $10,000 | H23: 24-220 | I23: 45450 | K23: GHC Housing Partners | M23: Foundation for Affordable Housing | N23: FALSE | O23: 58 | P23: 58 | Q23: =P23/O23 -> 1 | R23: 7940 Reseda Boulevard, Reseda, CA | S23: 8700 | T23: =COUNTIF(Parcels!A:A, A23) > 0 -> TRUE | U23: =MAXIFS(Parcels!AC:AC, Parcels!A:A, A23) > 0 -> TRUE | V23: =SUMIF(Parcels!A:A, A23, Parcels!Z:Z) -> 17952000 | W23: =SUMIF(Parcels!$A:$A, $A23, Parcels!AC:AC) -> 15786989 | X23: =V23*P23/O23*0.9 -> 16156800 | Y23: =IF(W23=0, X23, W23) -> 15786989 | Z23: {=_xlfn.XLOOKUP( A23, Parcels!A:A, Parcels!AL:AL)} -> 0.0118738 | AA23: =W23*Z23 -> 187451.55 | AB23: =Y23*Z23 -> 187451.55 | AG23: 17600000 | AH23: 45471 | AJ23: =if(F23="CMFA", if(O23<16,10000,O23*600),if(F23="CSCDA",if(33<O23<300, O23*600,if(O23>300,(180000+(O23-300)*300),20000)))) -> 34800 | AK23: =if(F23="CMFA", if(O23<26,4000,O23*150),if(F23="CSCDA",if(33<O23<300, O23*150,if(O23>300,(45000+(O23-300)*75),5000)))) -> 8700 | AL23: =if(AE23="YES",0,IF(AND(I23>=DATE(2022,7,1),I23<=DATE(2023,6,30)),3,IF(AND(I23>=DATE(2023,7,1),I23<=DATE(2024,6,30)),2,IF(AND(I23>=DATE(2024,7,1),I23<=DATE(2025,6,30)),1,IF(AND(I23>=DATE(2025,7,1),I23<=DATE(2026,6,30)),0,"-"))))) -> 2 | AM23: =AK23*AL23 -> 17400 | AN23: {=_xlfn.xlookup(C23,'SCC Certificate Review'!C:C,'SCC Certificate Review'!F:F)} -> TRUE
A24: 21 | B24: Windmere Court Apartments | C24: Hacienda Investors LP | D24: Los Angeles | E24: Los Angeles | F24: CMFA | G24: Grant up to $10,000 | H24: 24-221 | I24: 45450 | K24: GHC Housing Partners | M24: Foundation for Affordable Housing | N24: FALSE | O24: 52 | P24: 52 | Q24: =P24/O24 -> 1 | R24: 18325 Saticoy St, Reseda, CA 91335 | S24: 7800 | T24: =COUNTIF(Parcels!A:A, A24) > 0 -> TRUE | U24: =MAXIFS(Parcels!AC:AC, Parcels!A:A, A24) > 0 -> TRUE | V24: =SUMIF(Parcels!A:A, A24, Parcels!Z:Z) -> 16626000 | W24: =SUMIF(Parcels!$A:$A, $A24, Parcels!AC:AC) -> 16306781 | X24: =V24*P24/O24*0.9 -> 14963400 | Y24: =IF(W24=0, X24, W24) -> 16306781 | Z24: {=_xlfn.XLOOKUP( A24, Parcels!A:A, Parcels!AL:AL)} -> 0.0118738 | AA24: =W24*Z24 -> 193623.46 | AB24: =Y24*Z24 -> 193623.46 | AG24: 16300000 | AH24: 45456 | AJ24: =if(F24="CMFA", if(O24<16,10000,O24*600),if(F24="CSCDA",if(33<O24<300, O24*600,if(O24>300,(180000+(O24-300)*300),20000)))) -> 31200 | AK24: =if(F24="CMFA", if(O24<26,4000,O24*150),if(F24="CSCDA",if(33<O24<300, O24*150,if(O24>300,(45000+(O24-300)*75),5000)))) -> 7800 | AL24: =if(AE24="YES",0,IF(AND(I24>=DATE(2022,7,1),I24<=DATE(2023,6,30)),3,IF(AND(I24>=DATE(2023,7,1),I24<=DATE(2024,6,30)),2,IF(AND(I24>=DATE(2024,7,1),I24<=DATE(2025,6,30)),1,IF(AND(I24>=DATE(2025,7,1),I24<=DATE(2026,6,30)),0,"-"))))) -> 2 | AM24: =AK24*AL24 -> 15600 | AN24: {=_xlfn.xlookup(C24,'SCC Certificate Review'!C:C,'SCC Certificate Review'!F:F)} -> TRUE
A25: 19 | B25: The Arbors Apartments | C25: Post Arbors Santa Ana LP | D25: Santa Ana | E25: Orange | F25: CMFA | G25: Grant up to $10,000 | H25: 24-222 | I25: 45450 | K25: Ascenda Capital | L25: Post Investment Group | M25: Integrity Housing | N25: FALSE | O25: 160 | P25: 160 | R25: 1100-1200 E. Fairhaven Avenue, Santa Ana, CA | S25: 24000 | T25: =COUNTIF(Parcels!A:A, A25) > 0 -> TRUE | U25: =MAXIFS(Parcels!AC:AC, Parcels!A:A, A25) > 0 -> FALSE | V25: =SUMIF(Parcels!A:A, A25, Parcels!Z:Z) -> 40750000 | W25: =SUMIF(Parcels!$A:$A, $A25, Parcels!AC:AC) -> 0 | X25: =V25*P25/O25*0.9 -> 36675000 | Y25: =IF(W25=0, X25, W25) -> 36675000 | Z25: {=_xlfn.XLOOKUP( A25, Parcels!A:A, Parcels!AL:AL)} -> 0.011195 | AA25: =W25*Z25 -> 0 | AB25: =Y25*Z25 -> 410576.62 | AF25: 1969 | AJ25: =if(F25="CMFA", if(O25<16,10000,O25*600),if(F25="CSCDA",if(33<O25<300, O25*600,if(O25>300,(180000+(O25-300)*300),20000)))) -> 96000 | AK25: =if(F25="CMFA", if(O25<26,4000,O25*150),if(F25="CSCDA",if(33<O25<300, O25*150,if(O25>300,(45000+(O25-300)*75),5000)))) -> 24000 | AL25: =if(AE25="YES",0,IF(AND(I25>=DATE(2022,7,1),I25<=DATE(2023,6,30)),3,IF(AND(I25>=DATE(2023,7,1),I25<=DATE(2024,6,30)),2,IF(AND(I25>=DATE(2024,7,1),I25<=DATE(2025,6,30)),1,IF(AND(I25>=DATE(2025,7,1),I25<=DATE(2026,6,30)),0,"-"))))) -> 2 | AM25: =AK25*AL25 -> 48000 | AN25: {=_xlfn.xlookup(C25,'SCC Certificate Review'!C:C,'SCC Certificate Review'!F:F)} -> TRUE
A26: 22 | B26: Seville Gardens Apartments | C26: BG Apartments Investors LP | D26: Huntington Park | E26: Los Angeles | F26: CMFA | G26: Grant up to $10,000 | H26: 24-223 | I26: 45450 | K26: GHC Housing Partners | M26: Foundation for Affordable Housing | N26: FALSE | O26: 225 | P26: 225 | Q26: =P26/O26 -> 1 | R26: 2701 Randolph St., Huntington Park, CA | S26: 33750 | T26: =COUNTIF(Parcels!A:A, A26) > 0 -> TRUE | U26: =MAXIFS(Parcels!AC:AC, Parcels!A:A, A26) > 0 -> TRUE | V26: =SUMIF(Parcels!A:A, A26, Parcels!Z:Z) -> 34425000 | W26: =SUMIF(Parcels!$A:$A, $A26, Parcels!AC:AC) -> 31825913 | X26: =V26*P26/O26*0.9 -> 30982500 | Y26: =IF(W26=0, X26, W26) -> 31825913 | Z26: {=_xlfn.XLOOKUP( A26, Parcels!A:A, Parcels!AL:AL)} -> 0.01385148 | AA26: =W26*Z26 -> 440836 | AB26: =Y26*Z26 -> 440836 | AF26: 1989 | AJ26: =if(F26="CMFA", if(O26<16,10000,O26*600),if(F26="CSCDA",if(33<O26<300, O26*600,if(O26>300,(180000+(O26-300)*300),20000)))) -> 135000 | AK26: =if(F26="CMFA", if(O26<26,4000,O26*150),if(F26="CSCDA",if(33<O26<300, O26*150,if(O26>300,(45000+(O26-300)*75),5000)))) -> 33750 | AL26: =if(AE26="YES",0,IF(AND(I26>=DATE(2022,7,1),I26<=DATE(2023,6,30)),3,IF(AND(I26>=DATE(2023,7,1),I26<=DATE(2024,6,30)),2,IF(AND(I26>=DATE(2024,7,1),I26<=DATE(2025,6,30)),1,IF(AND(I26>=DATE(2025,7,1),I26<=DATE(2026,6,30)),0,"-"))))) -> 2 | AM26: =AK26*AL26 -> 67500 | AN26: {=_xlfn.xlookup(C26,'SCC Certificate Review'!C:C,'SCC Certificate Review'!F:F)} -> TRUE
A27: 23 | B27: Harbour Residences Apartments | C27: RMG Fee Avalon, LP | D27: Los Angeles | E27: Los Angeles | F27: CMFA | G27: Grant up to $10,000 | H27: 24-252 | I27: 45492 | J27: TRUE | K27: RMG Housing | M27: DECRO Corporation | N27: FALSE | O27: 74 | P27: 74 | Q27: =P27/O27 -> 1 | R27: 445 N. Avalon Boulevard, Los Angeles, CA | S27: 11100 | T27: =COUNTIF(Parcels!A:A, A27) > 0 -> TRUE | U27: =MAXIFS(Parcels!AC:AC, Parcels!A:A, A27) > 0 -> FALSE | V27: =SUMIF(Parcels!A:A, A27, Parcels!Z:Z) -> 8899678 | W27: =SUMIF(Parcels!$A:$A, $A27, Parcels!AC:AC) -> 0 | X27: =V27*P27/O27*0.9 -> 8009710.2 | Y27: =IF(W27=0, X27, W27) -> 8009710.2 | Z27: {=_xlfn.XLOOKUP( A27, Parcels!A:A, Parcels!AL:AL)} -> 0.0118738 | AA27: =W27*Z27 -> 0 | AB27: =Y27*Z27 -> 95105.697 | AE27: YES | AJ27: =if(F27="CMFA", if(O27<16,10000,O27*600),if(F27="CSCDA",if(33<O27<300, O27*600,if(O27>300,(180000+(O27-300)*300),20000)))) -> 44400 | AK27: =if(F27="CMFA", if(O27<26,4000,O27*150),if(F27="CSCDA",if(33<O27<300, O27*150,if(O27>300,(45000+(O27-300)*75),5000)))) -> 11100 | AL27: =if(AE27="YES",0,IF(AND(I27>=DATE(2022,7,1),I27<=DATE(2023,6,30)),3,IF(AND(I27>=DATE(2023,7,1),I27<=DATE(2024,6,30)),2,IF(AND(I27>=DATE(2024,7,1),I27<=DATE(2025,6,30)),1,IF(AND(I27>=DATE(2025,7,1),I27<=DATE(2026,6,30)),0,"-"))))) -> 0 | AM27: =AK27*AL27 -> 0 | AN27: {=_xlfn.xlookup(C27,'SCC Certificate Review'!C:C,'SCC Certificate Review'!F:F)}
A28: 24 | B28: 4209 Western Avenue Apartments | C28: BIF NON OZ 4209 WESTERN AVE, LP | D28: Los Angeles | E28: Los Angeles | F28: CMFA | G28: Grant up to $10,000 | H28: 24-253 | I28: 45492 | K28: SoLa Impact, LLC | M28: Housing on Merit | N28: FALSE | O28: 25 | P28: 24 | Q28: =P28/O28 -> 0.96 | R28: 4209 S Western Ave, Los Angeles, CA 90062 | S28: 3600 | T28: =COUNTIF(Parcels!A:A, A28) > 0 -> TRUE | U28: =MAXIFS(Parcels!AC:AC, Parcels!A:A, A28) > 0 -> TRUE | V28: =SUMIF(Parcels!A:A, A28, Parcels!Z:Z) -> 10924200 | W28: =SUMIF(Parcels!$A:$A, $A28, Parcels!AC:AC) -> 10903361 | X28: =V28*P28/O28*0.9 -> 9438508.8 | Y28: =IF(W28=0, X28, W28) -> 10903361 | Z28: {=_xlfn.XLOOKUP( A28, Parcels!A:A, Parcels!AL:AL)} -> 0.0118738 | AA28: =W28*Z28 -> 129464.33 | AB28: =Y28*Z28 -> 129464.33 | AJ28: =if(F28="CMFA", if(O28<16,10000,O28*600),if(F28="CSCDA",if(33<O28<300, O28*600,if(O28>300,(180000+(O28-300)*300),20000)))) -> 15000 | AK28: =if(F28="CMFA", if(O28<26,4000,O28*150),if(F28="CSCDA",if(33<O28<300, O28*150,if(O28>300,(45000+(O28-300)*75),5000)))) -> 4000 | AL28: =if(AE28="YES",0,IF(AND(I28>=DATE(2022,7,1),I28<=DATE(2023,6,30)),3,IF(AND(I28>=DATE(2023,7,1),I28<=DATE(2024,6,30)),2,IF(AND(I28>=DATE(2024,7,1),I28<=DATE(2025,6,30)),1,IF(AND(I28>=DATE(2025,7,1),I28<=DATE(2026,6,30)),0,"-"))))) -> 1 | AM28: =AK28*AL28 -> 4000 | AN28: {=_xlfn.xlookup(C28,'SCC Certificate Review'!C:C,'SCC Certificate Review'!F:F)} -> TRUE
A29: 25 | B29: 1130 Martin Luther King Jr. Blvd Apartments | C29: BIF NON OZ 1100 MLK BLK, LP | D29: Los Angeles | E29: Los Angeles | F29: CMFA | H29: 24-254 | I29: 45492 | K29: SoLa Impact, LLC | M29: Housing on Merit | N29: FALSE | O29: 29 | P29: 28 | Q29: =P29/O29 -> 0.96551724 | R29: 1130 W Martin Luther King Jr Blvd, Los Angeles, CA 90037 | S29: 4200 | T29: =COUNTIF(Parcels!A:A, A29) > 0 -> TRUE | U29: =MAXIFS(Parcels!AC:AC, Parcels!A:A, A29) > 0 -> TRUE | V29: =SUMIF(Parcels!A:A, A29, Parcels!Z:Z) -> 12796920 | W29: =SUMIF(Parcels!$A:$A, $A29, Parcels!AC:AC) -> 12776081 | X29: =V29*P29/O29*0.9 -> 11120082 | Y29: =IF(W29=0, X29, W29) -> 12776081 | Z29: {=_xlfn.XLOOKUP( A29, Parcels!A:A, Parcels!AL:AL)} -> 0.0118738 | AA29: =W29*Z29 -> 151700.63 | AB29: =Y29*Z29 -> 151700.63 | AJ29: =if(F29="CMFA", if(O29<16,10000,O29*600),if(F29="CSCDA",if(33<O29<300, O29*600,if(O29>300,(180000+(O29-300)*300),20000)))) -> 17400 | AK29: =if(F29="CMFA", if(O29<26,4000,O29*150),if(F29="CSCDA",if(33<O29<300, O29*150,if(O29>300,(45000+(O29-300)*75),5000)))) -> 4350 | AL29: =if(AE29="YES",0,IF(AND(I29>=DATE(2022,7,1),I29<=DATE(2023,6,30)),3,IF(AND(I29>=DATE(2023,7,1),I29<=DATE(2024,6,30)),2,IF(AND(I29>=DATE(2024,7,1),I29<=DATE(2025,6,30)),1,IF(AND(I29>=DATE(2025,7,1),I29<=DATE(2026,6,30)),0,"-"))))) -> 1 | AM29: =AK29*AL29 -> 4350 | AN29: {=_xlfn.xlookup(C29,'SCC Certificate Review'!C:C,'SCC Certificate Review'!F:F)} -> TRUE
A30: 34 | B30: Appian Terrace Apartments | C30: APPIAN LP | D30: El Sobrante | E30: Contra Costa | F30: CMFA | G30: Grant up to $10,000 | H30: 24-277 | I30: 45513 | K30: Tesseract Capital Group | M30: Housing on Merit | N30: FALSE | O30: 41 | P30: 41 | R30: 4481 Appian Way, El Sobrante, CA 94803 | S30: 6150 | T30: =COUNTIF(Parcels!A:A, A30) > 0 -> TRUE | U30: =MAXIFS(Parcels!AC:AC, Parcels!A:A, A30) > 0 -> FALSE | V30: =SUMIF(Parcels!A:A, A30, Parcels!Z:Z) -> 9977564 | W30: =SUMIF(Parcels!$A:$A, $A30, Parcels!AC:AC) -> 0 | X30: =V30*P30/O30*0.9 -> 8979807.6 | Y30: =IF(W30=0, X30, W30) -> 8979807.6 | Z30: {=_xlfn.XLOOKUP( A30, Parcels!A:A, Parcels!AL:AL)} -> 0.012792 | AA30: =W30*Z30 -> 0 | AB30: =Y30*Z30 -> 114869.7 | AJ30: =if(F30="CMFA", if(O30<16,10000,O30*600),if(F30="CSCDA",if(33<O30<300, O30*600,if(O30>300,(180000+(O30-300)*300),20000)))) -> 24600 | AK30: =if(F30="CMFA", if(O30<26,4000,O30*150),if(F30="CSCDA",if(33<O30<300, O30*150,if(O30>300,(45000+(O30-300)*75),5000)))) -> 6150 | AL30: =if(AE30="YES",0,IF(AND(I30>=DATE(2022,7,1),I30<=DATE(2023,6,30)),3,IF(AND(I30>=DATE(2023,7,1),I30<=DATE(2024,6,30)),2,IF(AND(I30>=DATE(2024,7,1),I30<=DATE(2025,6,30)),1,IF(AND(I30>=DATE(2025,7,1),I30<=DATE(2026,6,30)),0,"-"))))) -> 1 | AM30: =AK30*AL30 -> 6150 | AN30: {=_xlfn.xlookup(C30,'SCC Certificate Review'!C:C,'SCC Certificate Review'!F:F)} -> TRUE
A31: 35 | B31: Sierra Park Apartments | C31: Sierra Park LP, a California Limited Partnership | D31: Unincorporated | E31: Sacramento | F31: CMFA | G31: Grant up to $10,000 | H31: 24-278 | I31: 45513 | K31: Tesseract Capital Group | M31: Housing on Merit | N31: FALSE | O31: 104 | P31: 104 | R31: 4930 Polk St, North Highlands, CA 95660 | S31: 15600 | T31: =COUNTIF(Parcels!A:A, A31) > 0 -> TRUE | U31: =MAXIFS(Parcels!AC:AC, Parcels!A:A, A31) > 0 -> TRUE | V31: =SUMIF(Parcels!A:A, A31, Parcels!Z:Z) -> 25646900 | W31: =SUMIF(Parcels!$A:$A, $A31, Parcels!AC:AC) -> 23179668 | X31: =V31*P31/O31*0.9 -> 23082210 | Y31: =IF(W31=0, X31, W31) -> 23179668 | Z31: {=_xlfn.XLOOKUP( A31, Parcels!A:A, Parcels!AL:AL)} -> 0.011785 | AA31: =W31*Z31 -> 273172.39 | AB31: =Y31*Z31 -> 273172.39 | AJ31: =if(F31="CMFA", if(O31<16,10000,O31*600),if(F31="CSCDA",if(33<O31<300, O31*600,if(O31>300,(180000+(O31-300)*300),20000)))) -> 62400 | AK31: =if(F31="CMFA", if(O31<26,4000,O31*150),if(F31="CSCDA",if(33<O31<300, O31*150,if(O31>300,(45000+(O31-300)*75),5000)))) -> 15600 | AL31: =if(AE31="YES",0,IF(AND(I31>=DATE(2022,7,1),I31<=DATE(2023,6,30)),3,IF(AND(I31>=DATE(2023,7,1),I31<=DATE(2024,6,30)),2,IF(AND(I31>=DATE(2024,7,1),I31<=DATE(2025,6,30)),1,IF(AND(I31>=DATE(2025,7,1),I31<=DATE(2026,6,30)),0,"-"))))) -> 1 | AM31: =AK31*AL31 -> 15600 | AN31: {=_xlfn.xlookup(C31,'SCC Certificate Review'!C:C,'SCC Certificate Review'!F:F)} -> TRUE
A32: 33 | B32: 7524 S. Hoover St. Apartments | C32: BIF NON OZ 7524 S HOOVER ST, LP | D32: Los Angeles | E32: Los Angeles | F32: CMFA | G32: Grant up to $10,000 | H32: 24-279 | I32: 45513 | K32: SoLa Impact, LLC | M32: Housing on Merit | N32: TRUE | O32: 79 | P32: 48 | Q32: =P32/O32 -> 0.60759494 | R32: 7518 S. Hoover, Los Angeles, CA | S32: 11850 | T32: =COUNTIF(Parcels!A:A, A32) > 0 -> TRUE | U32: =MAXIFS(Parcels!AC:AC, Parcels!A:A, A32) > 0 -> FALSE | V32: =SUMIF(Parcels!A:A, A32, Parcels!Z:Z) -> 0 | W32: =SUMIF(Parcels!$A:$A, $A32, Parcels!AC:AC) -> 0 | X32: =V32*P32/O32*0.9 -> 0 | Y32: =IF(W32=0, X32, W32) -> 0 | Z32: {=_xlfn.XLOOKUP( A32, Parcels!A:A, Parcels!AL:AL)} -> 0.0118738 | AA32: =W32*Z32 -> 0 | AB32: =Y32*Z32 -> 0 | AE32: YES | AJ32: =if(F32="CMFA", if(O32<16,10000,O32*600),if(F32="CSCDA",if(33<O32<300, O32*600,if(O32>300,(180000+(O32-300)*300),20000)))) -> 47400 | AK32: =if(F32="CMFA", if(O32<26,4000,O32*150),if(F32="CSCDA",if(33<O32<300, O32*150,if(O32>300,(45000+(O32-300)*75),5000)))) -> 11850 | AL32: =if(AE32="YES",0,IF(AND(I32>=DATE(2022,7,1),I32<=DATE(2023,6,30)),3,IF(AND(I32>=DATE(2023,7,1),I32<=DATE(2024,6,30)),2,IF(AND(I32>=DATE(2024,7,1),I32<=DATE(2025,6,30)),1,IF(AND(I32>=DATE(2025,7,1),I32<=DATE(2026,6,30)),0,"-"))))) -> 0 | AM32: =AK32*AL32 -> 0 | AN32: {=_xlfn.xlookup(C32,'SCC Certificate Review'!C:C,'SCC Certificate Review'!F:F)}
A33: 27 | B33: Santa Monica Portfolio A Apartments | C33: GC 1422-1428 6th, LP | D33: Santa Monica | E33: Los Angeles | F33: CMFA | G33: Grant up to $10,000 | H33: 24-280 | I33: 45513 | K33: Gortikov Capital | M33: Kingdom Development, Inc. | N33: FALSE | O33: =28+24 -> 52 | P33: 32 | Q33: =P33/O33 -> 0.61538462 | R33: 1422-1428 6th St., Santa Monica, CA | S33: 4800 | T33: =COUNTIF(Parcels!A:A, A33) > 0 -> TRUE | U33: =MAXIFS(Parcels!AC:AC, Parcels!A:A, A33) > 0 -> TRUE | V33: =SUMIF(Parcels!A:A, A33, Parcels!Z:Z) -> 17170000 | W33: =SUMIF(Parcels!$A:$A, $A33, Parcels!AC:AC) -> 4062807 | X33: =V33*P33/O33*0.9 -> 9509538.5 | Y33: =IF(W33=0, X33, W33) -> 4062807 | Z33: {=_xlfn.XLOOKUP( A33, Parcels!A:A, Parcels!AL:AL)} -> 0.01203757 | AA33: =W33*Z33 -> 48906.324 | AB33: =Y33*Z33 -> 48906.324 | AC33: https://www.1422on6th.com/ | AE33: NO | AF33: 1997 | AG33: 17170000 | AH33: 45547 | AJ33: =if(F33="CMFA", if(O33<16,10000,O33*600),if(F33="CSCDA",if(33<O33<300, O33*600,if(O33>300,(180000+(O33-300)*300),20000)))) -> 31200 | AK33: =if(F33="CMFA", if(O33<26,4000,O33*150),if(F33="CSCDA",if(33<O33<300, O33*150,if(O33>300,(45000+(O33-300)*75),5000)))) -> 7800 | AL33: =if(AE33="YES",0,IF(AND(I33>=DATE(2022,7,1),I33<=DATE(2023,6,30)),3,IF(AND(I33>=DATE(2023,7,1),I33<=DATE(2024,6,30)),2,IF(AND(I33>=DATE(2024,7,1),I33<=DATE(2025,6,30)),1,IF(AND(I33>=DATE(2025,7,1),I33<=DATE(2026,6,30)),0,"-"))))) -> 1 | AM33: =AK33*AL33 -> 7800 | AN33: {=_xlfn.xlookup(C33,'SCC Certificate Review'!C:C,'SCC Certificate Review'!F:F)} -> TRUE
A34: 28 | B34: Santa Monica Portfolio B Apartments | C34: GC 1422-1432 7th, LP | D34: Santa Monica | E34: Los Angeles | F34: CMFA | G34: Grant up to $10,000 | H34: 24-281 | I34: 45513 | K34: Gortikov Capital | M34: Kingdom Development, Inc. | N34: FALSE | O34: =28+2*22 -> 72 | P34: 49 | Q34: =P34/O34 -> 0.68055556 | R34: 1422-1432 7th, Santa Monica, CA | S34: 7350 | T34: =COUNTIF(Parcels!A:A, A34) > 0 -> TRUE | U34: =MAXIFS(Parcels!AC:AC, Parcels!A:A, A34) > 0 -> TRUE | V34: =SUMIF(Parcels!A:A, A34, Parcels!Z:Z) -> 23070000 | W34: =SUMIF(Parcels!$A:$A, $A34, Parcels!AC:AC) -> 10578326 | X34: =V34*P34/O34*0.9 -> 14130375 | Y34: =IF(W34=0, X34, W34) -> 10578326 | Z34: {=_xlfn.XLOOKUP( A34, Parcels!A:A, Parcels!AL:AL)} -> 0.01203757 | AA34: =W34*Z34 -> 127337.34 | AB34: =Y34*Z34 -> 127337.34 | AJ34: =if(F34="CMFA", if(O34<16,10000,O34*600),"-") -> 43200 | AK34: =if(F34="CMFA", if(O34<26,4000,O34*150),"-") -> 10800 | AL34: =IF(AND(I34>=DATE(2022,7,1),I34<=DATE(2023,6,30)),3,IF(AND(I34>=DATE(2023,7,1),I34<=DATE(2024,6,30)),2,IF(AND(I34>=DATE(2024,7,1),I34<=DATE(2025,6,30)),1,IF(AND(I34>=DATE(2025,7,1),I34<=DATE(2026,6,30)),0,"-")))) -> 1 | AM34: =AK34*AL34 -> 10800 | AN34: {=_xlfn.xlookup(C34,'SCC Certificate Review'!C:C,'SCC Certificate Review'!F:F)} -> TRUE
A35: 29 | B35: Santa Monica Portfolio C Apartments | C35: GC 1423-1425 6th, LP | D35: Santa Monica | E35: Los Angeles | F35: CMFA | G35: Grant up to $10,000 | H35: 24-282 | I35: 45513 | K35: Gortikov Capital | M35: Kingdom Development, Inc. | N35: FALSE | O35: 48 | P35: 29 | Q35: =P35/O35 -> 0.60416667 | R35: 1423-1425 6th, Santa Monica, CA | S35: 4350 | T35: =COUNTIF(Parcels!A:A, A35) > 0 -> TRUE | U35: =MAXIFS(Parcels!AC:AC, Parcels!A:A, A35) > 0 -> TRUE | V35: =SUMIF(Parcels!A:A, A35, Parcels!Z:Z) -> 20900000 | W35: =SUMIF(Parcels!$A:$A, $A35, Parcels!AC:AC) -> 10886810 | X35: =V35*P35/O35*0.9 -> 11364375 | Y35: =IF(W35=0, X35, W35) -> 10886810 | Z35: {=_xlfn.XLOOKUP( A35, Parcels!A:A, Parcels!AL:AL)} -> 0.01203757 | AA35: =W35*Z35 -> 131050.74 | AB35: =Y35*Z35 -> 131050.74 | AJ35: =if(F35="CMFA", if(O35<16,10000,O35*600),if(F35="CSCDA",if(33<O35<300, O35*600,if(O35>300,(180000+(O35-300)*300),20000)))) -> 28800 | AK35: =if(F35="CMFA", if(O35<26,4000,O35*150),if(F35="CSCDA",if(33<O35<300, O35*150,if(O35>300,(45000+(O35-300)*75),5000)))) -> 7200 | AL35: =if(AE35="YES",0,IF(AND(I35>=DATE(2022,7,1),I35<=DATE(2023,6,30)),3,IF(AND(I35>=DATE(2023,7,1),I35<=DATE(2024,6,30)),2,IF(AND(I35>=DATE(2024,7,1),I35<=DATE(2025,6,30)),1,IF(AND(I35>=DATE(2025,7,1),I35<=DATE(2026,6,30)),0,"-"))))) -> 1 | AM35: =AK35*AL35 -> 7200 | AN35: {=_xlfn.xlookup(C35,'SCC Certificate Review'!C:C,'SCC Certificate Review'!F:F)} -> TRUE
A36: 30 | B36: Santa Monica Portfolio D Apartments | C36: GC 1522 6th, LP | D36: Santa Monica | E36: Los Angeles | F36: CMFA | G36: Grant up to $10,000 | H36: 24-283 | I36: 45513 | K36: Gortikov Capital | M36: Kingdom Development, Inc. | N36: FALSE | O36: 26 | P36: 25 | Q36: =P36/O36 -> 0.96153846 | R36: 1522 6th St, Santa Monica, CA | S36: 3750 | T36: =COUNTIF(Parcels!A:A, A36) > 0 -> TRUE | U36: =MAXIFS(Parcels!AC:AC, Parcels!A:A, A36) > 0 -> TRUE | V36: =SUMIF(Parcels!A:A, A36, Parcels!Z:Z) -> 7050000 | W36: =SUMIF(Parcels!$A:$A, $A36, Parcels!AC:AC) -> 3659058 | X36: =V36*P36/O36*0.9 -> 6100961.5 | Y36: =IF(W36=0, X36, W36) -> 3659058 | Z36: {=_xlfn.XLOOKUP( A36, Parcels!A:A, Parcels!AL:AL)} -> 0.01203757 | AA36: =W36*Z36 -> 44046.167 | AB36: =Y36*Z36 -> 44046.167 | AF36: 2004 | AJ36: =if(F36="CMFA", if(O36<16,10000,O36*600),if(F36="CSCDA",if(33<O36<300, O36*600,if(O36>300,(180000+(O36-300)*300),20000)))) -> 15600 | AK36: =if(F36="CMFA", if(O36<26,4000,O36*150),if(F36="CSCDA",if(33<O36<300, O36*150,if(O36>300,(45000+(O36-300)*75),5000)))) -> 3900 | AL36: =if(AE36="YES",0,IF(AND(I36>=DATE(2022,7,1),I36<=DATE(2023,6,30)),3,IF(AND(I36>=DATE(2023,7,1),I36<=DATE(2024,6,30)),2,IF(AND(I36>=DATE(2024,7,1),I36<=DATE(2025,6,30)),1,IF(AND(I36>=DATE(2025,7,1),I36<=DATE(2026,6,30)),0,"-"))))) -> 1 | AM36: =AK36*AL36 -> 3900 | AN36: {=_xlfn.xlookup(C36,'SCC Certificate Review'!C:C,'SCC Certificate Review'!F:F)} -> TRUE
A37: 31 | B37: Santa Monica Portfolio E Apartments | C37: GC 1537 7th, LP | D37: Santa Monica | E37: Los Angeles | F37: CMFA | G37: Grant up to $10,000 | H37: 24-284 | I37: 45513 | K37: Gortikov Capital | M37: Kingdom Development, Inc. | N37: FALSE | O37: 26 | P37: 25 | Q37: =P37/O37 -> 0.96153846 | R37: 1537 7th, Santa Monica, CA | S37: 3750 | T37: =COUNTIF(Parcels!A:A, A37) > 0 -> TRUE | U37: =MAXIFS(Parcels!AC:AC, Parcels!A:A, A37) > 0 -> TRUE | V37: =SUMIF(Parcels!A:A, A37, Parcels!Z:Z) -> 6580000 | W37: =SUMIF(Parcels!$A:$A, $A37, Parcels!AC:AC) -> 4088045 | X37: =V37*P37/O37*0.9 -> 5694230.8 | Y37: =IF(W37=0, X37, W37) -> 4088045 | Z37: {=_xlfn.XLOOKUP( A37, Parcels!A:A, Parcels!AL:AL)} -> 0.01203757 | AA37: =W37*Z37 -> 49210.128 | AB37: =Y37*Z37 -> 49210.128 | AG37: 5390000 | AH37: 45547 | AJ37: =if(F37="CMFA", if(O37<16,10000,O37*600),if(F37="CSCDA",if(33<O37<300, O37*600,if(O37>300,(180000+(O37-300)*300),20000)))) -> 15600 | AK37: =if(F37="CMFA", if(O37<26,4000,O37*150),if(F37="CSCDA",if(33<O37<300, O37*150,if(O37>300,(45000+(O37-300)*75),5000)))) -> 3900 | AL37: =if(AE37="YES",0,IF(AND(I37>=DATE(2022,7,1),I37<=DATE(2023,6,30)),3,IF(AND(I37>=DATE(2023,7,1),I37<=DATE(2024,6,30)),2,IF(AND(I37>=DATE(2024,7,1),I37<=DATE(2025,6,30)),1,IF(AND(I37>=DATE(2025,7,1),I37<=DATE(2026,6,30)),0,"-"))))) -> 1 | AM37: =AK37*AL37 -> 3900 | AN37: {=_xlfn.xlookup(C37,'SCC Certificate Review'!C:C,'SCC Certificate Review'!F:F)} -> TRUE
A38: 32 | B38: Santa Monica Portfolio F Apartments | C38: GC 2001-2029 Olympic, LP | D38: Santa Monica | E38: Los Angeles | F38: CMFA | G38: Grant up to $10,000 | H38: 24-285 | I38: 45513 | K38: Gortikov Capital | M38: Kingdom Development, Inc. | N38: FALSE | O38: 165 | P38: 98 | Q38: =P38/O38 -> 0.59393939 | R38: 2001-2029 Olympic Blvd, Santa Monica | S38: 14700 | T38: =COUNTIF(Parcels!A:A, A38) > 0 -> TRUE | U38: =MAXIFS(Parcels!AC:AC, Parcels!A:A, A38) > 0 -> TRUE | V38: =SUMIF(Parcels!A:A, A38, Parcels!Z:Z) -> 29350000 | W38: =SUMIF(Parcels!$A:$A, $A38, Parcels!AC:AC) -> 22352409 | X38: =V38*P38/O38*0.9 -> 15688909 | Y38: =IF(W38=0, X38, W38) -> 22352409 | Z38: {=_xlfn.XLOOKUP( A38, Parcels!A:A, Parcels!AL:AL)} -> 0.01203757 | AA38: =W38*Z38 -> 269068.69 | AB38: =Y38*Z38 -> 269068.69 | AF38: 2008 | AJ38: =if(F38="CMFA", if(O38<16,10000,O38*600),if(F38="CSCDA",if(33<O38<300, O38*600,if(O38>300,(180000+(O38-300)*300),20000)))) -> 99000 | AK38: =if(F38="CMFA", if(O38<26,4000,O38*150),if(F38="CSCDA",if(33<O38<300, O38*150,if(O38>300,(45000+(O38-300)*75),5000)))) -> 24750 | AL38: =if(AE38="YES",0,IF(AND(I38>=DATE(2022,7,1),I38<=DATE(2023,6,30)),3,IF(AND(I38>=DATE(2023,7,1),I38<=DATE(2024,6,30)),2,IF(AND(I38>=DATE(2024,7,1),I38<=DATE(2025,6,30)),1,IF(AND(I38>=DATE(2025,7,1),I38<=DATE(2026,6,30)),0,"-"))))) -> 1 | AM38: =AK38*AL38 -> 24750 | AN38: {=_xlfn.xlookup(C38,'SCC Certificate Review'!C:C,'SCC Certificate Review'!F:F)} -> TRUE
A39: 26 | B39: Harbor Terrace Apartments | C39: Post Harbor Terrace, LP | D39: Los Angeles | E39: Los Angeles | F39: CMFA | G39: Grant up to $10,000 | H39: 24-286 | I39: 45513 | K39: Ascenda Capital | M39: Integrity Housing | N39: FALSE | O39: 93 | P39: 93 | Q39: =P39/O39 -> 1 | R39: 441 W 3rd St, San Pedro, CA 90731 | S39: 13950 | T39: =COUNTIF(Parcels!A:A, A39) > 0 -> TRUE | U39: =MAXIFS(Parcels!AC:AC, Parcels!A:A, A39) > 0 -> TRUE | V39: =SUMIF(Parcels!A:A, A39, Parcels!Z:Z) -> 24250000 | W39: =SUMIF(Parcels!$A:$A, $A39, Parcels!AC:AC) -> 16429375 | X39: =V39*P39/O39*0.9 -> 21825000 | Y39: =IF(W39=0, X39, W39) -> 16429375 | Z39: {=_xlfn.XLOOKUP( A39, Parcels!A:A, Parcels!AL:AL)} -> 0.0118738 | AA39: =W39*Z39 -> 195079.11 | AB39: =Y39*Z39 -> 195079.11 | AF39: 1987 | AJ39: =if(F39="CMFA", if(O39<16,10000,O39*600),if(F39="CSCDA",if(33<O39<300, O39*600,if(O39>300,(180000+(O39-300)*300),20000)))) -> 55800 | AK39: =if(F39="CMFA", if(O39<26,4000,O39*150),if(F39="CSCDA",if(33<O39<300, O39*150,if(O39>300,(45000+(O39-300)*75),5000)))) -> 13950 | AL39: =if(AE39="YES",0,IF(AND(I39>=DATE(2022,7,1),I39<=DATE(2023,6,30)),3,IF(AND(I39>=DATE(2023,7,1),I39<=DATE(2024,6,30)),2,IF(AND(I39>=DATE(2024,7,1),I39<=DATE(2025,6,30)),1,IF(AND(I39>=DATE(2025,7,1),I39<=DATE(2026,6,30)),0,"-"))))) -> 1 | AM39: =AK39*AL39 -> 13950 | AN39: {=_xlfn.xlookup(C39,'SCC Certificate Review'!C:C,'SCC Certificate Review'!F:F)} -> TRUE
A40: 36 | B40: Stadium Village Apartments | C40: SV INGLEWOOD HOLDINGS, L.P., a California limited partnership | D40: Inglewood | E40: Los Angeles | F40: CMFA | G40: Grant up to $10,000 | H40: 24-361 | I40: 45534 | K40: Community HousingWorks | M40: Community HousingWorks | N40: FALSE | O40: 80 | P40: 80 | Q40: =P40/O40 -> 1 | R40: 9301 – 9609 Crenshaw Blvd, Inglewood, CA | S40: 12000 | T40: =COUNTIF(Parcels!A:A, A40) > 0 -> TRUE | U40: =MAXIFS(Parcels!AC:AC, Parcels!A:A, A40) > 0 -> FALSE | V40: =SUMIF(Parcels!A:A, A40, Parcels!Z:Z) -> 26900000 | W40: =SUMIF(Parcels!$A:$A, $A40, Parcels!AC:AC) -> 0 | X40: =V40*P40/O40*0.9 -> 24210000 | Y40: =IF(W40=0, X40, W40) -> 24210000 | Z40: {=_xlfn.XLOOKUP( A40, Parcels!A:A, Parcels!AL:AL)} -> 0.01280765 | AA40: =W40*Z40 -> 0 | AB40: =Y40*Z40 -> 310073.21 | AJ40: =if(F40="CMFA", if(O40<16,10000,O40*600),if(F40="CSCDA",if(33<O40<300, O40*600,if(O40>300,(180000+(O40-300)*300),20000)))) -> 48000 | AK40: =if(F40="CMFA", if(O40<26,4000,O40*150),if(F40="CSCDA",if(33<O40<300, O40*150,if(O40>300,(45000+(O40-300)*75),5000)))) -> 12000 | AL40: =if(AE40="YES",0,IF(AND(I40>=DATE(2022,7,1),I40<=DATE(2023,6,30)),3,IF(AND(I40>=DATE(2023,7,1),I40<=DATE(2024,6,30)),2,IF(AND(I40>=DATE(2024,7,1),I40<=DATE(2025,6,30)),1,IF(AND(I40>=DATE(2025,7,1),I40<=DATE(2026,6,30)),0,"-"))))) -> 1 | AM40: =AK40*AL40 -> 12000 | AN40: {=_xlfn.xlookup(C40,'SCC Certificate Review'!C:C,'SCC Certificate Review'!F:F)} -> TRUE
A41: 37 | B41: 2330 E. 3rd Street Apartments | C41: 2330 3rd Street Apartments L.P. | D41: Los Angeles | E41: Los Angeles | F41: CMFA | G41: Grant up to $10,000 | H41: 24-363 | I41: 45534 | K41: Terra Capital Development Group LLC | M41: Pacific Housing | N41: FALSE | O41: 53 | P41: 53 | Q41: =P41/O41 -> 1 | R41: 2330 E. 3rd Street, Los Angeles, CA | S41: 7950 | T41: =COUNTIF(Parcels!A:A, A41) > 0 -> TRUE | U41: =MAXIFS(Parcels!AC:AC, Parcels!A:A, A41) > 0 -> FALSE | V41: =SUMIF(Parcels!A:A, A41, Parcels!Z:Z) -> 1275000 | W41: =SUMIF(Parcels!$A:$A, $A41, Parcels!AC:AC) -> 0 | X41: =V41*P41/O41*0.9 -> 1147500 | Y41: =IF(W41=0, X41, W41) -> 1147500 | Z41: {=_xlfn.XLOOKUP( A41, Parcels!A:A, Parcels!AL:AL)} -> 0.0118738 | AA41: =W41*Z41 -> 0 | AB41: =Y41*Z41 -> 13625.185 | AE41: YES | AJ41: =if(F41="CMFA", if(O41<16,10000,O41*600),if(F41="CSCDA",if(33<O41<300, O41*600,if(O41>300,(180000+(O41-300)*300),20000)))) -> 31800 | AK41: =if(F41="CMFA", if(O41<26,4000,O41*150),if(F41="CSCDA",if(33<O41<300, O41*150,if(O41>300,(45000+(O41-300)*75),5000)))) -> 7950 | AL41: =if(AE41="YES",0,IF(AND(I41>=DATE(2022,7,1),I41<=DATE(2023,6,30)),3,IF(AND(I41>=DATE(2023,7,1),I41<=DATE(2024,6,30)),2,IF(AND(I41>=DATE(2024,7,1),I41<=DATE(2025,6,30)),1,IF(AND(I41>=DATE(2025,7,1),I41<=DATE(2026,6,30)),0,"-"))))) -> 0 | AM41: =AK41*AL41 -> 0 | AN41: {=_xlfn.xlookup(C41,'SCC Certificate Review'!C:C,'SCC Certificate Review'!F:F)} -> TRUE
A42: 39 | B42: 6200 S. Broadway Apartments | C42: BIF NON OZ 6200 BROADWAY BLK, LP | D42: Los Angeles | E42: Los Angeles | F42: CMFA | G42: Grant up to $10,000 | H42: 24-379 | I42: 45555 | K42: SoLa Impact, LLC | M42: Housing on Merit | N42: FALSE | O42: 66 | P42: 51 | Q42: =P42/O42 -> 0.77272727 | R42: 6200 S Broadway, Los Angeles, CA | S42: 7950 | T42: =COUNTIF(Parcels!A:A, A42) > 0 -> TRUE | U42: =MAXIFS(Parcels!AC:AC, Parcels!A:A, A42) > 0 -> FALSE | V42: =SUMIF(Parcels!A:A, A42, Parcels!Z:Z) -> 1326510 | W42: =SUMIF(Parcels!$A:$A, $A42, Parcels!AC:AC) -> 0 | X42: =V42*P42/O42*0.9 -> 922527.41 | Y42: =IF(W42=0, X42, W42) -> 922527.41 | Z42: {=_xlfn.XLOOKUP( A42, Parcels!A:A, Parcels!AL:AL)} -> 0.0118738 | AA42: =W42*Z42 -> 0 | AB42: =Y42*Z42 -> 10953.906 | AE42: YES | AJ42: =if(F42="CMFA", if(O42<16,10000,O42*600),if(F42="CSCDA",if(33<O42<300, O42*600,if(O42>300,(180000+(O42-300)*300),20000)))) -> 39600 | AK42: =if(F42="CMFA", if(O42<26,4000,O42*150),if(F42="CSCDA",if(33<O42<300, O42*150,if(O42>300,(45000+(O42-300)*75),5000)))) -> 9900 | AL42: =if(AE42="YES",0,IF(AND(I42>=DATE(2022,7,1),I42<=DATE(2023,6,30)),3,IF(AND(I42>=DATE(2023,7,1),I42<=DATE(2024,6,30)),2,IF(AND(I42>=DATE(2024,7,1),I42<=DATE(2025,6,30)),1,IF(AND(I42>=DATE(2025,7,1),I42<=DATE(2026,6,30)),0,"-"))))) -> 0 | AM42: =AK42*AL42 -> 0 | AN42: {=_xlfn.xlookup(C42,'SCC Certificate Review'!C:C,'SCC Certificate Review'!F:F)} -> TRUE
A43: 40 | B43: 4228 Western Ave. Apartments | C43: BIF NON OZ 4228 WESTERN AVE, LP | D43: Los Angeles | E43: Los Angeles | F43: CMFA | G43: Grant up to $10,000 | H43: 24-380 | I43: 45555 | J43: TRUE | K43: SoLa Impact, LLC | M43: Housing on Merit | N43: FALSE | O43: 68 | P43: 14 | Q43: =P43/O43 -> 0.20588235 | R43: 4228 Western Avenue, Los Angeles, CA | S43: 2500 | T43: =COUNTIF(Parcels!A:A, A43) > 0 -> TRUE | U43: =MAXIFS(Parcels!AC:AC, Parcels!A:A, A43) > 0 -> FALSE | V43: =SUMIF(Parcels!A:A, A43, Parcels!Z:Z) -> 17790840 | W43: =SUMIF(Parcels!$A:$A, $A43, Parcels!AC:AC) -> 0 | X43: =V43*P43/O43*0.9 -> 3296538 | Y43: =IF(W43=0, X43, W43) -> 3296538 | Z43: {=_xlfn.XLOOKUP( A43, Parcels!A:A, Parcels!AL:AL)} -> 0.0118738 | AA43: =W43*Z43 -> 0 | AB43: =Y43*Z43 -> 39142.433 | AE43: YES | AJ43: =if(F43="CMFA", if(O43<16,10000,O43*600),if(F43="CSCDA",if(33<O43<300, O43*600,if(O43>300,(180000+(O43-300)*300),20000)))) -> 40800 | AK43: =if(F43="CMFA", if(O43<26,4000,O43*150),if(F43="CSCDA",if(33<O43<300, O43*150,if(O43>300,(45000+(O43-300)*75),5000)))) -> 10200 | AL43: =if(AE43="YES",0,IF(AND(I43>=DATE(2022,7,1),I43<=DATE(2023,6,30)),3,IF(AND(I43>=DATE(2023,7,1),I43<=DATE(2024,6,30)),2,IF(AND(I43>=DATE(2024,7,1),I43<=DATE(2025,6,30)),1,IF(AND(I43>=DATE(2025,7,1),I43<=DATE(2026,6,30)),0,"-"))))) -> 0 | AM43: =AK43*AL43 -> 0 | AN43: {=_xlfn.xlookup(C43,'SCC Certificate Review'!C:C,'SCC Certificate Review'!F:F)}
A44: 41 | B44: 4327 S. Vermont Apartments | C44: IF OZ 4300 S VERMONT AVE BLK LP, a Delaware limited partnership | D44: Los Angeles | E44: Los Angeles | F44: CMFA | G44: Grant up to $10,000 | H44: 24-381 | I44: 45555 | K44: SoLa Impact, LLC | M44: Housing on Merit | N44: FALSE | O44: 188 | P44: 111 | Q44: =P44/O44 -> 0.59042553 | R44: 4327 S Vermont, Los Angeles, CA | S44: 16650 | T44: =COUNTIF(Parcels!A:A, A44) > 0 -> TRUE | U44: =MAXIFS(Parcels!AC:AC, Parcels!A:A, A44) > 0 -> FALSE | V44: =SUMIF(Parcels!A:A, A44, Parcels!Z:Z) -> 3719558 | W44: =SUMIF(Parcels!$A:$A, $A44, Parcels!AC:AC) -> 0 | X44: =V44*P44/O44*0.9 -> 1976509.8 | Y44: =IF(W44=0, X44, W44) -> 1976509.8 | Z44: {=_xlfn.XLOOKUP( A44, Parcels!A:A, Parcels!AL:AL)} -> 0.0118738 | AA44: =W44*Z44 -> 0 | AB44: =Y44*Z44 -> 23468.682 | AE44: YES | AJ44: =if(F44="CMFA", if(O44<16,10000,O44*600),if(F44="CSCDA",if(33<O44<300, O44*600,if(O44>300,(180000+(O44-300)*300),20000)))) -> 112800 | AK44: =if(F44="CMFA", if(O44<26,4000,O44*150),if(F44="CSCDA",if(33<O44<300, O44*150,if(O44>300,(45000+(O44-300)*75),5000)))) -> 28200 | AL44: =if(AE44="YES",0,IF(AND(I44>=DATE(2022,7,1),I44<=DATE(2023,6,30)),3,IF(AND(I44>=DATE(2023,7,1),I44<=DATE(2024,6,30)),2,IF(AND(I44>=DATE(2024,7,1),I44<=DATE(2025,6,30)),1,IF(AND(I44>=DATE(2025,7,1),I44<=DATE(2026,6,30)),0,"-"))))) -> 0 | AM44: =AK44*AL44 -> 0 | AN44: {=_xlfn.xlookup(C44,'SCC Certificate Review'!C:C,'SCC Certificate Review'!F:F)}
A45: 42 | B45: 2023 Imperial Apartments | C45: BIF NON OZ 2000 Imperial Hwy Blk, LP | D45: Los Angeles | E45: Los Angeles | F45: CMFA | G45: Grant up to $10,000 | H45: 24-382 | I45: 45555 | J45: TRUE | K45: SoLa Impact, LLC | M45: Housing on Merit | N45: FALSE | O45: 90 | P45: 71 | Q45: =P45/O45 -> 0.78888889 | R45: 110 Imperial Highway, Los Angeles, CA | S45: 10650 | T45: =COUNTIF(Parcels!A:A, A45) > 0 -> TRUE | U45: =MAXIFS(Parcels!AC:AC, Parcels!A:A, A45) > 0 -> FALSE | V45: =SUMIF(Parcels!A:A, A45, Parcels!Z:Z) -> 429364 | W45: =SUMIF(Parcels!$A:$A, $A45, Parcels!AC:AC) -> 0 | X45: =V45*P45/O45*0.9 -> 304848.44 | Y45: =IF(W45=0, X45, W45) -> 304848.44 | Z45: {=_xlfn.XLOOKUP( A45, Parcels!A:A, Parcels!AL:AL)} -> 0.0118738 | AA45: =W45*Z45 -> 0 | AB45: =Y45*Z45 -> 3619.7094 | AE45: YES | AJ45: =if(F45="CMFA", if(O45<16,10000,O45*600),if(F45="CSCDA",if(33<O45<300, O45*600,if(O45>300,(180000+(O45-300)*300),20000)))) -> 54000 | AK45: =if(F45="CMFA", if(O45<26,4000,O45*150),if(F45="CSCDA",if(33<O45<300, O45*150,if(O45>300,(45000+(O45-300)*75),5000)))) -> 13500 | AL45: =if(AE45="YES",0,IF(AND(I45>=DATE(2022,7,1),I45<=DATE(2023,6,30)),3,IF(AND(I45>=DATE(2023,7,1),I45<=DATE(2024,6,30)),2,IF(AND(I45>=DATE(2024,7,1),I45<=DATE(2025,6,30)),1,IF(AND(I45>=DATE(2025,7,1),I45<=DATE(2026,6,30)),0,"-"))))) -> 0 | AM45: =AK45*AL45 -> 0 | AN45: {=_xlfn.xlookup(C45,'SCC Certificate Review'!C:C,'SCC Certificate Review'!F:F)}
A46: 38 | B46: Marquee Apartments | C46: Post Marquee North Hollywood, LP | D46: Los Angeles | E46: Los Angeles | F46: CMFA | G46: Grant up to $10,000 | H46: 24-383 | I46: 45555 | K46: Ascenda Capital | M46: Integrity Housing | N46: FALSE | O46: 236 | P46: 236 | Q46: =P46/O46 -> 1 | R46: 12300 Sherman Way, North Hollywood, CA 91605 | S46: 35400 | T46: =COUNTIF(Parcels!A:A, A46) > 0 -> TRUE | U46: =MAXIFS(Parcels!AC:AC, Parcels!A:A, A46) > 0 -> FALSE | V46: =SUMIF(Parcels!A:A, A46, Parcels!Z:Z) -> 43800000 | W46: =SUMIF(Parcels!$A:$A, $A46, Parcels!AC:AC) -> 0 | X46: =V46*P46/O46*0.9 -> 39420000 | Y46: =IF(W46=0, X46, W46) -> 39420000 | Z46: {=_xlfn.XLOOKUP( A46, Parcels!A:A, Parcels!AL:AL)} -> 0.0118738 | AA46: =W46*Z46 -> 0 | AB46: =Y46*Z46 -> 468065.2 | AE46: NO | AF46: 1965 | AJ46: =if(F46="CMFA", if(O46<16,10000,O46*600),if(F46="CSCDA",if(33<O46<300, O46*600,if(O46>300,(180000+(O46-300)*300),20000)))) -> 141600 | AK46: =if(F46="CMFA", if(O46<26,4000,O46*150),if(F46="CSCDA",if(33<O46<300, O46*150,if(O46>300,(45000+(O46-300)*75),5000)))) -> 35400 | AL46: =if(AE46="YES",0,IF(AND(I46>=DATE(2022,7,1),I46<=DATE(2023,6,30)),3,IF(AND(I46>=DATE(2023,7,1),I46<=DATE(2024,6,30)),2,IF(AND(I46>=DATE(2024,7,1),I46<=DATE(2025,6,30)),1,IF(AND(I46>=DATE(2025,7,1),I46<=DATE(2026,6,30)),0,"-"))))) -> 1 | AM46: =AK46*AL46 -> 35400 | AN46: {=_xlfn.xlookup(C46,'SCC Certificate Review'!C:C,'SCC Certificate Review'!F:F)} -> TRUE
A47: 43 | B47: Meridian Apartments | C47: 400 Meridian, LP, a California limited partnership | D47: San Rafael | E47: Marin | F47: CMFA | G47: Grant up to $10,000 | H47: 24-384 | I47: 45555 | J47: TRUE | K47: Tesseract Capital Group | M47: Housing on Merit | N47: FALSE | O47: 99 | P47: 99 | R47: 400 Canal St, San Rafael, CA 94901 | S47: 14850 | T47: =COUNTIF(Parcels!A:A, A47) > 0 -> TRUE | U47: =MAXIFS(Parcels!AC:AC, Parcels!A:A, A47) > 0 -> FALSE | V47: =SUMIF(Parcels!A:A, A47, Parcels!Z:Z) -> 33879341 | W47: =SUMIF(Parcels!$A:$A, $A47, Parcels!AC:AC) -> 0 | X47: =V47*P47/O47*0.9 -> 30491407 | Y47: =IF(W47=0, X47, W47) -> 30491407 | Z47: {=_xlfn.XLOOKUP( A47, Parcels!A:A, Parcels!AL:AL)} -> 0.01084 | AA47: =W47*Z47 -> 0 | AB47: =Y47*Z47 -> 330526.85 | AE47: NO | AJ47: =if(F47="CMFA", if(O47<16,10000,O47*600),if(F47="CSCDA",if(33<O47<300, O47*600,if(O47>300,(180000+(O47-300)*300),20000)))) -> 59400 | AK47: =if(F47="CMFA", if(O47<26,4000,O47*150),if(F47="CSCDA",if(33<O47<300, O47*150,if(O47>300,(45000+(O47-300)*75),5000)))) -> 14850 | AL47: =if(AE47="YES",0,IF(AND(I47>=DATE(2022,7,1),I47<=DATE(2023,6,30)),3,IF(AND(I47>=DATE(2023,7,1),I47<=DATE(2024,6,30)),2,IF(AND(I47>=DATE(2024,7,1),I47<=DATE(2025,6,30)),1,IF(AND(I47>=DATE(2025,7,1),I47<=DATE(2026,6,30)),0,"-"))))) -> 1 | AM47: =AK47*AL47 -> 14850 | AN47: {=_xlfn.xlookup(C47,'SCC Certificate Review'!C:C,'SCC Certificate Review'!F:F)}
A48: 46 | B48: 4752 Main Street Apartments | C48: 4752 Main, LP | D48: Los Angeles | E48: Los Angeles | F48: CMFA | H48: 24-399 | I48: 45576 | J48: TRUE | K48: Eleos Ventures, LLC | M48: Step Forward Communities | N48: FALSE | O48: 53 | P48: 53 | Q48: =P48/O48 -> 1 | R48: 4752 Main St, Los Angeles, CA 90037 | T48: =COUNTIF(Parcels!A:A, A48) > 0 -> TRUE | U48: =MAXIFS(Parcels!AC:AC, Parcels!A:A, A48) > 0 -> FALSE | V48: =SUMIF(Parcels!A:A, A48, Parcels!Z:Z) -> 1298913 | W48: =SUMIF(Parcels!$A:$A, $A48, Parcels!AC:AC) -> 0 | X48: =V48*P48/O48*0.9 -> 1169021.7 | Y48: =IF(W48=0, X48, W48) -> 1169021.7 | Z48: {=_xlfn.XLOOKUP( A48, Parcels!A:A, Parcels!AL:AL)} -> 0.0118738 | AA48: =W48*Z48 -> 0 | AB48: =Y48*Z48 -> 13880.73 | AE48: YES | AJ48: =if(F48="CMFA", if(O48<16,10000,O48*600),if(F48="CSCDA",if(33<O48<300, O48*600,if(O48>300,(180000+(O48-300)*300),20000)))) -> 31800 | AK48: =if(F48="CMFA", if(O48<26,4000,O48*150),if(F48="CSCDA",if(33<O48<300, O48*150,if(O48>300,(45000+(O48-300)*75),5000)))) -> 7950 | AL48: =if(AE48="YES",0,IF(AND(I48>=DATE(2022,7,1),I48<=DATE(2023,6,30)),3,IF(AND(I48>=DATE(2023,7,1),I48<=DATE(2024,6,30)),2,IF(AND(I48>=DATE(2024,7,1),I48<=DATE(2025,6,30)),1,IF(AND(I48>=DATE(2025,7,1),I48<=DATE(2026,6,30)),0,"-"))))) -> 0 | AM48: =AK48*AL48 -> 0 | AN48: {=_xlfn.xlookup(C48,'SCC Certificate Review'!C:C,'SCC Certificate Review'!F:F)}
A49: 45 | B49: Horizon Apartments | C49: BWF II ETHOS CA HORIZON LP, a Delaware limited partnership | D49: Santa Ana | E49: Orange | F49: CMFA | G49: Grant up to $10,000 | H49: 24-410 | I49: 45576 | K49: Ethos Real Estate | L49: Bridge Investment Group | M49: Affordable Housing Access Inc | N49: FALSE | O49: 406 | P49: 406 | R49: 2414 N Tustin Ave, Santa Ana, CA 92705 | S49: 60900 | T49: =COUNTIF(Parcels!A:A, A49) > 0 -> TRUE | U49: =MAXIFS(Parcels!AC:AC, Parcels!A:A, A49) > 0 -> FALSE | V49: =SUMIF(Parcels!A:A, A49, Parcels!Z:Z) -> 129200000 | W49: =SUMIF(Parcels!$A:$A, $A49, Parcels!AC:AC) -> 0 | X49: =V49*P49/O49*0.9 -> 116280000 | Y49: =IF(W49=0, X49, W49) -> 116280000 | Z49: {=_xlfn.XLOOKUP( A49, Parcels!A:A, Parcels!AL:AL)} -> 0.011195 | AA49: =W49*Z49 -> 0 | AB49: =Y49*Z49 -> 1301754.6 | AE49: NO | AJ49: =if(F49="CMFA", if(O49<16,10000,O49*600),if(F49="CSCDA",if(33<O49<300, O49*600,if(O49>300,(180000+(O49-300)*300),20000)))) -> 243600 | AK49: =if(F49="CMFA", if(O49<26,4000,O49*150),if(F49="CSCDA",if(33<O49<300, O49*150,if(O49>300,(45000+(O49-300)*75),5000)))) -> 60900 | AL49: =if(AE49="YES",0,IF(AND(I49>=DATE(2022,7,1),I49<=DATE(2023,6,30)),3,IF(AND(I49>=DATE(2023,7,1),I49<=DATE(2024,6,30)),2,IF(AND(I49>=DATE(2024,7,1),I49<=DATE(2025,6,30)),1,IF(AND(I49>=DATE(2025,7,1),I49<=DATE(2026,6,30)),0,"-"))))) -> 1 | AM49: =AK49*AL49 -> 60900 | AN49: {=_xlfn.xlookup(C49,'SCC Certificate Review'!C:C,'SCC Certificate Review'!F:F)} -> TRUE
A50: 48 | B50: Hillsdale Gardens Apartments | C50: Hillsdale Property LP | D50: San Mateo | E50: San Mateo | F50: CMFA | G50: Grant up to $10,000 | H50: 24-411 | I50: 45576 | K50: Vistria Group | L50: Ethos Real Estate | M50: Pacific Housing, Inc. | N50: FALSE | O50: 697 | P50: 697 | R50: 3500 Edison St, San Mateo, CA 94403 | S50: 74775 | T50: =COUNTIF(Parcels!A:A, A50) > 0 -> TRUE | U50: =MAXIFS(Parcels!AC:AC, Parcels!A:A, A50) > 0 -> TRUE | V50: =SUMIF(Parcels!A:A, A50, Parcels!Z:Z) -> 252362500 | W50: =SUMIF(Parcels!$A:$A, $A50, Parcels!AC:AC) -> 28000 | X50: =V50*P50/O50*0.9 -> 227126250 | Y50: =IF(W50=0, X50, W50) -> 28000 | Z50: {=_xlfn.XLOOKUP( A50, Parcels!A:A, Parcels!AL:AL)} -> 0.011201 | AB50: =Y50*Z50 -> 313.628 | AE50: NO | AJ50: =if(F50="CMFA", if(O50<16,10000,O50*600),if(F50="CSCDA",if(33<O50<300, O50*600,if(O50>300,(180000+(O50-300)*300),20000)))) -> 418200 | AK50: =if(F50="CMFA", if(O50<26,4000,O50*150),if(F50="CSCDA",if(33<O50<300, O50*150,if(O50>300,(45000+(O50-300)*75),5000)))) -> 104550 | AL50: =if(AE50="YES",0,IF(AND(I50>=DATE(2022,7,1),I50<=DATE(2023,6,30)),3,IF(AND(I50>=DATE(2023,7,1),I50<=DATE(2024,6,30)),2,IF(AND(I50>=DATE(2024,7,1),I50<=DATE(2025,6,30)),1,IF(AND(I50>=DATE(2025,7,1),I50<=DATE(2026,6,30)),0,"-"))))) -> 1 | AM50: =AK50*AL50 -> 104550 | AN50: {=_xlfn.xlookup(C50,'SCC Certificate Review'!C:C,'SCC Certificate Review'!F:F)} -> TRUE
A51: 47 | B51: 6171 Mission Gorge Apartments | C51: 6171 Mission Gorge Owner LP, a California limited partnership | D51: San Diego | E51: San Diego | F51: CMFA | G51: Grant up to $10,000 | H51: 24-412 | I51: 45576 | K51: Impact Housing | M51: Las Palmas Housing & Development Corporation | N51: FALSE | O51: 488 | P51: 483 | R51: 6171 Mission Gorge Rd, San Diego, CA 92120 | S51: 72450 | T51: =COUNTIF(Parcels!A:A, A51) > 0 -> TRUE | U51: =MAXIFS(Parcels!AC:AC, Parcels!A:A, A51) > 0 -> FALSE | V51: =SUMIF(Parcels!A:A, A51, Parcels!Z:Z) -> 13362000 | W51: =SUMIF(Parcels!$A:$A, $A51, Parcels!AC:AC) -> 0 | X51: =V51*P51/O51*0.9 -> 11902585 | Y51: =IF(W51=0, X51, W51) -> 11902585 | Z51: {=_xlfn.XLOOKUP( A51, Parcels!A:A, Parcels!AL:AL)} -> 0.0125114 | AA51: =W51*Z51 -> 0 | AB51: =Y51*Z51 -> 148918 | AE51: YES | AJ51: =if(F51="CMFA", if(O51<16,10000,O51*600),if(F51="CSCDA",if(33<O51<300, O51*600,if(O51>300,(180000+(O51-300)*300),20000)))) -> 292800 | AK51: =if(F51="CMFA", if(O51<26,4000,O51*150),if(F51="CSCDA",if(33<O51<300, O51*150,if(O51>300,(45000+(O51-300)*75),5000)))) -> 73200 | AL51: =if(AE51="YES",0,IF(AND(I51>=DATE(2022,7,1),I51<=DATE(2023,6,30)),3,IF(AND(I51>=DATE(2023,7,1),I51<=DATE(2024,6,30)),2,IF(AND(I51>=DATE(2024,7,1),I51<=DATE(2025,6,30)),1,IF(AND(I51>=DATE(2025,7,1),I51<=DATE(2026,6,30)),0,"-"))))) -> 0 | AM51: =AK51*AL51 -> 0 | AN51: {=_xlfn.xlookup(C51,'SCC Certificate Review'!C:C,'SCC Certificate Review'!F:F)} -> TRUE
A52: 44 | B52: Soto Apartments | C52: EV 228 Soto, LP, a California limited partnership | D52: Los Angeles | E52: Los Angeles | F52: CMFA | G52: Grant up to $10,000 | H52: 24-413 | I52: 45576 | K52: Eleos Ventures, LLC | M52: Step Forward Comminities | N52: FALSE | O52: 41 | P52: 40 | Q52: =P52/O52 -> 0.97560976 | R52: 228 N Soto Street, Los Angeles, CA | S52: 6000 | T52: =COUNTIF(Parcels!A:A, A52) > 0 -> TRUE | U52: =MAXIFS(Parcels!AC:AC, Parcels!A:A, A52) > 0 -> FALSE | V52: =SUMIF(Parcels!A:A, A52, Parcels!Z:Z) -> 2509100 | W52: =SUMIF(Parcels!$A:$A, $A52, Parcels!AC:AC) -> 0 | X52: =V52*P52/O52*0.9 -> 2203112.2 | Y52: =IF(W52=0, X52, W52) -> 2203112.2 | Z52: {=_xlfn.XLOOKUP( A52, Parcels!A:A, Parcels!AL:AL)} -> 0.0118738 | AA52: =W52*Z52 -> 0 | AB52: =Y52*Z52 -> 26159.314 | AE52: YES | AJ52: =if(F52="CMFA", if(O52<16,10000,O52*600),if(F52="CSCDA",if(33<O52<300, O52*600,if(O52>300,(180000+(O52-300)*300),20000)))) -> 24600 | AK52: =if(F52="CMFA", if(O52<26,4000,O52*150),if(F52="CSCDA",if(33<O52<300, O52*150,if(O52>300,(45000+(O52-300)*75),5000)))) -> 6150 | AL52: =if(AE52="YES",0,IF(AND(I52>=DATE(2022,7,1),I52<=DATE(2023,6,30)),3,IF(AND(I52>=DATE(2023,7,1),I52<=DATE(2024,6,30)),2,IF(AND(I52>=DATE(2024,7,1),I52<=DATE(2025,6,30)),1,IF(AND(I52>=DATE(2025,7,1),I52<=DATE(2026,6,30)),0,"-"))))) -> 0 | AM52: =AK52*AL52 -> 0 | AN52: {=_xlfn.xlookup(C52,'SCC Certificate Review'!C:C,'SCC Certificate Review'!F:F)} -> TRUE
A53: 50 | B53: Market Street Village Apartments | C53: 699 14TH Street CSLC LP | D53: San Diego | E53: San Diego | F53: CMFA | G53: Grant up to $10,000 | H53: 24-427 | I53: 45597 | K53: Community Solutions | M53: Community Solutions | N53: FALSE | O53: 229 | P53: 229 | R53: 699 14th Street, San Diego, CA | S53: 34350 | T53: =COUNTIF(Parcels!A:A, A53) > 0 -> TRUE | U53: =MAXIFS(Parcels!AC:AC, Parcels!A:A, A53) > 0 -> FALSE | V53: =SUMIF(Parcels!A:A, A53, Parcels!Z:Z) -> 53339453 | W53: =SUMIF(Parcels!$A:$A, $A53, Parcels!AC:AC) -> 0 | X53: =V53*P53/O53*0.9 -> 48005508 | Y53: =IF(W53=0, X53, W53) -> 48005508 | Z53: {=_xlfn.XLOOKUP( A53, Parcels!A:A, Parcels!AL:AL)} -> 0.0125114 | AA53: =W53*Z53 -> 0 | AB53: =Y53*Z53 -> 600616.11 | AE53: NO | AJ53: =if(F53="CMFA", if(O53<16,10000,O53*600),if(F53="CSCDA",if(33<O53<300, O53*600,if(O53>300,(180000+(O53-300)*300),20000)))) -> 137400 | AK53: =if(F53="CMFA", if(O53<26,4000,O53*150),if(F53="CSCDA",if(33<O53<300, O53*150,if(O53>300,(45000+(O53-300)*75),5000)))) -> 34350 | AL53: =if(AE53="YES",0,IF(AND(I53>=DATE(2022,7,1),I53<=DATE(2023,6,30)),3,IF(AND(I53>=DATE(2023,7,1),I53<=DATE(2024,6,30)),2,IF(AND(I53>=DATE(2024,7,1),I53<=DATE(2025,6,30)),1,IF(AND(I53>=DATE(2025,7,1),I53<=DATE(2026,6,30)),0,"-"))))) -> 1 | AM53: =AK53*AL53 -> 34350 | AN53: {=_xlfn.xlookup(C53,'SCC Certificate Review'!C:C,'SCC Certificate Review'!F:F)} -> TRUE
A54: 52 | B54: The Carla Apartments | C54: 1201 Fulton Ave LP | D54: Unincorporated | E54: Sacramento | F54: CMFA | G54: Grant up to $10,000 | H54: 24-428 | I54: 45597 | J54: TRUE | K54: Trion Properties, Inc. | M54: Riverside Charitable Corporation | N54: FALSE | O54: 63 | P54: 62 | R54: 1201 Fulton Ave, Sacramento, CA 95825 | S54: 9300 | T54: =COUNTIF(Parcels!A:A, A54) > 0 -> TRUE | U54: =MAXIFS(Parcels!AC:AC, Parcels!A:A, A54) > 0 -> FALSE | V54: =SUMIF(Parcels!A:A, A54, Parcels!Z:Z) -> 15111810 | W54: =SUMIF(Parcels!$A:$A, $A54, Parcels!AC:AC) -> 0 | X54: =V54*P54/O54*0.9 -> 13384746 | Y54: =IF(W54=0, X54, W54) -> 13384746 | Z54: {=_xlfn.XLOOKUP( A54, Parcels!A:A, Parcels!AL:AL)} -> 0.011454 | AA54: =W54*Z54 -> 0 | AB54: =Y54*Z54 -> 153308.88 | AE54: NO | AJ54: =if(F54="CMFA", if(O54<16,10000,O54*600),if(F54="CSCDA",if(33<O54<300, O54*600,if(O54>300,(180000+(O54-300)*300),20000)))) -> 37800 | AK54: =if(F54="CMFA", if(O54<26,4000,O54*150),if(F54="CSCDA",if(33<O54<300, O54*150,if(O54>300,(45000+(O54-300)*75),5000)))) -> 9450 | AL54: =if(AE54="YES",0,IF(AND(I54>=DATE(2022,7,1),I54<=DATE(2023,6,30)),3,IF(AND(I54>=DATE(2023,7,1),I54<=DATE(2024,6,30)),2,IF(AND(I54>=DATE(2024,7,1),I54<=DATE(2025,6,30)),1,IF(AND(I54>=DATE(2025,7,1),I54<=DATE(2026,6,30)),0,"-"))))) -> 1 | AM54: =AK54*AL54 -> 9450 | AN54: {=_xlfn.xlookup(C54,'SCC Certificate Review'!C:C,'SCC Certificate Review'!F:F)}
A55: 51 | B55: Creekside Villas Apartments | C55: Post Creekside, LP | D55: San Diego | E55: San Diego | F55: CMFA | G55: Grant up to $10,000 | H55: 24-429 | I55: 45597 | J55: TRUE | K55: Post Investment Group | M55: Integrity Housing | N55: FALSE | O55: =99+44+1+1 -> 145 | P55: 144 | R55: 220 47th St, San Diego, CA 92102 | S55: 21600 | T55: =COUNTIF(Parcels!A:A, A55) > 0 -> TRUE | U55: =MAXIFS(Parcels!AC:AC, Parcels!A:A, A55) > 0 -> FALSE | V55: =SUMIF(Parcels!A:A, A55, Parcels!Z:Z) -> 5832864 | W55: =SUMIF(Parcels!$A:$A, $A55, Parcels!AC:AC) -> 0 | X55: =V55*P55/O55*0.9 -> 5213373.6 | Y55: =IF(W55=0, X55, W55) -> 5213373.6 | Z55: {=_xlfn.XLOOKUP( A55, Parcels!A:A, Parcels!AL:AL)} -> 0.0125114 | AA55: =W55*Z55 -> 0 | AB55: =Y55*Z55 -> 65226.603 | AE55: NO | AF55: 1984 | AJ55: =if(F55="CMFA", if(O55<16,10000,O55*600),if(F55="CSCDA",if(33<O55<300, O55*600,if(O55>300,(180000+(O55-300)*300),20000)))) -> 87000 | AK55: =if(F55="CMFA", if(O55<26,4000,O55*150),if(F55="CSCDA",if(33<O55<300, O55*150,if(O55>300,(45000+(O55-300)*75),5000)))) -> 21750 | AL55: =if(AE55="YES",0,IF(AND(I55>=DATE(2022,7,1),I55<=DATE(2023,6,30)),3,IF(AND(I55>=DATE(2023,7,1),I55<=DATE(2024,6,30)),2,IF(AND(I55>=DATE(2024,7,1),I55<=DATE(2025,6,30)),1,IF(AND(I55>=DATE(2025,7,1),I55<=DATE(2026,6,30)),0,"-"))))) -> 1 | AM55: =AK55*AL55 -> 21750 | AN55: {=_xlfn.xlookup(C55,'SCC Certificate Review'!C:C,'SCC Certificate Review'!F:F)}
A56: 53 | B56: Skylark Place by Trion Living Apartments | C56: Trion Skylark Properties, LP | D56: Unincorporated | E56: Sacramento | F56: CMFA | G56: Grant up to $10,000 | H56: 24-430 | I56: 45597 | J56: TRUE | K56: Trion Properties, Inc. | M56: Integrity Housing | N56: FALSE | O56: 198 | P56: 198 | R56: 6930 Fair Oaks Blvd, Carmichael, CA 95608 | S56: 29700 | T56: =COUNTIF(Parcels!A:A, A56) > 0 -> TRUE | U56: =MAXIFS(Parcels!AC:AC, Parcels!A:A, A56) > 0 -> FALSE | V56: =SUMIF(Parcels!A:A, A56, Parcels!Z:Z) -> 12145525 | W56: =SUMIF(Parcels!$A:$A, $A56, Parcels!AC:AC) -> 0 | X56: =V56*P56/O56*0.9 -> 10930972 | Y56: =IF(W56=0, X56, W56) -> 10930972 | Z56: {=_xlfn.XLOOKUP( A56, Parcels!A:A, Parcels!AL:AL)} -> 0.011873 | AA56: =W56*Z56 -> 0 | AB56: =Y56*Z56 -> 129783.44 | AE56: NO | AF56: 1973/1991 | AJ56: =if(F56="CMFA", if(O56<16,10000,O56*600),if(F56="CSCDA",if(33<O56<300, O56*600,if(O56>300,(180000+(O56-300)*300),20000)))) -> 118800 | AK56: =if(F56="CMFA", if(O56<26,4000,O56*150),if(F56="CSCDA",if(33<O56<300, O56*150,if(O56>300,(45000+(O56-300)*75),5000)))) -> 29700 | AL56: =if(AE56="YES",0,IF(AND(I56>=DATE(2022,7,1),I56<=DATE(2023,6,30)),3,IF(AND(I56>=DATE(2023,7,1),I56<=DATE(2024,6,30)),2,IF(AND(I56>=DATE(2024,7,1),I56<=DATE(2025,6,30)),1,IF(AND(I56>=DATE(2025,7,1),I56<=DATE(2026,6,30)),0,"-"))))) -> 1 | AM56: =AK56*AL56 -> 29700 | AN56: {=_xlfn.xlookup(C56,'SCC Certificate Review'!C:C,'SCC Certificate Review'!F:F)}
A57: 54 | B57: Seaport Village Apartments | C57: Avanath Seaport, LP | D57: Long Beach | E57: Los Angeles | F57: CMFA | G57: Grant up to $10,000 | H57: 24-442 | I57: 45618 | K57: Avanath Capital | M57: Pacific Housing, Inc. | N57: FALSE | O57: 356 | P57: 144 | Q57: =P57/O57 -> 0.40449438 | R57: 5601 North Paramount Boulevard, Long Beach, Los Angeles | S57: 21600 | T57: =COUNTIF(Parcels!A:A, A57) > 0 -> TRUE | U57: =MAXIFS(Parcels!AC:AC, Parcels!A:A, A57) > 0 -> TRUE | V57: =SUMIF(Parcels!A:A, A57, Parcels!Z:Z) -> 94978083 | W57: =SUMIF(Parcels!$A:$A, $A57, Parcels!AC:AC) -> 41642082 | X57: =V57*P57/O57*0.9 -> 34576291 | Y57: =IF(W57=0, X57, W57) -> 41642082 | Z57: {=_xlfn.XLOOKUP( A57, Parcels!A:A, Parcels!AL:AL)} -> 0.01206499 | AA57: =W57*Z57 -> 502411.3 | AB57: =Y57*Z57 -> 502411.3 | AE57: NO | AJ57: =if(F57="CMFA", if(O57<16,10000,O57*600),if(F57="CSCDA",if(33<O57<300, O57*600,if(O57>300,(180000+(O57-300)*300),20000)))) -> 213600 | AK57: =if(F57="CMFA", if(O57<26,4000,O57*150),if(F57="CSCDA",if(33<O57<300, O57*150,if(O57>300,(45000+(O57-300)*75),5000)))) -> 53400 | AL57: =if(AE57="YES",0,IF(AND(I57>=DATE(2022,7,1),I57<=DATE(2023,6,30)),3,IF(AND(I57>=DATE(2023,7,1),I57<=DATE(2024,6,30)),2,IF(AND(I57>=DATE(2024,7,1),I57<=DATE(2025,6,30)),1,IF(AND(I57>=DATE(2025,7,1),I57<=DATE(2026,6,30)),0,"-"))))) -> 1 | AM57: =AK57*AL57 -> 53400 | AN57: {=_xlfn.xlookup(C57,'SCC Certificate Review'!C:C,'SCC Certificate Review'!F:F)} -> TRUE
A58: 55 | B58: 1457 Main Street Apartments | C58: 1457 Main Owner LP | D58: Los Angeles | E58: Los Angeles | F58: CMFA | H58: 24-443 | I58: 45618 | K58: Thrive Living | L58: Open House Group Co., Ltd | M58: Kingdom Development, Inc. | N58: FALSE | O58: 377 | P58: 151 | Q58: =P58/O58 -> 0.4005305 | R58: 1457 N Main St, Los Angeles, CA 90012 | S58: 22650 | T58: =COUNTIF(Parcels!A:A, A58) > 0 -> TRUE | U58: =MAXIFS(Parcels!AC:AC, Parcels!A:A, A58) > 0 -> TRUE | V58: =SUMIF(Parcels!A:A, A58, Parcels!Z:Z) -> 17293255 | W58: =SUMIF(Parcels!$A:$A, $A58, Parcels!AC:AC) -> 16976485 | X58: =V58*P58/O58*0.9 -> 6233828.5 | Y58: =IF(W58=0, X58, W58) -> 16976485 | Z58: {=_xlfn.XLOOKUP( A58, Parcels!A:A, Parcels!AL:AL)} -> 0.0118738 | AA58: =W58*Z58 -> 201575.39 | AB58: =Y58*Z58 -> 201575.39 | AE58: YES | AJ58: =if(F58="CMFA", if(O58<16,10000,O58*600),if(F58="CSCDA",if(33<O58<300, O58*600,if(O58>300,(180000+(O58-300)*300),20000)))) -> 226200 | AK58: =if(F58="CMFA", if(O58<26,4000,O58*150),if(F58="CSCDA",if(33<O58<300, O58*150,if(O58>300,(45000+(O58-300)*75),5000)))) -> 56550 | AL58: =if(AE58="YES",0,IF(AND(I58>=DATE(2022,7,1),I58<=DATE(2023,6,30)),3,IF(AND(I58>=DATE(2023,7,1),I58<=DATE(2024,6,30)),2,IF(AND(I58>=DATE(2024,7,1),I58<=DATE(2025,6,30)),1,IF(AND(I58>=DATE(2025,7,1),I58<=DATE(2026,6,30)),0,"-"))))) -> 0 | AM58: =AK58*AL58 -> 0 | AN58: {=_xlfn.xlookup(C58,'SCC Certificate Review'!C:C,'SCC Certificate Review'!F:F)} -> TRUE
A59: 56 | B59: Viewpoint Apartments | C59: 651 Addison LLC | D59: Berkeley | E59: Alameda | F59: CMFA | G59: Grant up to $10,000 | H59: 24-470 | I59: 45639 | K59: Bridge Housing | M59: Bridge Housing | N59: FALSE | O59: 94 | P59: 71 | R59: 651 Addison St, Berkeley, CA 94710 | S59: 10650 | T59: =COUNTIF(Parcels!A:A, A59) > 0 -> TRUE | U59: =MAXIFS(Parcels!AC:AC, Parcels!A:A, A59) > 0 -> FALSE | V59: =SUMIF(Parcels!A:A, A59, Parcels!Z:Z) -> 31838150 | W59: =SUMIF(Parcels!$A:$A, $A59, Parcels!AC:AC) -> 0 | X59: =V59*P59/O59*0.9 -> 21643168 | Y59: =IF(W59=0, X59, W59) -> 21643168 | Z59: {=_xlfn.XLOOKUP( A59, Parcels!A:A, Parcels!AL:AL)} -> 0.012323 | AA59: =W59*Z59 -> 0 | AB59: =Y59*Z59 -> 266708.76 | AD59: https://bridgehousing.com/properties/viewpoint/ | AJ59: =if(F59="CMFA", if(O59<16,10000,O59*600),if(F59="CSCDA",if(33<O59<300, O59*600,if(O59>300,(180000+(O59-300)*300),20000)))) -> 56400 | AK59: =if(F59="CMFA", if(O59<26,4000,O59*150),if(F59="CSCDA",if(33<O59<300, O59*150,if(O59>300,(45000+(O59-300)*75),5000)))) -> 14100 | AL59: =if(AE59="YES",0,IF(AND(I59>=DATE(2022,7,1),I59<=DATE(2023,6,30)),3,IF(AND(I59>=DATE(2023,7,1),I59<=DATE(2024,6,30)),2,IF(AND(I59>=DATE(2024,7,1),I59<=DATE(2025,6,30)),1,IF(AND(I59>=DATE(2025,7,1),I59<=DATE(2026,6,30)),0,"-"))))) -> 1 | AM59: =AK59*AL59 -> 14100 | AN59: {=_xlfn.xlookup(C59,'SCC Certificate Review'!C:C,'SCC Certificate Review'!F:F)}
A60: 59 | B60: Ventana Residences Apartments | C60: 99 Ocean Avenue LP | D60: San Francisco | E60: San Francisco | F60: CMFA | G60: Grant up to $10,000 | H60: 24-471 | I60: 45639 | K60: Presidio Bay Ventures, LLC | M60: Pacific Housing, Inc | N60: FALSE | O60: 193 | P60: 100 | R60: 99 OCEAN AVE SAN FRANCISCO, CA 94112-2548 | S60: 15000 | T60: =COUNTIF(Parcels!A:A, A60) > 0 -> TRUE | U60: =MAXIFS(Parcels!AC:AC, Parcels!A:A, A60) > 0 -> FALSE | V60: =SUMIF(Parcels!A:A, A60, Parcels!Z:Z) -> 82453101 | W60: =SUMIF(Parcels!$A:$A, $A60, Parcels!AC:AC) -> 0 | X60: =V60*P60/O60*0.9 -> 38449633 | Y60: =IF(W60=0, X60, W60) -> 38449633 | Z60: {=_xlfn.XLOOKUP( A60, Parcels!A:A, Parcels!AL:AL)} -> 0.012 | AA60: =W60*Z60 -> 0 | AB60: =Y60*Z60 -> 461395.59 | AE60: YES | AF60: 2023 | AJ60: =if(F60="CMFA", if(O60<16,10000,O60*600),if(F60="CSCDA",if(33<O60<300, O60*600,if(O60>300,(180000+(O60-300)*300),20000)))) -> 115800 | AK60: =if(F60="CMFA", if(O60<26,4000,O60*150),if(F60="CSCDA",if(33<O60<300, O60*150,if(O60>300,(45000+(O60-300)*75),5000)))) -> 28950 | AL60: =if(AE60="YES",0,IF(AND(I60>=DATE(2022,7,1),I60<=DATE(2023,6,30)),3,IF(AND(I60>=DATE(2023,7,1),I60<=DATE(2024,6,30)),2,IF(AND(I60>=DATE(2024,7,1),I60<=DATE(2025,6,30)),1,IF(AND(I60>=DATE(2025,7,1),I60<=DATE(2026,6,30)),0,"-"))))) -> 0 | AM60: =AK60*AL60 -> 0 | AN60: {=_xlfn.xlookup(C60,'SCC Certificate Review'!C:C,'SCC Certificate Review'!F:F)} -> TRUE
A61: 57 | B61: SoFi Los Gatos Creek Apartments | C61: BWF III Ethos CA Los Gatos Creek LP | D61: San Jose | E61: Santa Clara | F61: CMFA | G61: Grant up to $10,000 | H61: 24-472 | I61: 45639 | K61: Ethos Real Estate | L61: Bridge Investment Group | M61: Casa Major, Inc. | N61: FALSE | O61: 193 | P61: 193 | R61: 2130 Southwest Expy, San Jose, CA 95126 | S61: 28950 | T61: =COUNTIF(Parcels!A:A, A61) > 0 -> TRUE | U61: =MAXIFS(Parcels!AC:AC, Parcels!A:A, A61) > 0 -> TRUE | V61: =SUMIF(Parcels!A:A, A61, Parcels!Z:Z) -> 36559633 | W61: =SUMIF(Parcels!$A:$A, $A61, Parcels!AC:AC) -> 18850147 | X61: =V61*P61/O61*0.9 -> 32903670 | Y61: =IF(W61=0, X61, W61) -> 18850147 | Z61: {=_xlfn.XLOOKUP( A61, Parcels!A:A, Parcels!AL:AL)} -> 0.012401 | AA61: =W61*Z61 -> 233760.67 | AB61: =Y61*Z61 -> 233760.67 | AC61: https://www.ethos-re.com/news/sofi-at-los-gatos-creek-adam-siegman-comments-on-affordable-housing | AD61: https://www.losgatoslandingapts.com/ | AE61: NO | AF61: 1969 | AG61: 61.1 | AH61: 45657 | AJ61: =if(F61="CMFA", if(O61<16,10000,O61*600),if(F61="CSCDA",if(33<O61<300, O61*600,if(O61>300,(180000+(O61-300)*300),20000)))) -> 115800 | AK61: =if(F61="CMFA", if(O61<26,4000,O61*150),if(F61="CSCDA",if(33<O61<300, O61*150,if(O61>300,(45000+(O61-300)*75),5000)))) -> 28950 | AL61: =if(AE61="YES",0,IF(AND(I61>=DATE(2022,7,1),I61<=DATE(2023,6,30)),3,IF(AND(I61>=DATE(2023,7,1),I61<=DATE(2024,6,30)),2,IF(AND(I61>=DATE(2024,7,1),I61<=DATE(2025,6,30)),1,IF(AND(I61>=DATE(2025,7,1),I61<=DATE(2026,6,30)),0,"-"))))) -> 1 | AM61: =AK61*AL61 -> 28950 | AN61: {=_xlfn.xlookup(C61,'SCC Certificate Review'!C:C,'SCC Certificate Review'!F:F)} -> TRUE
A62: 58 | B62: Chaparral Apartments | C62: Post Chaparral, LP | D62: Palmdale | E62: Los Angeles | F62: CMFA | G62: Grant up to $10,000 | H62: 24-473 | I62: 45639 | K62: Post Investment Group | M62: Integrity Housing | N62: FALSE | O62: =72+164+60 -> 296 | P62: 296 | Q62: =P62/O62 -> 1 | R62: 38441 5th St W, Palmdale, CA 93551 | S62: 44400 | T62: =COUNTIF(Parcels!A:A, A62) > 0 -> TRUE | U62: =MAXIFS(Parcels!AC:AC, Parcels!A:A, A62) > 0 -> TRUE | V62: =SUMIF(Parcels!A:A, A62, Parcels!Z:Z) -> 14702565 | W62: =SUMIF(Parcels!$A:$A, $A62, Parcels!AC:AC) -> 4371074 | X62: =V62*P62/O62*0.9 -> 13232308 | Y62: =IF(W62=0, X62, W62) -> 4371074 | Z62: {=_xlfn.XLOOKUP( A62, Parcels!A:A, Parcels!AL:AL)} -> 0.01233086 | AA62: =W62*Z62 -> 53899.102 | AB62: =Y62*Z62 -> 53899.102 | AE62: NO | AJ62: =if(F62="CMFA", if(O62<16,10000,O62*600),if(F62="CSCDA",if(33<O62<300, O62*600,if(O62>300,(180000+(O62-300)*300),20000)))) -> 177600 | AK62: =if(F62="CMFA", if(O62<26,4000,O62*150),if(F62="CSCDA",if(33<O62<300, O62*150,if(O62>300,(45000+(O62-300)*75),5000)))) -> 44400 | AL62: =if(AE62="YES",0,IF(AND(I62>=DATE(2022,7,1),I62<=DATE(2023,6,30)),3,IF(AND(I62>=DATE(2023,7,1),I62<=DATE(2024,6,30)),2,IF(AND(I62>=DATE(2024,7,1),I62<=DATE(2025,6,30)),1,IF(AND(I62>=DATE(2025,7,1),I62<=DATE(2026,6,30)),0,"-"))))) -> 1 | AM62: =AK62*AL62 -> 44400 | AN62: {=_xlfn.xlookup(C62,'SCC Certificate Review'!C:C,'SCC Certificate Review'!F:F)} -> TRUE
A63: 60 | B63: HARKEN APARTMENTS | C63: Prometheus Real Estate Group | D63: Los Altos | E63: Santa Clara | F63: CMFA | H63: 25-065 | I63: 45688 | K63: Prometheus Real Estate Group, Inc. | M63: Hearthstone Housing Foundation | N63: FALSE | O63: =172+24 -> 196 | P63: 29 | R63: 5150 El Camino Real, Los Altos, CA | S63: 4350 | T63: =COUNTIF(Parcels!A:A, A63) > 0 -> TRUE | U63: =MAXIFS(Parcels!AC:AC, Parcels!A:A, A63) > 0 -> FALSE | V63: =SUMIF(Parcels!A:A, A63, Parcels!Z:Z) -> 50937984 | W63: =SUMIF(Parcels!$A:$A, $A63, Parcels!AC:AC) -> 0 | X63: =V63*P63/O63*0.9 -> 6783068.3 | Y63: =IF(W63=0, X63, W63) -> 6783068.3 | Z63: {=_xlfn.XLOOKUP( A63, Parcels!A:A, Parcels!AL:AL)} -> 0.011268 | AA63: =W63*Z63 -> 0 | AB63: =Y63*Z63 -> 76431.613 | AE63: YES | AJ63: =if(F63="CMFA", if(O63<16,10000,O63*600),if(F63="CSCDA",if(33<O63<300, O63*600,if(O63>300,(180000+(O63-300)*300),20000)))) -> 117600 | AK63: =if(F63="CMFA", if(O63<26,4000,O63*150),if(F63="CSCDA",if(33<O63<300, O63*150,if(O63>300,(45000+(O63-300)*75),5000)))) -> 29400 | AL63: =if(AE63="YES",0,IF(AND(I63>=DATE(2022,7,1),I63<=DATE(2023,6,30)),3,IF(AND(I63>=DATE(2023,7,1),I63<=DATE(2024,6,30)),2,IF(AND(I63>=DATE(2024,7,1),I63<=DATE(2025,6,30)),1,IF(AND(I63>=DATE(2025,7,1),I63<=DATE(2026,6,30)),0,"-"))))) -> 0 | AM63: =AK63*AL63 -> 0 | AN63: {=_xlfn.xlookup(C63,'SCC Certificate Review'!C:C,'SCC Certificate Review'!F:F)}
A64: 64 | B64: 333 Douglas Apartments | C64: 333 Douglas Street, LP, a California limited partnership | D64: Los Angeles | E64: Los Angeles | F64: CMFA | G64: Grant up to $10,000 (Charitable Affordable Housing) | H64: 25-080 | I64: 45709 | J64: TRUE | K64: Visionary Development Enterprises LLC | M64: Housing on Merit | N64: FALSE | O64: 33 | P64: 32 | Q64: =P64/O64 -> 0.96969697 | R64: 333 Douglas St, Los Angeles, CA | S64: 4800 | T64: =COUNTIF(Parcels!A:A, A64) > 0 -> TRUE | U64: =MAXIFS(Parcels!AC:AC, Parcels!A:A, A64) > 0 -> FALSE | V64: =SUMIF(Parcels!A:A, A64, Parcels!Z:Z) -> 1144440 | W64: =SUMIF(Parcels!$A:$A, $A64, Parcels!AC:AC) -> 0 | X64: =V64*P64/O64*0.9 -> 998784 | Y64: =IF(W64=0, X64, W64) -> 998784 | Z64: {=_xlfn.XLOOKUP( A64, Parcels!A:A, Parcels!AL:AL)} -> 0.0118738 | AA64: =W64*Z64 -> 0 | AB64: =Y64*Z64 -> 11859.361 | AJ64: =if(F64="CMFA", if(O64<16,10000,O64*600),if(F64="CSCDA",if(33<O64<300, O64*600,if(O64>300,(180000+(O64-300)*300),20000)))) -> 19800 | AK64: =if(F64="CMFA", if(O64<26,4000,O64*150),if(F64="CSCDA",if(33<O64<300, O64*150,if(O64>300,(45000+(O64-300)*75),5000)))) -> 4950 | AL64: =if(AE64="YES",0,IF(AND(I64>=DATE(2022,7,1),I64<=DATE(2023,6,30)),3,IF(AND(I64>=DATE(2023,7,1),I64<=DATE(2024,6,30)),2,IF(AND(I64>=DATE(2024,7,1),I64<=DATE(2025,6,30)),1,IF(AND(I64>=DATE(2025,7,1),I64<=DATE(2026,6,30)),0,"-"))))) -> 1 | AM64: =AK64*AL64 -> 4950 | AN64: {=_xlfn.xlookup(C64,'SCC Certificate Review'!C:C,'SCC Certificate Review'!F:F)}
A65: 61 | B65: 11422 Broadway Apartments | C65: BIF IMPACT OZ 1100 BROADWAY BLK, LP | D65: Los Angeles | E65: Los Angeles | F65: CMFA | H65: 25-081 | I65: 45709 | J65: TRUE | K65: SoLa Impact, LLC | M65: Housing on Merit | N65: FALSE | O65: 166 | P65: 165 | Q65: =P65/O65 -> 0.9939759 | R65: 11422 S Broadway, Los Angeles, CA 90061 | S65: 24750 | T65: =COUNTIF(Parcels!A:A, A65) > 0 -> TRUE | U65: =MAXIFS(Parcels!AC:AC, Parcels!A:A, A65) > 0 -> FALSE | V65: =SUMIF(Parcels!A:A, A65, Parcels!Z:Z) -> 2850591 | W65: =SUMIF(Parcels!$A:$A, $A65, Parcels!AC:AC) -> 0 | X65: =V65*P65/O65*0.9 -> 2550076.9 | Y65: =IF(W65=0, X65, W65) -> 2550076.9 | Z65: {=_xlfn.XLOOKUP( A65, Parcels!A:A, Parcels!AL:AL)} -> 0.0118738 | AA65: =W65*Z65 -> 0 | AB65: =Y65*Z65 -> 30279.103 | AE65: YES | AJ65: =if(F65="CMFA", if(O65<16,10000,O65*600),if(F65="CSCDA",if(33<O65<300, O65*600,if(O65>300,(180000+(O65-300)*300),20000)))) -> 99600 | AK65: =if(F65="CMFA", if(O65<26,4000,O65*150),if(F65="CSCDA",if(33<O65<300, O65*150,if(O65>300,(45000+(O65-300)*75),5000)))) -> 24900 | AL65: =if(AE65="YES",0,IF(AND(I65>=DATE(2022,7,1),I65<=DATE(2023,6,30)),3,IF(AND(I65>=DATE(2023,7,1),I65<=DATE(2024,6,30)),2,IF(AND(I65>=DATE(2024,7,1),I65<=DATE(2025,6,30)),1,IF(AND(I65>=DATE(2025,7,1),I65<=DATE(2026,6,30)),0,"-"))))) -> 0 | AM65: =AK65*AL65 -> 0 | AN65: {=_xlfn.xlookup(C65,'SCC Certificate Review'!C:C,'SCC Certificate Review'!F:F)}
A66: 63 | B66: The Enclave Apartments | C66: ENCLAVE LP, a California limited partnership | D66: Walnut Creek | E66: Contra Costa | F66: CMFA | G66: Grant up to $10,000 (Charitable Affordable Housing) | H66: 25-082 | I66: 45709 | K66: Tesseract Capital Group | M66: Housing on Merit | N66: FALSE | O66: 32 | P66: 32 | R66: 3081 N Main St, Walnut Creek, CA 94597 | S66: 4800 | T66: =COUNTIF(Parcels!A:A, A66) > 0 -> TRUE | U66: =MAXIFS(Parcels!AC:AC, Parcels!A:A, A66) > 0 -> FALSE | V66: =SUMIF(Parcels!A:A, A66, Parcels!Z:Z) -> 10616112 | W66: =SUMIF(Parcels!$A:$A, $A66, Parcels!AC:AC) -> 0 | X66: =V66*P66/O66*0.9 -> 9554500.8 | Y66: =IF(W66=0, X66, W66) -> 9554500.8 | Z66: {=_xlfn.XLOOKUP( A66, Parcels!A:A, Parcels!AL:AL)} -> 0.011015 | AA66: =W66*Z66 -> 0 | AB66: =Y66*Z66 -> 105242.83 | AJ66: =if(F66="CMFA", if(O66<16,10000,O66*600),if(F66="CSCDA",if(33<O66<300, O66*600,if(O66>300,(180000+(O66-300)*300),20000)))) -> 19200 | AK66: =if(F66="CMFA", if(O66<26,4000,O66*150),if(F66="CSCDA",if(33<O66<300, O66*150,if(O66>300,(45000+(O66-300)*75),5000)))) -> 4800 | AL66: =if(AE66="YES",0,IF(AND(I66>=DATE(2022,7,1),I66<=DATE(2023,6,30)),3,IF(AND(I66>=DATE(2023,7,1),I66<=DATE(2024,6,30)),2,IF(AND(I66>=DATE(2024,7,1),I66<=DATE(2025,6,30)),1,IF(AND(I66>=DATE(2025,7,1),I66<=DATE(2026,6,30)),0,"-"))))) -> 1 | AM66: =AK66*AL66 -> 4800 | AN66: {=_xlfn.xlookup(C66,'SCC Certificate Review'!C:C,'SCC Certificate Review'!F:F)} -> TRUE
A67: 62 | B67: Mansfield Micro Apartments | C67: 2533 Mansfield Owner, L.P., a California limited partnership | D67: Los Angeles | E67: Los Angeles | F67: CMFA | G67: Grant up to $10,000 (Charitable Affordable Housing) | H67: 25-084 | I67: 45709 | K67: CIM Group, LLC | M67: Pacific Housing, Inc. | N67: FALSE | O67: 116 | P67: 115 | Q67: =P67/O67 -> 0.99137931 | R67: 2533 S Mansfield Ave, Los Angeles, CA 90016 | S67: 17250 | T67: =COUNTIF(Parcels!A:A, A67) > 0 -> TRUE | U67: =MAXIFS(Parcels!AC:AC, Parcels!A:A, A67) > 0 -> FALSE | V67: =SUMIF(Parcels!A:A, A67, Parcels!Z:Z) -> 2065837 | W67: =SUMIF(Parcels!$A:$A, $A67, Parcels!AC:AC) -> 0 | X67: =V67*P67/O67*0.9 -> 1843225.3 | Y67: =IF(W67=0, X67, W67) -> 1843225.3 | Z67: {=_xlfn.XLOOKUP( A67, Parcels!A:A, Parcels!AL:AL)} -> 0.0118738 | AA67: =W67*Z67 -> 0 | AB67: =Y67*Z67 -> 21886.088 | AE67: YES | AJ67: =if(F67="CMFA", if(O67<16,10000,O67*600),if(F67="CSCDA",if(33<O67<300, O67*600,if(O67>300,(180000+(O67-300)*300),20000)))) -> 69600 | AK67: =if(F67="CMFA", if(O67<26,4000,O67*150),if(F67="CSCDA",if(33<O67<300, O67*150,if(O67>300,(45000+(O67-300)*75),5000)))) -> 17400 | AL67: =if(AE67="YES",0,IF(AND(I67>=DATE(2022,7,1),I67<=DATE(2023,6,30)),3,IF(AND(I67>=DATE(2023,7,1),I67<=DATE(2024,6,30)),2,IF(AND(I67>=DATE(2024,7,1),I67<=DATE(2025,6,30)),1,IF(AND(I67>=DATE(2025,7,1),I67<=DATE(2026,6,30)),0,"-"))))) -> 0 | AM67: =AK67*AL67 -> 0 | AN67: {=_xlfn.xlookup(C67,'SCC Certificate Review'!C:C,'SCC Certificate Review'!F:F)} -> TRUE
A68: 67 | B68: Coronado Palms Apartments | C68: Coronado Owner, LP | D68: Anaheim | E68: Orange | F68: CMFA | G68: Grant up to $10,000 (Charitable Affordable Housing) | H68: 25-102 | I68: 45730 | K68: TriWest Multifamily | M68: Kingdom Development, Inc. | N68: FALSE | O68: 169 | P68: 68 | R68: 1250 S. Euclid St., Anaheim, CA | S68: 10200 | T68: =COUNTIF(Parcels!A:A, A68) > 0 -> TRUE | U68: =MAXIFS(Parcels!AC:AC, Parcels!A:A, A68) > 0 -> FALSE | V68: =SUMIF(Parcels!A:A, A68, Parcels!Z:Z) -> 60690000 | W68: =SUMIF(Parcels!$A:$A, $A68, Parcels!AC:AC) -> 0 | X68: =V68*P68/O68*0.9 -> 21977680 | Y68: =IF(W68=0, X68, W68) -> 21977680 | Z68: {=_xlfn.XLOOKUP( A68, Parcels!A:A, Parcels!AL:AL)} -> 0.011372 | AA68: =W68*Z68 -> 0 | AB68: =Y68*Z68 -> 249930.18 | AJ68: =if(F68="CMFA", if(O68<16,10000,O68*600),if(F68="CSCDA",if(33<O68<300, O68*600,if(O68>300,(180000+(O68-300)*300),20000)))) -> 101400 | AK68: =if(F68="CMFA", if(O68<26,4000,O68*150),if(F68="CSCDA",if(33<O68<300, O68*150,if(O68>300,(45000+(O68-300)*75),5000)))) -> 25350 | AL68: =if(AE68="YES",0,IF(AND(I68>=DATE(2022,7,1),I68<=DATE(2023,6,30)),3,IF(AND(I68>=DATE(2023,7,1),I68<=DATE(2024,6,30)),2,IF(AND(I68>=DATE(2024,7,1),I68<=DATE(2025,6,30)),1,IF(AND(I68>=DATE(2025,7,1),I68<=DATE(2026,6,30)),0,"-"))))) -> 1 | AM68: =AK68*AL68 -> 25350 | AN68: {=_xlfn.xlookup(C68,'SCC Certificate Review'!C:C,'SCC Certificate Review'!F:F)} -> TRUE
A69: 65 | B69: Casa La Palma Apartments | C69: 7777 Valley View, L.P., a California limited partnership | D69: La Palma | E69: Orange | F69: CMFA | G69: Grant up to $10,000 (Charitable Affordable Housing) | H69: 25-103 | I69: 45730 | K69: Mariman & Co. | M69: AOF/Pacific Affordable Housing Corporation | N69: FALSE | O69: 272 | P69: 270 | R69: 7777 Valley View Street, La Palma, CA | S69: 40500 | T69: =COUNTIF(Parcels!A:A, A69) > 0 -> TRUE | U69: =MAXIFS(Parcels!AC:AC, Parcels!A:A, A69) > 0 -> TRUE | V69: =SUMIF(Parcels!A:A, A69, Parcels!Z:Z) -> 53482929 | W69: =SUMIF(Parcels!$A:$A, $A69, Parcels!AC:AC) -> 53482929 | X69: =V69*P69/O69*0.9 -> 47780705 | Y69: =IF(W69=0, X69, W69) -> 53482929 | Z69: {=_xlfn.XLOOKUP( A69, Parcels!A:A, Parcels!AL:AL)} -> 0.011162 | AA69: =W69*Z69 -> 596976.45 | AB69: =Y69*Z69 -> 596976.45 | AE69: NO | AF69: 1978 | AJ69: =if(F69="CMFA", if(O69<16,10000,O69*600),if(F69="CSCDA",if(33<O69<300, O69*600,if(O69>300,(180000+(O69-300)*300),20000)))) -> 163200 | AK69: =if(F69="CMFA", if(O69<26,4000,O69*150),if(F69="CSCDA",if(33<O69<300, O69*150,if(O69>300,(45000+(O69-300)*75),5000)))) -> 40800 | AL69: =if(AE69="YES",0,IF(AND(I69>=DATE(2022,7,1),I69<=DATE(2023,6,30)),3,IF(AND(I69>=DATE(2023,7,1),I69<=DATE(2024,6,30)),2,IF(AND(I69>=DATE(2024,7,1),I69<=DATE(2025,6,30)),1,IF(AND(I69>=DATE(2025,7,1),I69<=DATE(2026,6,30)),0,"-"))))) -> 1 | AM69: =AK69*AL69 -> 40800 | AN69: {=_xlfn.xlookup(C69,'SCC Certificate Review'!C:C,'SCC Certificate Review'!F:F)} -> TRUE
A70: 66 | B70: The Eaves Apartments | C70: 920 Gramercy Upwell, LP, a Delaware limited partnership | D70: Los Angeles | E70: Los Angeles | F70: CMFA | G70: Grant up to $10,000 (Charitable Affordable Housing) | H70: 25-104 | I70: 45730 | J70: TRUE | K70: Treehouse Community | M70: Butterfly’s Haven | N70: FALSE | O70: 13 | P70: 13 | Q70: =P70/O70 -> 1 | R70: 920 S. Gramercy Place, Los Angeles, CA | S70: 2500 | T70: =COUNTIF(Parcels!A:A, A70) > 0 -> TRUE | U70: =MAXIFS(Parcels!AC:AC, Parcels!A:A, A70) > 0 -> FALSE | V70: =SUMIF(Parcels!A:A, A70, Parcels!Z:Z) -> 7802661 | W70: =SUMIF(Parcels!$A:$A, $A70, Parcels!AC:AC) -> 0 | X70: =V70*P70/O70*0.9 -> 7022394.9 | Y70: =IF(W70=0, X70, W70) -> 7022394.9 | Z70: {=_xlfn.XLOOKUP( A70, Parcels!A:A, Parcels!AL:AL)} -> 0.0118738 | AA70: =W70*Z70 -> 0 | AB70: =Y70*Z70 -> 83382.513 | AJ70: =if(F70="CMFA", if(O70<16,10000,O70*600),if(F70="CSCDA",if(33<O70<300, O70*600,if(O70>300,(180000+(O70-300)*300),20000)))) -> 10000 | AK70: =if(F70="CMFA", if(O70<26,4000,O70*150),if(F70="CSCDA",if(33<O70<300, O70*150,if(O70>300,(45000+(O70-300)*75),5000)))) -> 4000 | AL70: =if(AE70="YES",0,IF(AND(I70>=DATE(2022,7,1),I70<=DATE(2023,6,30)),3,IF(AND(I70>=DATE(2023,7,1),I70<=DATE(2024,6,30)),2,IF(AND(I70>=DATE(2024,7,1),I70<=DATE(2025,6,30)),1,IF(AND(I70>=DATE(2025,7,1),I70<=DATE(2026,6,30)),0,"-"))))) -> 1 | AM70: =AK70*AL70 -> 4000 | AN70: {=_xlfn.xlookup(C70,'SCC Certificate Review'!C:C,'SCC Certificate Review'!F:F)}
A71: 69 | B71: Lindley Parc Apartments | C71: 10535 Lindley Affordable L.P. | D71: Los Angeles | E71: Los Angeles | F71: CMFA | G71: Grant up to $10,000 (Charitable Affordable Housing) | H71: 25-116 | I71: 45751 | J71: TRUE | K71: Taylor Equities | M71: Housing on Merit | N71: FALSE | O71: 50 | P71: 50 | Q71: =P71/O71 -> 1 | R71: 10535 Lindley Ave, Granada Hills, CA 91326 | S71: 4800 | T71: =COUNTIF(Parcels!A:A, A71) > 0 -> TRUE | U71: =MAXIFS(Parcels!AC:AC, Parcels!A:A, A71) > 0 -> FALSE | V71: =SUMIF(Parcels!A:A, A71, Parcels!Z:Z) -> 14877720 | W71: =SUMIF(Parcels!$A:$A, $A71, Parcels!AC:AC) -> 0 | X71: =V71*P71/O71*0.9 -> 13389948 | Y71: =IF(W71=0, X71, W71) -> 13389948 | Z71: {=_xlfn.XLOOKUP( A71, Parcels!A:A, Parcels!AL:AL)} -> 0.0118738 | AA71: =W71*Z71 -> 0 | AB71: =Y71*Z71 -> 158989.56 | AJ71: =if(F71="CMFA", if(O71<16,10000,O71*600),if(F71="CSCDA",if(33<O71<300, O71*600,if(O71>300,(180000+(O71-300)*300),20000)))) -> 30000 | AK71: =if(F71="CMFA", if(O71<26,4000,O71*150),if(F71="CSCDA",if(33<O71<300, O71*150,if(O71>300,(45000+(O71-300)*75),5000)))) -> 7500 | AL71: =if(AE71="YES",0,IF(AND(I71>=DATE(2022,7,1),I71<=DATE(2023,6,30)),3,IF(AND(I71>=DATE(2023,7,1),I71<=DATE(2024,6,30)),2,IF(AND(I71>=DATE(2024,7,1),I71<=DATE(2025,6,30)),1,IF(AND(I71>=DATE(2025,7,1),I71<=DATE(2026,6,30)),0,"-"))))) -> 1 | AM71: =AK71*AL71 -> 7500 | AN71: {=_xlfn.xlookup(C71,'SCC Certificate Review'!C:C,'SCC Certificate Review'!F:F)}
A72: 68 | B72: Candlewood North Apartments | C72: Post Candlewood North, LP | D72: Los Angeles | E72: Los Angeles | F72: CMFA | G72: Grant up to $10,000 (Charitable Affordable Housing) | H72: 25-117 | I72: 45751 | K72: Post Investment Group | M72: Integrity Housing | N72: FALSE | O72: 189 | P72: 189 | Q72: =P72/O72 -> 1 | R72: 9830 Reseda Blvd, Northridge, CA 91324 | S72: 28350 | T72: =COUNTIF(Parcels!A:A, A72) > 0 -> TRUE | U72: =MAXIFS(Parcels!AC:AC, Parcels!A:A, A72) > 0 -> FALSE | V72: =SUMIF(Parcels!A:A, A72, Parcels!Z:Z) -> 17292725 | W72: =SUMIF(Parcels!$A:$A, $A72, Parcels!AC:AC) -> 0 | X72: =V72*P72/O72*0.9 -> 15563452 | Y72: =IF(W72=0, X72, W72) -> 15563452 | Z72: {=_xlfn.XLOOKUP( A72, Parcels!A:A, Parcels!AL:AL)} -> 0.0118738 | AA72: =W72*Z72 -> 0 | AB72: =Y72*Z72 -> 184797.32 | AE72: NO | AF72: 1964 | AJ72: =if(F72="CMFA", if(O72<16,10000,O72*600),if(F72="CSCDA",if(33<O72<300, O72*600,if(O72>300,(180000+(O72-300)*300),20000)))) -> 113400 | AK72: =if(F72="CMFA", if(O72<26,4000,O72*150),if(F72="CSCDA",if(33<O72<300, O72*150,if(O72>300,(45000+(O72-300)*75),5000)))) -> 28350 | AL72: =if(AE72="YES",0,IF(AND(I72>=DATE(2022,7,1),I72<=DATE(2023,6,30)),3,IF(AND(I72>=DATE(2023,7,1),I72<=DATE(2024,6,30)),2,IF(AND(I72>=DATE(2024,7,1),I72<=DATE(2025,6,30)),1,IF(AND(I72>=DATE(2025,7,1),I72<=DATE(2026,6,30)),0,"-"))))) -> 1 | AM72: =AK72*AL72 -> 28350 | AN72: {=_xlfn.xlookup(C72,'SCC Certificate Review'!C:C,'SCC Certificate Review'!F:F)} -> TRUE
A73: 70 | B73: Terrace View Apartments | C73: SFF 4, LLC | D73: Daly City | E73: San Mateo | F73: CMFA | G73: Grant up to $10,000 (Charitable Affordable Housing) | H73: 25-144 | I73: 45772 | K73: The Sobrato Organization | M73: Pacific Housing, Inc. | N73: FALSE | O73: 122 | R73: 26 Terrace View Ct, Daly City, CA 94015 | S73: 18300 | T73: =COUNTIF(Parcels!A:A, A73) > 0 -> TRUE | U73: =MAXIFS(Parcels!AC:AC, Parcels!A:A, A73) > 0 -> FALSE | V73: =SUMIF(Parcels!A:A, A73, Parcels!Z:Z) -> 34811784 | W73: =SUMIF(Parcels!$A:$A, $A73, Parcels!AC:AC) -> 0 | X73: =V73*P73/O73*0.9 -> 0 | Y73: =IF(W73=0, X73, W73) -> 0 | Z73: {=_xlfn.XLOOKUP( A73, Parcels!A:A, Parcels!AL:AL)} -> 0.011602 | AA73: =W73*Z73 -> 0 | AB73: =Y73*Z73 -> 0 | AJ73: =if(F73="CMFA", if(O73<16,10000,O73*600),if(F73="CSCDA",if(33<O73<300, O73*600,if(O73>300,(180000+(O73-300)*300),20000)))) -> 73200 | AK73: =if(F73="CMFA", if(O73<26,4000,O73*150),if(F73="CSCDA",if(33<O73<300, O73*150,if(O73>300,(45000+(O73-300)*75),5000)))) -> 18300 | AL73: =if(AE73="YES",0,IF(AND(I73>=DATE(2022,7,1),I73<=DATE(2023,6,30)),3,IF(AND(I73>=DATE(2023,7,1),I73<=DATE(2024,6,30)),2,IF(AND(I73>=DATE(2024,7,1),I73<=DATE(2025,6,30)),1,IF(AND(I73>=DATE(2025,7,1),I73<=DATE(2026,6,30)),0,"-"))))) -> 1 | AM73: =AK73*AL73 -> 18300 | AN73: {=_xlfn.xlookup(C73,'SCC Certificate Review'!C:C,'SCC Certificate Review'!F:F)}
A74: 71 | B74: SoFi Redwood Park Apartments | C74: SFF 3, LLC | D74: Redwood City | E74: San Mateo | F74: CMFA | G74: Grant up to $10,000 (Charitable Affordable Housing) | H74: 25-145 | I74: 45772 | K74: The Sobrato Organization | M74: Pacific Housing, Inc. | N74: FALSE | O74: 112 | P74: 112 | R74: 1212 Whipple Ave, Redwood City, CA 94062 | S74: 16800 | T74: =COUNTIF(Parcels!A:A, A74) > 0 -> TRUE | U74: =MAXIFS(Parcels!AC:AC, Parcels!A:A, A74) > 0 -> FALSE | V74: =SUMIF(Parcels!A:A, A74, Parcels!Z:Z) -> 25240000 | W74: =SUMIF(Parcels!$A:$A, $A74, Parcels!AC:AC) -> 0 | X74: =V74*P74/O74*0.9 -> 22716000 | Y74: =IF(W74=0, X74, W74) -> 22716000 | Z74: {=_xlfn.XLOOKUP( A74, Parcels!A:A, Parcels!AL:AL)} -> 0.010941 | AA74: =W74*Z74 -> 0 | AB74: =Y74*Z74 -> 248535.76 | AD74: https://www.theheltsley.com/ | AH74: 45631 | AJ74: =if(F74="CMFA", if(O74<16,10000,O74*600),if(F74="CSCDA",if(33<O74<300, O74*600,if(O74>300,(180000+(O74-300)*300),20000)))) -> 67200 | AK74: =if(F74="CMFA", if(O74<26,4000,O74*150),if(F74="CSCDA",if(33<O74<300, O74*150,if(O74>300,(45000+(O74-300)*75),5000)))) -> 16800 | AL74: =if(AE74="YES",0,IF(AND(I74>=DATE(2022,7,1),I74<=DATE(2023,6,30)),3,IF(AND(I74>=DATE(2023,7,1),I74<=DATE(2024,6,30)),2,IF(AND(I74>=DATE(2024,7,1),I74<=DATE(2025,6,30)),1,IF(AND(I74>=DATE(2025,7,1),I74<=DATE(2026,6,30)),0,"-"))))) -> 1 | AM74: =AK74*AL74 -> 16800 | AN74: {=_xlfn.xlookup(C74,'SCC Certificate Review'!C:C,'SCC Certificate Review'!F:F)}
A75: 72 | B75: Waterbend Apartments | C75: AXIS FEE OWNER LP | D75: San Francisco | E75: San Francisco | F75: CMFA | H75: 25-219 | I75: 45772 | K75: TruAmerica Multifamily LLC | L75: Angeleno Investments LP | M75: Affordable Housing Access | N75: FALSE | O75: 136 | P75: 136 | R75: 5880 3rd St, San Francisco, CA 94124 | S75: 20400 | T75: =COUNTIF(Parcels!A:A, A75) > 0 -> TRUE | U75: =MAXIFS(Parcels!AC:AC, Parcels!A:A, A75) > 0 -> FALSE | V75: =SUMIF(Parcels!A:A, A75, Parcels!Z:Z) -> 73513835 | W75: =SUMIF(Parcels!$A:$A, $A75, Parcels!AC:AC) -> 0 | X75: =V75*P75/O75*0.9 -> 66162452 | Y75: =IF(W75=0, X75, W75) -> 66162452 | Z75: {=_xlfn.XLOOKUP( A75, Parcels!A:A, Parcels!AL:AL)} -> 0.012 | AA75: =W75*Z75 -> 0 | AB75: =Y75*Z75 -> 793949.42 | AE75: NO | AF75: 2016 | AJ75: =if(F75="CMFA", if(O75<16,10000,O75*600),if(F75="CSCDA",if(33<O75<300, O75*600,if(O75>300,(180000+(O75-300)*300),20000)))) -> 81600 | AK75: =if(F75="CMFA", if(O75<26,4000,O75*150),if(F75="CSCDA",if(33<O75<300, O75*150,if(O75>300,(45000+(O75-300)*75),5000)))) -> 20400 | AL75: =if(AE75="YES",0,IF(AND(I75>=DATE(2022,7,1),I75<=DATE(2023,6,30)),3,IF(AND(I75>=DATE(2023,7,1),I75<=DATE(2024,6,30)),2,IF(AND(I75>=DATE(2024,7,1),I75<=DATE(2025,6,30)),1,IF(AND(I75>=DATE(2025,7,1),I75<=DATE(2026,6,30)),0,"-"))))) -> 1 | AM75: =AK75*AL75 -> 20400 | AN75: {=_xlfn.xlookup(C75,'SCC Certificate Review'!C:C,'SCC Certificate Review'!F:F)}
A76: 73 | B76: 1540 W Court Apartments | C76: 1540 W. Court Street, LP | D76: Los Angeles | E76: Los Angeles | F76: CMFA | H76: 25-207 | I76: 45793 | K76: Visionary Development Enterprises LLC | M76: Housing on Merit | N76: FALSE | O76: 189 | P76: 148 | Q76: =P76/O76 -> 0.78306878 | R76: 1540 W Court St, Los Angeles, CA 90026 | S76: 22200 | T76: =COUNTIF(Parcels!A:A, A76) > 0 -> TRUE | U76: =MAXIFS(Parcels!AC:AC, Parcels!A:A, A76) > 0 -> FALSE | V76: =SUMIF(Parcels!A:A, A76, Parcels!Z:Z) -> 3138751 | W76: =SUMIF(Parcels!$A:$A, $A76, Parcels!AC:AC) -> 0 | X76: =V76*P76/O76*0.9 -> 2212072.1 | Y76: =IF(W76=0, X76, W76) -> 2212072.1 | Z76: {=_xlfn.XLOOKUP( A76, Parcels!A:A, Parcels!AL:AL)} -> 0.0118738 | AA76: =W76*Z76 -> 0 | AB76: =Y76*Z76 -> 26265.702 | AE76: YES | AJ76: =if(F76="CMFA", if(O76<16,10000,O76*600),if(F76="CSCDA",if(33<O76<300, O76*600,if(O76>300,(180000+(O76-300)*300),20000)))) -> 113400 | AK76: =if(F76="CMFA", if(O76<26,4000,O76*150),if(F76="CSCDA",if(33<O76<300, O76*150,if(O76>300,(45000+(O76-300)*75),5000)))) -> 28350 | AL76: =if(AE76="YES",0,IF(AND(I76>=DATE(2022,7,1),I76<=DATE(2023,6,30)),3,IF(AND(I76>=DATE(2023,7,1),I76<=DATE(2024,6,30)),2,IF(AND(I76>=DATE(2024,7,1),I76<=DATE(2025,6,30)),1,IF(AND(I76>=DATE(2025,7,1),I76<=DATE(2026,6,30)),0,"-"))))) -> 0 | AM76: =AK76*AL76 -> 0 | AN76: {=_xlfn.xlookup(C76,'SCC Certificate Review'!C:C,'SCC Certificate Review'!F:F)} -> TRUE
A77: 75 | B77: Palmilla Apartments | C77: BWF III Ethos CA Palmilla LP | D77: San Diego | E77: San Diego | F77: CMFA | G77: Grant up to $10,000 (Charitable Affordable Housing) | H77: 25-208 | I77: 45793 | K77: Ethos Real Estate | L77: Bridge Investment Group | M77: Casa Major, Inc. | N77: FALSE | O77: 203 | P77: 203 | R77: 5474 Reservoir Dr, San Diego, CA 92120 | S77: 30450 | T77: =COUNTIF(Parcels!A:A, A77) > 0 -> TRUE | U77: =MAXIFS(Parcels!AC:AC, Parcels!A:A, A77) > 0 -> FALSE | V77: =SUMIF(Parcels!A:A, A77, Parcels!Z:Z) -> 30350548 | W77: =SUMIF(Parcels!$A:$A, $A77, Parcels!AC:AC) -> 0 | X77: =V77*P77/O77*0.9 -> 27315493 | Y77: =IF(W77=0, X77, W77) -> 27315493 | Z77: {=_xlfn.XLOOKUP( A77, Parcels!A:A, Parcels!AL:AL)} -> 0.0125114 | AA77: =W77*Z77 -> 0 | AB77: =Y77*Z77 -> 341755.06 | AE77: NO | AJ77: =if(F77="CMFA", if(O77<16,10000,O77*600),if(F77="CSCDA",if(33<O77<300, O77*600,if(O77>300,(180000+(O77-300)*300),20000)))) -> 121800 | AK77: =if(F77="CMFA", if(O77<26,4000,O77*150),if(F77="CSCDA",if(33<O77<300, O77*150,if(O77>300,(45000+(O77-300)*75),5000)))) -> 30450 | AL77: =if(AE77="YES",0,IF(AND(I77>=DATE(2022,7,1),I77<=DATE(2023,6,30)),3,IF(AND(I77>=DATE(2023,7,1),I77<=DATE(2024,6,30)),2,IF(AND(I77>=DATE(2024,7,1),I77<=DATE(2025,6,30)),1,IF(AND(I77>=DATE(2025,7,1),I77<=DATE(2026,6,30)),0,"-"))))) -> 1 | AM77: =AK77*AL77 -> 30450 | AN77: {=_xlfn.xlookup(C77,'SCC Certificate Review'!C:C,'SCC Certificate Review'!F:F)}
A78: 74 | B78: Sol Haus Apartments | C78: Sol Haus Owner LP, California Limited Partnership | D78: San Diego | E78: San Diego | F78: CMFA | G78: Grant up to $10,000 (Charitable Affordable Housing) | H78: 25-209 | I78: 45793 | K78: CONAM Management Corporation | M78: Las Palmas Housing & Development Corporation | N78: FALSE | O78: 147 | P78: 145 | R78: 5040 Logan Avenue, San Diego, CA 92113 | S78: 22050 | T78: =COUNTIF(Parcels!A:A, A78) > 0 -> TRUE | U78: =MAXIFS(Parcels!AC:AC, Parcels!A:A, A78) > 0 -> FALSE | V78: =SUMIF(Parcels!A:A, A78, Parcels!Z:Z) -> 2804259 | W78: =SUMIF(Parcels!$A:$A, $A78, Parcels!AC:AC) -> 0 | X78: =V78*P78/O78*0.9 -> 2489495.2 | Y78: =IF(W78=0, X78, W78) -> 2489495.2 | Z78: {=_xlfn.XLOOKUP( A78, Parcels!A:A, Parcels!AL:AL)} -> 0.0125114 | AA78: =W78*Z78 -> 0 | AB78: =Y78*Z78 -> 31147.071 | AE78: YES | AJ78: =if(F78="CMFA", if(O78<16,10000,O78*600),if(F78="CSCDA",if(33<O78<300, O78*600,if(O78>300,(180000+(O78-300)*300),20000)))) -> 88200 | AK78: =if(F78="CMFA", if(O78<26,4000,O78*150),if(F78="CSCDA",if(33<O78<300, O78*150,if(O78>300,(45000+(O78-300)*75),5000)))) -> 22050 | AL78: =if(AE78="YES",0,IF(AND(I78>=DATE(2022,7,1),I78<=DATE(2023,6,30)),3,IF(AND(I78>=DATE(2023,7,1),I78<=DATE(2024,6,30)),2,IF(AND(I78>=DATE(2024,7,1),I78<=DATE(2025,6,30)),1,IF(AND(I78>=DATE(2025,7,1),I78<=DATE(2026,6,30)),0,"-"))))) -> 0 | AM78: =AK78*AL78 -> 0 | AN78: {=_xlfn.xlookup(C78,'SCC Certificate Review'!C:C,'SCC Certificate Review'!F:F)} -> TRUE
A79: 76 | B79: 1451 W. MLK Boulevard Apartments | C79: 1451 W. MLK Boulevard Apartments | D79: Los Angeles | E79: Los Angeles | F79: CMFA | H79: Proposed | I79: 45814 | K79: SoLa Impact, LLC | M79: Housing on Merit | N79: FALSE | O79: 50 | P79: 49 | Q79: =P79/O79 -> 0.98 | R79: 1451 W. MLK Blvd, Los Angeles, CA | S79: 7350 | T79: =COUNTIF(Parcels!A:A, A79) > 0 -> TRUE | U79: =MAXIFS(Parcels!AC:AC, Parcels!A:A, A79) > 0 -> FALSE | V79: =SUMIF(Parcels!A:A, A79, Parcels!Z:Z) -> 1569525 | W79: =SUMIF(Parcels!$A:$A, $A79, Parcels!AC:AC) -> 0 | X79: =V79*P79/O79*0.9 -> 1384321.1 | Y79: =IF(W79=0, X79, W79) -> 1384321.1 | Z79: {=_xlfn.XLOOKUP( A79, Parcels!A:A, Parcels!AL:AL)} -> 0.0118738 | AA79: =W79*Z79 -> 0 | AB79: =Y79*Z79 -> 16437.151 | AE79: YES | AJ79: =if(F79="CMFA", if(O79<16,10000,O79*600),if(F79="CSCDA",if(33<O79<300, O79*600,if(O79>300,(180000+(O79-300)*300),20000)))) -> 30000 | AK79: =if(F79="CMFA", if(O79<26,4000,O79*150),if(F79="CSCDA",if(33<O79<300, O79*150,if(O79>300,(45000+(O79-300)*75),5000)))) -> 7500 | AL79: =if(AE79="YES",0,IF(AND(I79>=DATE(2022,7,1),I79<=DATE(2023,6,30)),3,IF(AND(I79>=DATE(2023,7,1),I79<=DATE(2024,6,30)),2,IF(AND(I79>=DATE(2024,7,1),I79<=DATE(2025,6,30)),1,IF(AND(I79>=DATE(2025,7,1),I79<=DATE(2026,6,30)),0,"-"))))) -> 0 | AM79: =AK79*AL79 -> 0 | AN79: {=_xlfn.xlookup(C79,'SCC Certificate Review'!C:C,'SCC Certificate Review'!F:F)}
A80: 78 | B80: Bella Vista at Hilltop Apartments | C80: Bella Vista Owner, LP | D80: Richmond | E80: Contra Costa | F80: CMFA | G80: Grant up to $10,000 (Charitable Affordable Housing) | H80: 25-281 | I80: 45835 | K80: Kennedy Wilson | L80: Vintage Housing Holdings | M80: Hearthstone Housing Foundation | N80: FALSE | O80: 1008 | P80: 1008 | R80: 3400 Richmond Pkwy, Richmond, CA 94806 | S80: 98100 | T80: =COUNTIF(Parcels!A:A, A80) > 0 -> TRUE | U80: =MAXIFS(Parcels!AC:AC, Parcels!A:A, A80) > 0 -> FALSE | V80: =SUMIF(Parcels!A:A, A80, Parcels!Z:Z) -> 222047798 | W80: =SUMIF(Parcels!$A:$A, $A80, Parcels!AC:AC) -> 0 | X80: =V80*P80/O80*0.9 -> 1.9984302e+08 | Y80: =IF(W80=0, X80, W80) -> 1.9984302e+08 | Z80: {=_xlfn.XLOOKUP( A80, Parcels!A:A, Parcels!AL:AL)} -> 0.014192 | AA80: =W80*Z80 -> 0 | AB80: =Y80*Z80 -> 2836172.1 | AC80: https://www.cmfa-ca.com/wp-content/uploads/2025/01/CMFA-Staff-Reports-01-10-25.pdf | AE80: NO | AJ80: =if(F80="CMFA", if(O80<16,10000,O80*600),if(F80="CSCDA",if(33<O80<300, O80*600,if(O80>300,(180000+(O80-300)*300),20000)))) -> 604800 | AK80: =if(F80="CMFA", if(O80<26,4000,O80*150),if(F80="CSCDA",if(33<O80<300, O80*150,if(O80>300,(45000+(O80-300)*75),5000)))) -> 151200 | AL80: =if(AE80="YES",0,IF(AND(I80>=DATE(2022,7,1),I80<=DATE(2023,6,30)),3,IF(AND(I80>=DATE(2023,7,1),I80<=DATE(2024,6,30)),2,IF(AND(I80>=DATE(2024,7,1),I80<=DATE(2025,6,30)),1,IF(AND(I80>=DATE(2025,7,1),I80<=DATE(2026,6,30)),0,"-"))))) -> 1 | AM80: =AK80*AL80 -> 151200 | AN80: {=_xlfn.xlookup(C80,'SCC Certificate Review'!C:C,'SCC Certificate Review'!F:F)} -> TRUE
A81: 80 | B81: 4101 Somerset Dr. Apartments | C81: 6 SIOF 4101 Somerset Dr, LP | D81: Los Angeles | E81: Los Angeles | F81: CMFA | G81: Grant up to $10,000 (Charitable Affordable Housing) | H81: 25-282 | I81: 45835 | K81: SoLa Impact, LLC | M81: Housing on Merit | N81: FALSE | O81: 36 | P81: 35 | Q81: =P81/O81 -> 0.97222222 | R81: 4101 Somerset Drive, Los Angeles, CA | S81: 5250 | T81: =COUNTIF(Parcels!A:A, A81) > 0 -> TRUE | U81: =MAXIFS(Parcels!AC:AC, Parcels!A:A, A81) > 0 -> FALSE | V81: =SUMIF(Parcels!A:A, A81, Parcels!Z:Z) -> 3451872 | W81: =SUMIF(Parcels!$A:$A, $A81, Parcels!AC:AC) -> 0 | X81: =V81*P81/O81*0.9 -> 3020388 | Y81: =IF(W81=0, X81, W81) -> 3020388 | Z81: {=_xlfn.XLOOKUP( A81, Parcels!A:A, Parcels!AL:AL)} -> 0.0118738 | AA81: =W81*Z81 -> 0 | AB81: =Y81*Z81 -> 35863.483 | AE81: YES | AJ81: =if(F81="CMFA", if(O81<16,10000,O81*600),if(F81="CSCDA",if(33<O81<300, O81*600,if(O81>300,(180000+(O81-300)*300),20000)))) -> 21600 | AK81: =if(F81="CMFA", if(O81<26,4000,O81*150),if(F81="CSCDA",if(33<O81<300, O81*150,if(O81>300,(45000+(O81-300)*75),5000)))) -> 5400 | AL81: =if(AE81="YES",0,IF(AND(I81>=DATE(2022,7,1),I81<=DATE(2023,6,30)),3,IF(AND(I81>=DATE(2023,7,1),I81<=DATE(2024,6,30)),2,IF(AND(I81>=DATE(2024,7,1),I81<=DATE(2025,6,30)),1,IF(AND(I81>=DATE(2025,7,1),I81<=DATE(2026,6,30)),0,"-"))))) -> 0 | AM81: =AK81*AL81 -> 0 | AN81: {=_xlfn.xlookup(C81,'SCC Certificate Review'!C:C,'SCC Certificate Review'!F:F)}
A82: 81 | B82: 321 E. Florence Apartments | C82: 3 SIOF 321 E Florence Ave, LP | D82: Los Angeles | E82: Los Angeles | F82: CMFA | G82: Grant up to $10,000 (Charitable Affordable Housing) | H82: 25-283 | I82: 45835 | K82: SoLa Impact, LLC | M82: Housing on Merit | N82: FALSE | O82: 31 | P82: 30 | Q82: =P82/O82 -> 0.96774194 | R82: 321 E. Florence Ave, Los Angeles, CA | S82: 4500 | T82: =COUNTIF(Parcels!A:A, A82) > 0 -> TRUE | U82: =MAXIFS(Parcels!AC:AC, Parcels!A:A, A82) > 0 -> FALSE | V82: =SUMIF(Parcels!A:A, A82, Parcels!Z:Z) -> 5960901 | W82: =SUMIF(Parcels!$A:$A, $A82, Parcels!AC:AC) -> 0 | X82: =V82*P82/O82*0.9 -> 5191752.5 | Y82: =IF(W82=0, X82, W82) -> 5191752.5 | Z82: {=_xlfn.XLOOKUP( A82, Parcels!A:A, Parcels!AL:AL)} -> 0.0118738 | AA82: =W82*Z82 -> 0 | AB82: =Y82*Z82 -> 61645.831 | AE82: YES | AJ82: =if(F82="CMFA", if(O82<16,10000,O82*600),if(F82="CSCDA",if(33<O82<300, O82*600,if(O82>300,(180000+(O82-300)*300),20000)))) -> 18600 | AK82: =if(F82="CMFA", if(O82<26,4000,O82*150),if(F82="CSCDA",if(33<O82<300, O82*150,if(O82>300,(45000+(O82-300)*75),5000)))) -> 4650 | AL82: =if(AE82="YES",0,IF(AND(I82>=DATE(2022,7,1),I82<=DATE(2023,6,30)),3,IF(AND(I82>=DATE(2023,7,1),I82<=DATE(2024,6,30)),2,IF(AND(I82>=DATE(2024,7,1),I82<=DATE(2025,6,30)),1,IF(AND(I82>=DATE(2025,7,1),I82<=DATE(2026,6,30)),0,"-"))))) -> 0 | AM82: =AK82*AL82 -> 0 | AN82: {=_xlfn.xlookup(C82,'SCC Certificate Review'!C:C,'SCC Certificate Review'!F:F)}
A83: 82 | B83: 9300 Compton Ave. Apartments | C83: 6 SIOF 9300 Compton Ave, LP | D83: Los Angeles | E83: Los Angeles | F83: CMFA | G83: Grant up to $10,000 (Charitable Affordable Housing) | H83: 25-284 | I83: 45835 | K83: SoLa Impact, LLC | M83: Housing on Merit | N83: FALSE | O83: 20 | P83: 19 | Q83: =P83/O83 -> 0.95 | R83: 9300 Compton Ave., Los Angeles, CA | S83: 2850 | T83: =COUNTIF(Parcels!A:A, A83) > 0 -> TRUE | U83: =MAXIFS(Parcels!AC:AC, Parcels!A:A, A83) > 0 -> FALSE | V83: =SUMIF(Parcels!A:A, A83, Parcels!Z:Z) -> 595337 | W83: =SUMIF(Parcels!$A:$A, $A83, Parcels!AC:AC) -> 0 | X83: =V83*P83/O83*0.9 -> 509013.14 | Y83: =IF(W83=0, X83, W83) -> 509013.14 | Z83: {=_xlfn.XLOOKUP( A83, Parcels!A:A, Parcels!AL:AL)} -> 0.0118738 | AA83: =W83*Z83 -> 0 | AB83: =Y83*Z83 -> 6043.9202 | AE83: YES | AJ83: =if(F83="CMFA", if(O83<16,10000,O83*600),if(F83="CSCDA",if(33<O83<300, O83*600,if(O83>300,(180000+(O83-300)*300),20000)))) -> 12000 | AK83: =if(F83="CMFA", if(O83<26,4000,O83*150),if(F83="CSCDA",if(33<O83<300, O83*150,if(O83>300,(45000+(O83-300)*75),5000)))) -> 4000 | AL83: =if(AE83="YES",0,IF(AND(I83>=DATE(2022,7,1),I83<=DATE(2023,6,30)),3,IF(AND(I83>=DATE(2023,7,1),I83<=DATE(2024,6,30)),2,IF(AND(I83>=DATE(2024,7,1),I83<=DATE(2025,6,30)),1,IF(AND(I83>=DATE(2025,7,1),I83<=DATE(2026,6,30)),0,"-"))))) -> 0 | AM83: =AK83*AL83 -> 0 | AN83: {=_xlfn.xlookup(C83,'SCC Certificate Review'!C:C,'SCC Certificate Review'!F:F)}
A84: 83 | B84: 6401 S. Avalon Blvd. Apartments | C84: 6 SIOF 6401 S Avalon Blvd, LP | D84: Los Angeles | E84: Los Angeles | F84: CMFA | G84: Grant up to $10,000 (Charitable Affordable Housing) | H84: 25-285 | I84: 45835 | K84: SoLa Impact, LLC | M84: Housing on Merit | N84: FALSE | O84: 28 | P84: 27 | Q84: =P84/O84 -> 0.96428571 | R84: 6401 S. Avalon Blvd., Los Angeles, CA | S84: 4050 | T84: =COUNTIF(Parcels!A:A, A84) > 0 -> TRUE | U84: =MAXIFS(Parcels!AC:AC, Parcels!A:A, A84) > 0 -> FALSE | V84: =SUMIF(Parcels!A:A, A84, Parcels!Z:Z) -> 426520 | W84: =SUMIF(Parcels!$A:$A, $A84, Parcels!AC:AC) -> 0 | X84: =V84*P84/O84*0.9 -> 370158.43 | Y84: =IF(W84=0, X84, W84) -> 370158.43 | Z84: {=_xlfn.XLOOKUP( A84, Parcels!A:A, Parcels!AL:AL)} -> 0.0118738 | AA84: =W84*Z84 -> 0 | AB84: =Y84*Z84 -> 4395.1871 | AE84: YES | AJ84: =if(F84="CMFA", if(O84<16,10000,O84*600),if(F84="CSCDA",if(33<O84<300, O84*600,if(O84>300,(180000+(O84-300)*300),20000)))) -> 16800 | AK84: =if(F84="CMFA", if(O84<26,4000,O84*150),if(F84="CSCDA",if(33<O84<300, O84*150,if(O84>300,(45000+(O84-300)*75),5000)))) -> 4200 | AL84: =if(AE84="YES",0,IF(AND(I84>=DATE(2022,7,1),I84<=DATE(2023,6,30)),3,IF(AND(I84>=DATE(2023,7,1),I84<=DATE(2024,6,30)),2,IF(AND(I84>=DATE(2024,7,1),I84<=DATE(2025,6,30)),1,IF(AND(I84>=DATE(2025,7,1),I84<=DATE(2026,6,30)),0,"-"))))) -> 0 | AM84: =AK84*AL84 -> 0 | AN84: {=_xlfn.xlookup(C84,'SCC Certificate Review'!C:C,'SCC Certificate Review'!F:F)}
A85: 84 | B85: 9515 Compton Ave. Apartments | C85: 6 SIOF 9515 Compton Ave, LP | D85: Los Angeles | E85: Los Angeles | F85: CMFA | G85: Grant up to $10,000 (Charitable Affordable Housing) | H85: 25-286 | I85: 45835 | K85: SoLa Impact, LLC | M85: Housing on Merit | N85: FALSE | O85: 21 | P85: 20 | Q85: =P85/O85 -> 0.95238095 | R85: 9515 Compton Avenue, Los Angeles, CA | S85: 3000 | T85: =COUNTIF(Parcels!A:A, A85) > 0 -> TRUE | U85: =MAXIFS(Parcels!AC:AC, Parcels!A:A, A85) > 0 -> FALSE | V85: =SUMIF(Parcels!A:A, A85, Parcels!Z:Z) -> 1352393 | W85: =SUMIF(Parcels!$A:$A, $A85, Parcels!AC:AC) -> 0 | X85: =V85*P85/O85*0.9 -> 1159194 | Y85: =IF(W85=0, X85, W85) -> 1159194 | Z85: {=_xlfn.XLOOKUP( A85, Parcels!A:A, Parcels!AL:AL)} -> 0.0118738 | AA85: =W85*Z85 -> 0 | AB85: =Y85*Z85 -> 13764.038 | AE85: YES | AJ85: =if(F85="CMFA", if(O85<16,10000,O85*600),if(F85="CSCDA",if(33<O85<300, O85*600,if(O85>300,(180000+(O85-300)*300),20000)))) -> 12600 | AK85: =if(F85="CMFA", if(O85<26,4000,O85*150),if(F85="CSCDA",if(33<O85<300, O85*150,if(O85>300,(45000+(O85-300)*75),5000)))) -> 4000 | AL85: =if(AE85="YES",0,IF(AND(I85>=DATE(2022,7,1),I85<=DATE(2023,6,30)),3,IF(AND(I85>=DATE(2023,7,1),I85<=DATE(2024,6,30)),2,IF(AND(I85>=DATE(2024,7,1),I85<=DATE(2025,6,30)),1,IF(AND(I85>=DATE(2025,7,1),I85<=DATE(2026,6,30)),0,"-"))))) -> 0 | AM85: =AK85*AL85 -> 0 | AN85: {=_xlfn.xlookup(C85,'SCC Certificate Review'!C:C,'SCC Certificate Review'!F:F)}
A86: 79 | B86: 10811 S. Compton Ave Apartments | C86: 10811 S. Compton Ave Apartments | D86: Los Angeles | E86: Los Angeles | F86: CMFA | H86: 25-287 | I86: 45835 | K86: SoLa Impact, LLC | M86: Housing on Merit | N86: FALSE | O86: 29 | P86: 28 | Q86: =P86/O86 -> 0.96551724 | R86: 10811 S. Compton Avenue, Los Angeles, CA | S86: 4200 | T86: =COUNTIF(Parcels!A:A, A86) > 0 -> TRUE | U86: =MAXIFS(Parcels!AC:AC, Parcels!A:A, A86) > 0 -> FALSE | V86: =SUMIF(Parcels!A:A, A86, Parcels!Z:Z) -> 689784 | W86: =SUMIF(Parcels!$A:$A, $A86, Parcels!AC:AC) -> 0 | X86: =V86*P86/O86*0.9 -> 599398.51 | Y86: =IF(W86=0, X86, W86) -> 599398.51 | Z86: {=_xlfn.XLOOKUP( A86, Parcels!A:A, Parcels!AL:AL)} -> 0.0118738 | AA86: =W86*Z86 -> 0 | AB86: =Y86*Z86 -> 7117.138 | AE86: YES | AJ86: =if(F86="CMFA", if(O86<16,10000,O86*600),if(F86="CSCDA",if(33<O86<300, O86*600,if(O86>300,(180000+(O86-300)*300),20000)))) -> 17400 | AK86: =if(F86="CMFA", if(O86<26,4000,O86*150),if(F86="CSCDA",if(33<O86<300, O86*150,if(O86>300,(45000+(O86-300)*75),5000)))) -> 4350 | AL86: =if(AE86="YES",0,IF(AND(I86>=DATE(2022,7,1),I86<=DATE(2023,6,30)),3,IF(AND(I86>=DATE(2023,7,1),I86<=DATE(2024,6,30)),2,IF(AND(I86>=DATE(2024,7,1),I86<=DATE(2025,6,30)),1,IF(AND(I86>=DATE(2025,7,1),I86<=DATE(2026,6,30)),0,"-"))))) -> 0 | AM86: =AK86*AL86 -> 0 | AN86: {=_xlfn.xlookup(C86,'SCC Certificate Review'!C:C,'SCC Certificate Review'!F:F)}
A87: 85 | B87: 569 W. 6th Street Apartments | C87: SIOF 5 Properties, LP, California limited partnership | D87: Los Angeles | E87: Los Angeles | F87: CMFA | G87: Grant up to $10,000 (Charitable Affordable Housing) | H87: 25-288 | I87: 45835 | K87: SoLa Impact, LLC | M87: Housing on Merit | N87: FALSE | O87: 48 | P87: 47 | Q87: =P87/O87 -> 0.97916667 | R87: 569 W. 6th Street, San Pedro, CA | S87: 7050 | T87: =COUNTIF(Parcels!A:A, A87) > 0 -> TRUE | U87: =MAXIFS(Parcels!AC:AC, Parcels!A:A, A87) > 0 -> FALSE | V87: =SUMIF(Parcels!A:A, A87, Parcels!Z:Z) -> 1363864 | W87: =SUMIF(Parcels!$A:$A, $A87, Parcels!AC:AC) -> 0 | X87: =V87*P87/O87*0.9 -> 1201905.1 | Y87: =IF(W87=0, X87, W87) -> 1201905.1 | Z87: {=_xlfn.XLOOKUP( A87, Parcels!A:A, Parcels!AL:AL)} -> 0.0118738 | AA87: =W87*Z87 -> 0 | AB87: =Y87*Z87 -> 14271.181 | AE87: YES | AJ87: =if(F87="CMFA", if(O87<16,10000,O87*600),if(F87="CSCDA",if(33<O87<300, O87*600,if(O87>300,(180000+(O87-300)*300),20000)))) -> 28800 | AK87: =if(F87="CMFA", if(O87<26,4000,O87*150),if(F87="CSCDA",if(33<O87<300, O87*150,if(O87>300,(45000+(O87-300)*75),5000)))) -> 7200 | AL87: =if(AE87="YES",0,IF(AND(I87>=DATE(2022,7,1),I87<=DATE(2023,6,30)),3,IF(AND(I87>=DATE(2023,7,1),I87<=DATE(2024,6,30)),2,IF(AND(I87>=DATE(2024,7,1),I87<=DATE(2025,6,30)),1,IF(AND(I87>=DATE(2025,7,1),I87<=DATE(2026,6,30)),0,"-"))))) -> 0 | AM87: =AK87*AL87 -> 0 | AN87: {=_xlfn.xlookup(C87,'SCC Certificate Review'!C:C,'SCC Certificate Review'!F:F)}
A88: 86 | B88: 685 W. 4th St Apartments | C88: 2 SIOF 685 W Fourth St, LP, Delaware limited partnership | D88: Los Angeles | E88: Los Angeles | F88: CMFA | G88: Grant up to $10,000 (Charitable Affordable Housing) | H88: 25-289 | I88: 45835 | K88: SoLa Impact, LLC | M88: Housing on Merit | N88: FALSE | O88: 28 | P88: 27 | Q88: =P88/O88 -> 0.96428571 | R88: 685 W. 4th St., Los Angeles, CA | S88: 4050 | T88: =COUNTIF(Parcels!A:A, A88) > 0 -> TRUE | U88: =MAXIFS(Parcels!AC:AC, Parcels!A:A, A88) > 0 -> FALSE | V88: =SUMIF(Parcels!A:A, A88, Parcels!Z:Z) -> 3002337 | W88: =SUMIF(Parcels!$A:$A, $A88, Parcels!AC:AC) -> 0 | X88: =V88*P88/O88*0.9 -> 2605599.6 | Y88: =IF(W88=0, X88, W88) -> 2605599.6 | Z88: {=_xlfn.XLOOKUP( A88, Parcels!A:A, Parcels!AL:AL)} -> 0.0118738 | AA88: =W88*Z88 -> 0 | AB88: =Y88*Z88 -> 30938.369 | AE88: YES | AJ88: =if(F88="CMFA", if(O88<16,10000,O88*600),if(F88="CSCDA",if(33<O88<300, O88*600,if(O88>300,(180000+(O88-300)*300),20000)))) -> 16800 | AK88: =if(F88="CMFA", if(O88<26,4000,O88*150),if(F88="CSCDA",if(33<O88<300, O88*150,if(O88>300,(45000+(O88-300)*75),5000)))) -> 4200 | AL88: =if(AE88="YES",0,IF(AND(I88>=DATE(2022,7,1),I88<=DATE(2023,6,30)),3,IF(AND(I88>=DATE(2023,7,1),I88<=DATE(2024,6,30)),2,IF(AND(I88>=DATE(2024,7,1),I88<=DATE(2025,6,30)),1,IF(AND(I88>=DATE(2025,7,1),I88<=DATE(2026,6,30)),0,"-"))))) -> 0 | AM88: =AK88*AL88 -> 0 | AN88: {=_xlfn.xlookup(C88,'SCC Certificate Review'!C:C,'SCC Certificate Review'!F:F)}
A89: 87 | B89: Chadwick Apartments | C89: Chadwick Owner, LP | D89: Los Angeles | E89: Los Angeles | F89: CMFA | G89: Grant up to $10,000 (Charitable Affordable Housing) | H89: 25-290 | I89: 45835 | K89: Vintage Housing Holdings | L89: Kennedy Wilson | M89: Pacific Housing, Inc | N89: FALSE | O89: 687 | P89: 687 | Q89: =P89/O89 -> 1 | R89: 209 Westmoreland Ave, Los Angeles, CA 90004 | S89: 74025 | T89: =COUNTIF(Parcels!A:A, A89) > 0 -> TRUE | U89: =MAXIFS(Parcels!AC:AC, Parcels!A:A, A89) > 0 -> FALSE | V89: =SUMIF(Parcels!A:A, A89, Parcels!Z:Z) -> 129082596 | W89: =SUMIF(Parcels!$A:$A, $A89, Parcels!AC:AC) -> 0 | X89: =V89*P89/O89*0.9 -> 1.1617434e+08 | Y89: =IF(W89=0, X89, W89) -> 1.1617434e+08 | Z89: {=_xlfn.XLOOKUP( A89, Parcels!A:A, Parcels!AL:AL)} -> 0.0118738 | AA89: =W89*Z89 -> 0 | AB89: =Y89*Z89 -> 1379430.8 | AE89: NO | AJ89: =if(F89="CMFA", if(O89<16,10000,O89*600),if(F89="CSCDA",if(33<O89<300, O89*600,if(O89>300,(180000+(O89-300)*300),20000)))) -> 412200 | AK89: =if(F89="CMFA", if(O89<26,4000,O89*150),if(F89="CSCDA",if(33<O89<300, O89*150,if(O89>300,(45000+(O89-300)*75),5000)))) -> 103050 | AL89: =if(AE89="YES",0,IF(AND(I89>=DATE(2022,7,1),I89<=DATE(2023,6,30)),3,IF(AND(I89>=DATE(2023,7,1),I89<=DATE(2024,6,30)),2,IF(AND(I89>=DATE(2024,7,1),I89<=DATE(2025,6,30)),1,IF(AND(I89>=DATE(2025,7,1),I89<=DATE(2026,6,30)),0,"-"))))) -> 1 | AM89: =AK89*AL89 -> 103050 | AN89: {=_xlfn.xlookup(C89,'SCC Certificate Review'!C:C,'SCC Certificate Review'!F:F)} -> TRUE
A90: 77 | B90: 11630 S. Main Street Apartments | C90: 4 SIOF 11630 S MAIN ST, LP | D90: Los Angeles | E90: Los Angeles | F90: CMFA | H90: 25-291 | I90: 45835 | K90: SoLa Impact, LLC | M90: Housing on Merit | N90: FALSE | O90: 84 | P90: 17 | Q90: =P90/O90 -> 0.20238095 | R90: 11630 Main St, Los Angeles, CA 90061 | S90: 2550 | T90: =COUNTIF(Parcels!A:A, A90) > 0 -> TRUE | U90: =MAXIFS(Parcels!AC:AC, Parcels!A:A, A90) > 0 -> FALSE | V90: =SUMIF(Parcels!A:A, A90, Parcels!Z:Z) -> 0 | W90: =SUMIF(Parcels!$A:$A, $A90, Parcels!AC:AC) -> 0 | X90: =V90*P90/O90*0.9 -> 0 | Y90: =IF(W90=0, X90, W90) -> 0 | Z90: {=_xlfn.XLOOKUP( A90, Parcels!A:A, Parcels!AL:AL)} -> 0.0118738 | AA90: =W90*Z90 -> 0 | AB90: =Y90*Z90 -> 0 | AE90: YES | AJ90: =if(F90="CMFA", if(O90<16,10000,O90*600),if(F90="CSCDA",if(33<O90<300, O90*600,if(O90>300,(180000+(O90-300)*300),20000)))) -> 50400 | AK90: =if(F90="CMFA", if(O90<26,4000,O90*150),if(F90="CSCDA",if(33<O90<300, O90*150,if(O90>300,(45000+(O90-300)*75),5000)))) -> 12600 | AL90: =if(AE90="YES",0,IF(AND(I90>=DATE(2022,7,1),I90<=DATE(2023,6,30)),3,IF(AND(I90>=DATE(2023,7,1),I90<=DATE(2024,6,30)),2,IF(AND(I90>=DATE(2024,7,1),I90<=DATE(2025,6,30)),1,IF(AND(I90>=DATE(2025,7,1),I90<=DATE(2026,6,30)),0,"-"))))) -> 0 | AM90: =AK90*AL90 -> 0 | AN90: {=_xlfn.xlookup(C90,'SCC Certificate Review'!C:C,'SCC Certificate Review'!F:F)}
A91: 90 | B91: Pacific Trails Apartments | C91: Pacific Trails, LP | D91: Azusa | E91: Los Angeles | F91: CMFA | G91: Grant up to $10,000 (Charitable Affordable Housing) | H91: 25-304 | I91: 45856 | K91: Langdon Park Capital | M91: Housing on Merit | N91: FALSE | O91: 84 | P91: 84 | Q91: =P91/O91 -> 1 | R91: 18615 E Arrow Hwy, Covina, CA 91722 | S91: 12600 | T91: =COUNTIF(Parcels!A:A, A91) > 0 -> TRUE | U91: =MAXIFS(Parcels!AC:AC, Parcels!A:A, A91) > 0 -> FALSE | V91: =SUMIF(Parcels!A:A, A91, Parcels!Z:Z) -> 21864168 | W91: =SUMIF(Parcels!$A:$A, $A91, Parcels!AC:AC) -> 0 | X91: =V91*P91/O91*0.9 -> 19677751 | Y91: =IF(W91=0, X91, W91) -> 19677751 | Z91: {=_xlfn.XLOOKUP( A91, Parcels!A:A, Parcels!AL:AL)} -> 0.01175703 | AA91: =W91*Z91 -> 0 | AB91: =Y91*Z91 -> 231351.91 | AE91: NO | AJ91: =if(F91="CMFA", if(O91<16,10000,O91*600),if(F91="CSCDA",if(33<O91<300, O91*600,if(O91>300,(180000+(O91-300)*300),20000)))) -> 50400 | AK91: =if(F91="CMFA", if(O91<26,4000,O91*150),if(F91="CSCDA",if(33<O91<300, O91*150,if(O91>300,(45000+(O91-300)*75),5000)))) -> 12600 | AL91: =if(AE91="YES",0,IF(AND(I91>=DATE(2022,7,1),I91<=DATE(2023,6,30)),3,IF(AND(I91>=DATE(2023,7,1),I91<=DATE(2024,6,30)),2,IF(AND(I91>=DATE(2024,7,1),I91<=DATE(2025,6,30)),1,IF(AND(I91>=DATE(2025,7,1),I91<=DATE(2026,6,30)),0,"-"))))) -> 0 | AM91: =AK91*AL91 -> 0 | AN91: {=_xlfn.xlookup(C91,'SCC Certificate Review'!C:C,'SCC Certificate Review'!F:F)}
A92: 89 | B92: LINQ Apartments | C92: Ethos GP I Venture, LP | D92: San Jose | E92: Santa Clara | F92: CMFA | G92: Grant up to $10,000 (Charitable Affordable Housing) | H92: 25-305 | I92: 45856 | K92: Ethos Real Estate | M92: Pacific Housing, Inc | N92: FALSE | O92: 230 | P92: 230 | R92: 1700 Newbury Park Dr, San Jose, CA 95133 | S92: 34500 | T92: =COUNTIF(Parcels!A:A, A92) > 0 -> TRUE | U92: =MAXIFS(Parcels!AC:AC, Parcels!A:A, A92) > 0 -> FALSE | V92: =SUMIF(Parcels!A:A, A92, Parcels!Z:Z) -> 113197044 | W92: =SUMIF(Parcels!$A:$A, $A92, Parcels!AC:AC) -> 0 | X92: =V92*P92/O92*0.9 -> 1.0187734e+08 | Y92: =IF(W92=0, X92, W92) -> 1.0187734e+08 | Z92: {=_xlfn.XLOOKUP( A92, Parcels!A:A, Parcels!AL:AL)} -> 0.012401 | AA92: =W92*Z92 -> 0 | AB92: =Y92*Z92 -> 1263380.9 | AH92: 45903 | AJ92: =if(F92="CMFA", if(O92<16,10000,O92*600),if(F92="CSCDA",if(33<O92<300, O92*600,if(O92>300,(180000+(O92-300)*300),20000)))) -> 138000 | AK92: =if(F92="CMFA", if(O92<26,4000,O92*150),if(F92="CSCDA",if(33<O92<300, O92*150,if(O92>300,(45000+(O92-300)*75),5000)))) -> 34500 | AL92: =if(AE92="YES",0,IF(AND(I92>=DATE(2022,7,1),I92<=DATE(2023,6,30)),3,IF(AND(I92>=DATE(2023,7,1),I92<=DATE(2024,6,30)),2,IF(AND(I92>=DATE(2024,7,1),I92<=DATE(2025,6,30)),1,IF(AND(I92>=DATE(2025,7,1),I92<=DATE(2026,6,30)),0,"-"))))) -> 0 | AM92: =AK92*AL92 -> 0 | AN92: {=_xlfn.xlookup(C92,'SCC Certificate Review'!C:C,'SCC Certificate Review'!F:F)}
A93: 158 | B93: Kalmia Apartments | C93: Kalmia Supportive Housing, LP | D93: Los Angeles | E93: Los Angeles | F93: CMFA | H93: 25-306 | I93: 45856 | J93: TRUE | K93: A Community of Friends | M93: A Community of Friends | N93: FALSE | O93: 29 | P93: 29 | Q93: =P93/O93 -> 1 | S93: 4350 | T93: =COUNTIF(Parcels!A:A, A93) > 0 -> TRUE | U93: =MAXIFS(Parcels!AC:AC, Parcels!A:A, A93) > 0 -> FALSE | V93: =SUMIF(Parcels!A:A, A93, Parcels!Z:Z) -> 0 | W93: =SUMIF(Parcels!$A:$A, $A93, Parcels!AC:AC) -> 0 | X93: =V93*P93/O93*0.9 -> 0 | Y93: =IF(W93=0, X93, W93) -> 0 | Z93: {=_xlfn.XLOOKUP( A93, Parcels!A:A, Parcels!AL:AL)} | AA93: =W93*Z93 -> 0 | AB93: =Y93*Z93 -> 0 | AE93: YES | AJ93: =if(F93="CMFA", if(O93<16,10000,O93*600),if(F93="CSCDA",if(33<O93<300, O93*600,if(O93>300,(180000+(O93-300)*300),20000)))) -> 17400 | AK93: =if(F93="CMFA", if(O93<26,4000,O93*150),if(F93="CSCDA",if(33<O93<300, O93*150,if(O93>300,(45000+(O93-300)*75),5000)))) -> 4350 | AL93: =if(AE93="YES",0,IF(AND(I93>=DATE(2022,7,1),I93<=DATE(2023,6,30)),3,IF(AND(I93>=DATE(2023,7,1),I93<=DATE(2024,6,30)),2,IF(AND(I93>=DATE(2024,7,1),I93<=DATE(2025,6,30)),1,IF(AND(I93>=DATE(2025,7,1),I93<=DATE(2026,6,30)),0,"-"))))) -> 0 | AM93: =AK93*AL93 -> 0 | AN93: {=_xlfn.xlookup(C93,'SCC Certificate Review'!C:C,'SCC Certificate Review'!F:F)}
A94: 88 | B94: Chatsworth Apartments | C94: Chatsworth Housing, LP | D94: Los Angeles | E94: Los Angeles | F94: CMFA | G94: Grant up to $10,000 (Charitable Affordable Housing) | H94: 25-308 | I94: 45856 | K94: BMI Developments | M94: Kingdom Development, Inc. | N94: FALSE | O94: 69 | P94: 68 | Q94: =P94/O94 -> 0.98550725 | R94: 17188 Chatsworth St., Los Angeles, CA | S94: 10200 | T94: =COUNTIF(Parcels!A:A, A94) > 0 -> TRUE | U94: =MAXIFS(Parcels!AC:AC, Parcels!A:A, A94) > 0 -> FALSE | V94: =SUMIF(Parcels!A:A, A94, Parcels!Z:Z) -> 850000 | W94: =SUMIF(Parcels!$A:$A, $A94, Parcels!AC:AC) -> 0 | X94: =V94*P94/O94*0.9 -> 753913.04 | Y94: =IF(W94=0, X94, W94) -> 753913.04 | Z94: {=_xlfn.XLOOKUP( A94, Parcels!A:A, Parcels!AL:AL)} -> 0.0118738 | AA94: =W94*Z94 -> 0 | AB94: =Y94*Z94 -> 8951.8127 | AE94: YES | AJ94: =if(F94="CMFA", if(O94<16,10000,O94*600),if(F94="CSCDA",if(33<O94<300, O94*600,if(O94>300,(180000+(O94-300)*300),20000)))) -> 41400 | AK94: =if(F94="CMFA", if(O94<26,4000,O94*150),if(F94="CSCDA",if(33<O94<300, O94*150,if(O94>300,(45000+(O94-300)*75),5000)))) -> 10350 | AL94: =if(AE94="YES",0,IF(AND(I94>=DATE(2022,7,1),I94<=DATE(2023,6,30)),3,IF(AND(I94>=DATE(2023,7,1),I94<=DATE(2024,6,30)),2,IF(AND(I94>=DATE(2024,7,1),I94<=DATE(2025,6,30)),1,IF(AND(I94>=DATE(2025,7,1),I94<=DATE(2026,6,30)),0,"-"))))) -> 0 | AM94: =AK94*AL94 -> 0 | AN94: {=_xlfn.xlookup(C94,'SCC Certificate Review'!C:C,'SCC Certificate Review'!F:F)}
A95: 97 | B95: Azusa Gardens Apartments | C95: Azusa Gardens Owner, LP | D95: Azusa | E95: Los Angeles | F95: CMFA | G95: Grant up to $10,000 (Charitable Affordable Housing) | H95: 25-347 | I95: 45877 | K95: TriWest Multifamily | M95: Kingdom Development, Inc. | N95: FALSE | O95: 112 | P95: 112 | Q95: =P95/O95 -> 1 | R95: 601 E 8th St, Azusa, CA 91702 | S95: 16800 | T95: =COUNTIF(Parcels!A:A, A95) > 0 -> TRUE | U95: =MAXIFS(Parcels!AC:AC, Parcels!A:A, A95) > 0 -> FALSE | V95: =SUMIF(Parcels!A:A, A95, Parcels!Z:Z) -> 13224803 | W95: =SUMIF(Parcels!$A:$A, $A95, Parcels!AC:AC) -> 0 | X95: =V95*P95/O95*0.9 -> 11902323 | Y95: =IF(W95=0, X95, W95) -> 11902323 | Z95: {=_xlfn.XLOOKUP( A95, Parcels!A:A, Parcels!AL:AL)} -> 0.0116448 | AA95: =W95*Z95 -> 0 | AB95: =Y95*Z95 -> 138600.17 | AE95: NO | AJ95: =if(F95="CMFA", if(O95<16,10000,O95*600),if(F95="CSCDA",if(33<O95<300, O95*600,if(O95>300,(180000+(O95-300)*300),20000)))) -> 67200 | AK95: =if(F95="CMFA", if(O95<26,4000,O95*150),if(F95="CSCDA",if(33<O95<300, O95*150,if(O95>300,(45000+(O95-300)*75),5000)))) -> 16800 | AL95: =if(AE95="YES",0,IF(AND(I95>=DATE(2022,7,1),I95<=DATE(2023,6,30)),3,IF(AND(I95>=DATE(2023,7,1),I95<=DATE(2024,6,30)),2,IF(AND(I95>=DATE(2024,7,1),I95<=DATE(2025,6,30)),1,IF(AND(I95>=DATE(2025,7,1),I95<=DATE(2026,6,30)),0,"-"))))) -> 0 | AM95: =AK95*AL95 -> 0 | AN95: {=_xlfn.xlookup(C95,'SCC Certificate Review'!C:C,'SCC Certificate Review'!F:F)}
A96: 96 | B96: Park Kiely Apartments | C96: Standard Vistria Park Kiely Owner, LP | D96: San Jose | E96: Santa Clara | F96: CMFA | G96: Grant up to $10,000 (Charitable Affordable Housing) | H96: 25-348 | I96: 45877 | K96: Standard Property Company | L96: Vistria | M96: Housing on Merit | N96: FALSE | O96: 948 | P96: 948 | Q96: =P96/O96 -> 1 | R96: 355 Kiely Blvd, San Jose, CA 95129 | S96: 93600 | T96: =COUNTIF(Parcels!A:A, A96) > 0 -> TRUE | U96: =MAXIFS(Parcels!AC:AC, Parcels!A:A, A96) > 0 -> FALSE | V96: =SUMIF(Parcels!A:A, A96, Parcels!Z:Z) -> 297316740 | W96: =SUMIF(Parcels!$A:$A, $A96, Parcels!AC:AC) -> 0 | X96: =V96*P96/O96*0.9 -> 267585066 | Y96: =IF(W96=0, X96, W96) -> 267585066 | Z96: {=_xlfn.XLOOKUP( A96, Parcels!A:A, Parcels!AL:AL)} -> 0.012401 | AA96: =W96*Z96 -> 0 | AB96: =Y96*Z96 -> 3318322.4 | AF96: 1972 | AG96: 410 | AH96: 45896 | AJ96: =if(F96="CMFA", if(O96<16,10000,O96*600),if(F96="CSCDA",if(33<O96<300, O96*600,if(O96>300,(180000+(O96-300)*300),20000)))) -> 568800 | AK96: =if(F96="CMFA", if(O96<26,4000,O96*150),if(F96="CSCDA",if(33<O96<300, O96*150,if(O96>300,(45000+(O96-300)*75),5000)))) -> 142200 | AL96: =if(AE96="YES",0,IF(AND(I96>=DATE(2022,7,1),I96<=DATE(2023,6,30)),3,IF(AND(I96>=DATE(2023,7,1),I96<=DATE(2024,6,30)),2,IF(AND(I96>=DATE(2024,7,1),I96<=DATE(2025,6,30)),1,IF(AND(I96>=DATE(2025,7,1),I96<=DATE(2026,6,30)),0,"-"))))) -> 0 | AM96: =AK96*AL96 -> 0 | AN96: {=_xlfn.xlookup(C96,'SCC Certificate Review'!C:C,'SCC Certificate Review'!F:F)} -> TRUE
A97: 95 | B97: Fountain Park Apartments | C97: Fountain Park, L.P. | D97: San Jose | E97: Santa Clara | F97: CMFA | G97: Grant up to $10,000 (Charitable Affordable Housing) | H97: 25-349 | I97: 45877 | K97: Sack Capital Partners | L97: Belveron Partners | M97: Las Palmas Housing & Development Corp. | N97: FALSE | O97: 164 | P97: 164 | R97: 1026 S De Anza Blvd, San Jose, CA 95129 | S97: 24600 | T97: =COUNTIF(Parcels!A:A, A97) > 0 -> TRUE | U97: =MAXIFS(Parcels!AC:AC, Parcels!A:A, A97) > 0 -> FALSE | V97: =SUMIF(Parcels!A:A, A97, Parcels!Z:Z) -> 4853048 | W97: =SUMIF(Parcels!$A:$A, $A97, Parcels!AC:AC) -> 0 | X97: =V97*P97/O97*0.9 -> 4367743.2 | Y97: =IF(W97=0, X97, W97) -> 4367743.2 | Z97: {=_xlfn.XLOOKUP( A97, Parcels!A:A, Parcels!AL:AL)} -> 0.012401 | AA97: =W97*Z97 -> 0 | AB97: =Y97*Z97 -> 54164.383 | AC97: https://rebusinessonline.com/sack-properties-belveron-partners-buy-164-unit-multifamily-property-in-san-jose-california/ | AH97: 45898 | AJ97: =if(F97="CMFA", if(O97<16,10000,O97*600),if(F97="CSCDA",if(33<O97<300, O97*600,if(O97>300,(180000+(O97-300)*300),20000)))) -> 98400 | AK97: =if(F97="CMFA", if(O97<26,4000,O97*150),if(F97="CSCDA",if(33<O97<300, O97*150,if(O97>300,(45000+(O97-300)*75),5000)))) -> 24600 | AL97: =if(AE97="YES",0,IF(AND(I97>=DATE(2022,7,1),I97<=DATE(2023,6,30)),3,IF(AND(I97>=DATE(2023,7,1),I97<=DATE(2024,6,30)),2,IF(AND(I97>=DATE(2024,7,1),I97<=DATE(2025,6,30)),1,IF(AND(I97>=DATE(2025,7,1),I97<=DATE(2026,6,30)),0,"-"))))) -> 0 | AM97: =AK97*AL97 -> 0 | AN97: {=_xlfn.xlookup(C97,'SCC Certificate Review'!C:C,'SCC Certificate Review'!F:F)} -> TRUE
A98: 92 | B98: The Parker Apartments | C98: Flag VII The Parker, L.P. | D98: El Monte | E98: Los Angeles | F98: CMFA | G98: Grant up to $10,000 (Charitable Affordable Housing) | H98: 25-350 | I98: 45877 | K98: Belveron Partners | M98: Las Palmas Housing & Development Corporation | N98: FALSE | O98: 177 | P98: 177 | Q98: =P98/O98 -> 1 | R98: 4640 Arden Way, El Monte, CA 91731 | S98: 26550 | T98: =COUNTIF(Parcels!A:A, A98) > 0 -> TRUE | U98: =MAXIFS(Parcels!AC:AC, Parcels!A:A, A98) > 0 -> FALSE | V98: =SUMIF(Parcels!A:A, A98, Parcels!Z:Z) -> 45003808 | W98: =SUMIF(Parcels!$A:$A, $A98, Parcels!AC:AC) -> 0 | X98: =V98*P98/O98*0.9 -> 40503427 | Y98: =IF(W98=0, X98, W98) -> 40503427 | Z98: {=_xlfn.XLOOKUP( A98, Parcels!A:A, Parcels!AL:AL)} -> 0.01323192 | AA98: =W98*Z98 -> 0 | AB98: =Y98*Z98 -> 535938.11 | AE98: NO | AJ98: =if(F98="CMFA", if(O98<16,10000,O98*600),if(F98="CSCDA",if(33<O98<300, O98*600,if(O98>300,(180000+(O98-300)*300),20000)))) -> 106200 | AK98: =if(F98="CMFA", if(O98<26,4000,O98*150),if(F98="CSCDA",if(33<O98<300, O98*150,if(O98>300,(45000+(O98-300)*75),5000)))) -> 26550 | AL98: =if(AE98="YES",0,IF(AND(I98>=DATE(2022,7,1),I98<=DATE(2023,6,30)),3,IF(AND(I98>=DATE(2023,7,1),I98<=DATE(2024,6,30)),2,IF(AND(I98>=DATE(2024,7,1),I98<=DATE(2025,6,30)),1,IF(AND(I98>=DATE(2025,7,1),I98<=DATE(2026,6,30)),0,"-"))))) -> 0 | AM98: =AK98*AL98 -> 0 | AN98: {=_xlfn.xlookup(C98,'SCC Certificate Review'!C:C,'SCC Certificate Review'!F:F)} -> TRUE
A99: 93 | B99: Canyon Ridge at Napa Junction Apartments | C99: Canyon Ridge at Napa Junction, LP | D99: American Canyon | E99: Napa | F99: CMFA | G99: Grant up to $10,000 (Charitable Affordable Housing) | H99: 25-351 | I99: 45877 | K99: BRIDGE Housing Corp. | M99: BRIDGE Housing Corp. | N99: FALSE | O99: 148 | P99: 148 | R99: 800 Reliant Wy, American Canyon, CA 94503 | S99: 22200 | T99: =COUNTIF(Parcels!A:A, A99) > 0 -> TRUE | U99: =MAXIFS(Parcels!AC:AC, Parcels!A:A, A99) > 0 -> FALSE | V99: =SUMIF(Parcels!A:A, A99, Parcels!Z:Z) -> 46693244 | W99: =SUMIF(Parcels!$A:$A, $A99, Parcels!AC:AC) -> 0 | X99: =V99*P99/O99*0.9 -> 42023920 | Y99: =IF(W99=0, X99, W99) -> 42023920 | Z99: {=_xlfn.XLOOKUP( A99, Parcels!A:A, Parcels!AL:AL)} -> 0.010944 | AA99: =W99*Z99 -> 0 | AB99: =Y99*Z99 -> 459909.78 | AE99: NO | AJ99: =if(F99="CMFA", if(O99<16,10000,O99*600),if(F99="CSCDA",if(33<O99<300, O99*600,if(O99>300,(180000+(O99-300)*300),20000)))) -> 88800 | AK99: =if(F99="CMFA", if(O99<26,4000,O99*150),if(F99="CSCDA",if(33<O99<300, O99*150,if(O99>300,(45000+(O99-300)*75),5000)))) -> 22200 | AL99: =if(AE99="YES",0,IF(AND(I99>=DATE(2022,7,1),I99<=DATE(2023,6,30)),3,IF(AND(I99>=DATE(2023,7,1),I99<=DATE(2024,6,30)),2,IF(AND(I99>=DATE(2024,7,1),I99<=DATE(2025,6,30)),1,IF(AND(I99>=DATE(2025,7,1),I99<=DATE(2026,6,30)),0,"-"))))) -> 0 | AM99: =AK99*AL99 -> 0 | AN99: {=_xlfn.xlookup(C99,'SCC Certificate Review'!C:C,'SCC Certificate Review'!F:F)}
A100: 94 | B100: Canyon Villa Apartment Homes | C100: Post Canyon Villa, LP | D100: Chula Vista | E100: San Diego | F100: CMFA | G100: Grant up to $10,000 (Charitable Affordable Housing) | H100: 25-352 | I100: 45877 | K100: Post Investment Group | M100: Integrity Housing | N100: FALSE | O100: 183 | P100: 183 | R100: 601 Telegraph Canyon Road, Chula Vista, CA 91910 | S100: 27450 | T100: =COUNTIF(Parcels!A:A, A100) > 0 -> TRUE | U100: =MAXIFS(Parcels!AC:AC, Parcels!A:A, A100) > 0 -> FALSE | V100: =SUMIF(Parcels!A:A, A100, Parcels!Z:Z) -> 51548563 | W100: =SUMIF(Parcels!$A:$A, $A100, Parcels!AC:AC) -> 0 | X100: =V100*P100/O100*0.9 -> 46393707 | Y100: =IF(W100=0, X100, W100) -> 46393707 | Z100: {=_xlfn.XLOOKUP( A100, Parcels!A:A, Parcels!AL:AL)} -> 0.0118748 | AA100: =W100*Z100 -> 0 | AB100: =Y100*Z100 -> 550915.99 | AE100: NO | AF100: 1981 | AJ100: =if(F100="CMFA", if(O100<16,10000,O100*600),if(F100="CSCDA",if(33<O100<300, O100*600,if(O100>300,(180000+(O100-300)*300),20000)))) -> 109800 | AK100: =if(F100="CMFA", if(O100<26,4000,O100*150),if(F100="CSCDA",if(33<O100<300, O100*150,if(O100>300,(45000+(O100-300)*75),5000)))) -> 27450 | AL100: =if(AE100="YES",0,IF(AND(I100>=DATE(2022,7,1),I100<=DATE(2023,6,30)),3,IF(AND(I100>=DATE(2023,7,1),I100<=DATE(2024,6,30)),2,IF(AND(I100>=DATE(2024,7,1),I100<=DATE(2025,6,30)),1,IF(AND(I100>=DATE(2025,7,1),I100<=DATE(2026,6,30)),0,"-"))))) -> 0 | AM100: =AK100*AL100 -> 0 | AN100: {=_xlfn.xlookup(C100,'SCC Certificate Review'!C:C,'SCC Certificate Review'!F:F)} -> TRUE
...

Sheet Parcels
A1: project_id | B1: county | C1: property | D1: ain | E1: legacy_ain | F1: legacy_redundant | G1: apn | H1: situs_address | I1: situs_city | J1: situs_zip | K1: input_address | L1: property_name | M1: tract_number | N1: method | O1: use_description | P1: use_type | Q1: use_code | R1: year_built | S1: units | T1: bedrooms | U1: bathrooms | V1: sqft | W1: roll_year | X1: roll_land_value | Y1: roll_imp_value | Z1: roll_total_value | AA1: roll_land_base_year | AB1: roll_imp_base_year | AC1: real_estate_exemp | AD1: tax_rate_area | AE1: tax_rate_city | AF1: latitude | AG1: longitude | AH1: legal_description | AI1: notes | AJ1: CMFA Total Units | AK1: CMFA Restricted | AL1: Total Tax Rate
A2: 1 | B2: {=_xlfn.XLOOKUP( A2, 'CMFA-CSCDA Grants'!A:A, 'CMFA-CSCDA Grants'!E:E)} -> Los Angeles | C2: {=_xlfn.XLOOKUP( A2, 'CMFA-CSCDA Grants'!A:A, 'CMFA-CSCDA Grants'!B:B)} -> Alvarado Streets Apartments | D2: 5136019013 | F2: FALSE | G2: 5136-019-013 | H2: 1136 S ALVARADO ST LOS ANGELES CA 90006 | I2: LOS ANGELES CA | J2: 90006-4138 | K2: 1136 S. Alvarado Street, Los Angeles, CA | L2: Alvarado Streets Apartments | N2: manual_verified | O2: Five or more apartments | P2: Residential | Q2: 500 | R2: 1912 | S2: 24 | T2: 0 | U2: 24 | V2: 16113 | W2: 2025 | X2: 2080800 | Y2: 2366910 | Z2: =SUM(X2:Y2) -> 4447710 | AA2: 2023 | AB2: 2023 | AC2: 4262686 | AD2: 36 | AE2: LOS ANGELES | AF2: 34.04914 | AG2: -118.28104 | AH2: ALVARADO HEIGHTS LOT 4 BLK 6 | AI2: Corrected from AIN 5136019023 (auto/equipment use) to 5136019013 (apartments) | AJ2: {=_xlfn.XLOOKUP( A2, 'CMFA-CSCDA Grants'!A:A, 'CMFA-CSCDA Grants'!O:O)} -> 24 | AK2: {=_xlfn.XLOOKUP( A2, 'CMFA-CSCDA Grants'!A:A, 'CMFA-CSCDA Grants'!P:P)} -> 24 | AL2: {=_xlfn.XLOOKUP( AD2, 'Tax Rates'!A:A, 'Tax Rates'!B:B)} -> 0.0118738
A3: 2 | B3: {=_xlfn.XLOOKUP( A3, 'CMFA-CSCDA Grants'!A:A, 'CMFA-CSCDA Grants'!E:E)} -> Los Angeles | C3: {=_xlfn.XLOOKUP( A3, 'CMFA-CSCDA Grants'!A:A, 'CMFA-CSCDA Grants'!B:B)} -> 2025 New Jersey Apartments | D3: 5183001017 | F3: FALSE | G3: 5183-001-017 | H3: 2025 NEW JERSEY ST LOS ANGELES CA 90033 | I3: LOS ANGELES CA | J3: 90033-2805 | K3: 2025 New Jersey St, Los Angeles, CA | L3: 2025 New Jersey Apartments | N3: manual_verified | O3: Five or more apartments | P3: Residential | Q3: 050V | W3: 2025 | X3: 527950 | Y3: 0 | Z3: =SUM(X3:Y3) -> 527950 | AA3: 2018 | AB3: 2018 | AC3: 527950 | AD3: 4 | AE3: LOS ANGELES | AF3: 34.048011 | AG3: -118.21232 | AH3: SUBDN OF LOT 2 BLK 60 H S NW 20 FT OF LOT 3 AND SE 20 FT OF LOT 5 BLK A | AJ3: {=_xlfn.XLOOKUP( A3, 'CMFA-CSCDA Grants'!A:A, 'CMFA-CSCDA Grants'!O:O)} -> 15 | AK3: {=_xlfn.XLOOKUP( A3, 'CMFA-CSCDA Grants'!A:A, 'CMFA-CSCDA Grants'!P:P)} -> 14 | AL3: {=_xlfn.XLOOKUP( AD3, 'Tax Rates'!A:A, 'Tax Rates'!B:B)} -> 0.0118738
A4: 3 | B4: {=_xlfn.XLOOKUP( A4, 'CMFA-CSCDA Grants'!A:A, 'CMFA-CSCDA Grants'!E:E)} -> Santa Clara | C4: {=_xlfn.XLOOKUP( A4, 'CMFA-CSCDA Grants'!A:A, 'CMFA-CSCDA Grants'!B:B)} -> Mariposa Club Apartments | D4: 15434025 | F4: FALSE | H4: 660 MARIPOSA AVE MOUNTAIN VIEW CA 94041-1867 | X4: - | Y4: - | Z4: 17059601 | AC4: 16718409 | AD4: Mountain View | AJ4: {=_xlfn.XLOOKUP( A4, 'CMFA-CSCDA Grants'!A:A, 'CMFA-CSCDA Grants'!O:O)} -> 48 | AK4: {=_xlfn.XLOOKUP( A4, 'CMFA-CSCDA Grants'!A:A, 'CMFA-CSCDA Grants'!P:P)} -> 48 | AL4: {=_xlfn.XLOOKUP( AD4, 'Tax Rates'!A:A, 'Tax Rates'!B:B)} -> 0.011211
A5: 4 | B5: {=_xlfn.XLOOKUP( A5, 'CMFA-CSCDA Grants'!A:A, 'CMFA-CSCDA Grants'!E:E)} -> San Bernardino | C5: {=_xlfn.XLOOKUP( A5, 'CMFA-CSCDA Grants'!A:A, 'CMFA-CSCDA Grants'!B:B)} -> Bernardine Apartments | D5: 147091180000 | F5: FALSE | H5: 363 E GILBERT ST SAN BERNARDINO CA 92404-5343 | X5: - | Y5: - | Z5: 4156500 | AC5: 4156500 | AD5: San Bernardino | AJ5: {=_xlfn.XLOOKUP( A5, 'CMFA-CSCDA Grants'!A:A, 'CMFA-CSCDA Grants'!O:O)} -> 71 | AK5: {=_xlfn.XLOOKUP( A5, 'CMFA-CSCDA Grants'!A:A, 'CMFA-CSCDA Grants'!P:P)} -> 70 | AL5: {=_xlfn.XLOOKUP( AD5, 'Tax Rates'!A:A, 'Tax Rates'!B:B)} -> 0.0113
A6: 5 | B6: {=_xlfn.XLOOKUP( A6, 'CMFA-CSCDA Grants'!A:A, 'CMFA-CSCDA Grants'!E:E)} -> San Diego | C6: {=_xlfn.XLOOKUP( A6, 'CMFA-CSCDA Grants'!A:A, 'CMFA-CSCDA Grants'!B:B)} -> City View aka Outlook at Mission Valley Apartments | D6: 5343602100 | F6: FALSE | H6: 840.0 17TH ST SAN DIEGO CA 92101-6666 | X6: - | Y6: - | Z6: 9316117 | AD6: San Diego | AJ6: {=_xlfn.XLOOKUP( A6, 'CMFA-CSCDA Grants'!A:A, 'CMFA-CSCDA Grants'!O:O)} -> 56 | AK6: {=_xlfn.XLOOKUP( A6, 'CMFA-CSCDA Grants'!A:A, 'CMFA-CSCDA Grants'!P:P)} -> 23 | AL6: {=_xlfn.XLOOKUP( AD6, 'Tax Rates'!A:A, 'Tax Rates'!B:B)} -> 0.0125114
A7: 6 | B7: {=_xlfn.XLOOKUP( A7, 'CMFA-CSCDA Grants'!A:A, 'CMFA-CSCDA Grants'!E:E)} -> San Francisco | C7: {=_xlfn.XLOOKUP( A7, 'CMFA-CSCDA Grants'!A:A, 'CMFA-CSCDA Grants'!B:B)} -> 381 Turk Street Apartment | D7: 0345012C | F7: FALSE | H7: 381 TURK ST SAN FRANCISCO CA 94102-3749 | X7: - | Y7: - | Z7: 7398189 | AD7: San Francisco | AJ7: {=_xlfn.XLOOKUP( A7, 'CMFA-CSCDA Grants'!A:A, 'CMFA-CSCDA Grants'!O:O)} -> 32 | AK7: {=_xlfn.XLOOKUP( A7, 'CMFA-CSCDA Grants'!A:A, 'CMFA-CSCDA Grants'!P:P)} -> 13 | AL7: {=_xlfn.XLOOKUP( AD7, 'Tax Rates'!A:A, 'Tax Rates'!B:B)} -> 0.012
A8: 7 | B8: {=_xlfn.XLOOKUP( A8, 'CMFA-CSCDA Grants'!A:A, 'CMFA-CSCDA Grants'!E:E)} -> Alameda | C8: {=_xlfn.XLOOKUP( A8, 'CMFA-CSCDA Grants'!A:A, 'CMFA-CSCDA Grants'!B:B)} -> Townhomes at Gading Apartments | D8: 454251243 | F8: FALSE | G8: 454-25-124-3 | H8: 26409 GADING RD HAYWARD CA 94544-3603 | X8: 4845000 | Y8: 12468480 | Z8: =sum(X8:Y8) -> 17313480 | AC8: 0 | AD8: Hayward | AJ8: {=_xlfn.XLOOKUP( A8, 'CMFA-CSCDA Grants'!A:A, 'CMFA-CSCDA Grants'!O:O)} -> 61 | AK8: {=_xlfn.XLOOKUP( A8, 'CMFA-CSCDA Grants'!A:A, 'CMFA-CSCDA Grants'!P:P)} -> 61 | AL8: {=_xlfn.XLOOKUP( AD8, 'Tax Rates'!A:A, 'Tax Rates'!B:B)} -> 0.011724
A9: 8 | B9: {=_xlfn.XLOOKUP( A9, 'CMFA-CSCDA Grants'!A:A, 'CMFA-CSCDA Grants'!E:E)} -> Los Angeles | C9: {=_xlfn.XLOOKUP( A9, 'CMFA-CSCDA Grants'!A:A, 'CMFA-CSCDA Grants'!B:B)} -> 1317 S. Grand Apartments | D9: 5134017037 | E9: 5134017016 | F9: FALSE | G9: 5134-017-037 | H9: 1317 S GRAND AVE LOS ANGELES CA 900015 | I9: LOS ANGELES CA | J9: 90015-3008 | K9: 1317 S. Grand St, Los Angeles, CA 90015 | L9: 1317 S. Grand Apartments | N9: parcel_in_transition | O9: Multi-Family Residence | P9: Residential | S9: 147 | V9: 65894 | W9: 2025 | X9: 5905687 | Y9: 5878260 | Z9: =SUM(X9:Y9) -> 11783947 | AA9: 2020 | AB9: 2023 | AD9: 13264 | AE9: LOS ANGELES | AF9: 34.038496 | AG9: -118.26503 | AI9: AIN not in DB | AJ9: {=_xlfn.XLOOKUP( A9, 'CMFA-CSCDA Grants'!A:A, 'CMFA-CSCDA Grants'!O:O)} -> 147 | AK9: {=_xlfn.XLOOKUP( A9, 'CMFA-CSCDA Grants'!A:A, 'CMFA-CSCDA Grants'!P:P)} -> 147 | AL9: {=_xlfn.XLOOKUP( AD9, 'Tax Rates'!A:A, 'Tax Rates'!B:B)} -> 0.0118738
A10: 9 | B10: {=_xlfn.XLOOKUP( A10, 'CMFA-CSCDA Grants'!A:A, 'CMFA-CSCDA Grants'!E:E)} -> Los Angeles | C10: {=_xlfn.XLOOKUP( A10, 'CMFA-CSCDA Grants'!A:A, 'CMFA-CSCDA Grants'!B:B)} -> 1411 S. Flower Apartments | D10: 5134009025 | E10: 5134009008 | F10: FALSE | G10: 5134-009-025 | H10: 1411 S FLOWER ST | I10: LOS ANGELES CA | K10: 1411 Flower St, Los Angeles, CA 90015 | L10: 1411 S. Flower Apartments | N10: parcel_in_transition | O10: Multi-Family Residence | P10: Residential | Q10: 05S0 | R10: 2024 | S10: 227 | V10: 97266 | W10: 2025 | X10: 4643633 | Y10: 4498824 | Z10: =SUM(X10:Y10) -> 9142457 | AA10: 2021 | AB10: 2024 | AD10: 13264 | AE10: LOS ANGELES | AF10: 34.037999 | AG10: -118.2686 | AI10: Multi-parcel (2). AIN not in DB. | AJ10: {=_xlfn.XLOOKUP( A10, 'CMFA-CSCDA Grants'!A:A, 'CMFA-CSCDA Grants'!O:O)} -> 227 | AK10: {=_xlfn.XLOOKUP( A10, 'CMFA-CSCDA Grants'!A:A, 'CMFA-CSCDA Grants'!P:P)} -> 227 | AL10: {=_xlfn.XLOOKUP( AD10, 'Tax Rates'!A:A, 'Tax Rates'!B:B)} -> 0.0118738
A11: 9 | B11: {=_xlfn.XLOOKUP( A11, 'CMFA-CSCDA Grants'!A:A, 'CMFA-CSCDA Grants'!E:E)} -> Los Angeles | C11: {=_xlfn.XLOOKUP( A11, 'CMFA-CSCDA Grants'!A:A, 'CMFA-CSCDA Grants'!B:B)} -> 1411 S. Flower Apartments | D11: 5134009024 | E11: 5134009007 | F11: TRUE | G11: 5134-009-024 | K11: 1411 Flower St, Los Angeles, CA 90015 | L11: 1411 S. Flower Apartments | N11: parcel_in_transition | O11: (pending) | X11: 0 | Y11: 0 | Z11: =SUM(X11:Y11) -> 0 | AD11: 13264 | AE11: LOS ANGELES | AF11: 34.037999 | AG11: -118.2686 | AI11: Multi-parcel (2). AIN not in DB. | AJ11: {=_xlfn.XLOOKUP( A11, 'CMFA-CSCDA Grants'!A:A, 'CMFA-CSCDA Grants'!O:O)} -> 227 | AK11: {=_xlfn.XLOOKUP( A11, 'CMFA-CSCDA Grants'!A:A, 'CMFA-CSCDA Grants'!P:P)} -> 227 | AL11: {=_xlfn.XLOOKUP( AD11, 'Tax Rates'!A:A, 'Tax Rates'!B:B)} -> 0.0118738
A12: 10 | B12: {=_xlfn.XLOOKUP( A12, 'CMFA-CSCDA Grants'!A:A, 'CMFA-CSCDA Grants'!E:E)} -> Los Angeles | C12: {=_xlfn.XLOOKUP( A12, 'CMFA-CSCDA Grants'!A:A, 'CMFA-CSCDA Grants'!B:B)} -> 7518 Hoover St. Apartments | D12: 6020022027 | E12: 6020022025 | F12: FALSE | G12: 6020-022-027 | H12: 7524 S HOOVER ST | I12: LOS ANGELES CA | K12: 7518 S. Hoover, Los Angeles, CA 90044 | L12: 7518 Hoover St. Apartments | N12: parcel_in_transition | O12: (pending) | W12: 2025 | X12: 2856000 | Y12: 0 | Z12: =SUM(X12:Y12) -> 2856000 | AA12: 2024 | AB12: 2024 | AC12: 0 | AD12: 212 | AE12: LOS ANGELES | AF12: 33.971016 | AG12: -118.28679 | AI12: Multi-parcel (2). AIN not in DB. | AJ12: {=_xlfn.XLOOKUP( A12, 'CMFA-CSCDA Grants'!A:A, 'CMFA-CSCDA Grants'!O:O)} -> 79 | AK12: {=_xlfn.XLOOKUP( A12, 'CMFA-CSCDA Grants'!A:A, 'CMFA-CSCDA Grants'!P:P)} -> 48 | AL12: {=_xlfn.XLOOKUP( AD12, 'Tax Rates'!A:A, 'Tax Rates'!B:B)} -> 0.0118738
A13: 11 | B13: {=_xlfn.XLOOKUP( A13, 'CMFA-CSCDA Grants'!A:A, 'CMFA-CSCDA Grants'!E:E)} -> Alameda | C13: {=_xlfn.XLOOKUP( A13, 'CMFA-CSCDA Grants'!A:A, 'CMFA-CSCDA Grants'!B:B)} -> 820 MacArthur Apartments | D13: 1295996 | F13: FALSE | G13: 12-959-9-6 | H13: 820 W MACARTHUR BLVD OAKLAND CA 94608 | X13: 2013882 | Y13: - | Z13: =sum(X13:Y13) -> 2013882 | AC13: 7089890 | AD13: Oakland | AJ13: {=_xlfn.XLOOKUP( A13, 'CMFA-CSCDA Grants'!A:A, 'CMFA-CSCDA Grants'!O:O)} -> 166 | AK13: {=_xlfn.XLOOKUP( A13, 'CMFA-CSCDA Grants'!A:A, 'CMFA-CSCDA Grants'!P:P)} -> 166 | AL13: {=_xlfn.XLOOKUP( AD13, 'Tax Rates'!A:A, 'Tax Rates'!B:B)} -> 0.012779
A14: 12 | B14: {=_xlfn.XLOOKUP( A14, 'CMFA-CSCDA Grants'!A:A, 'CMFA-CSCDA Grants'!E:E)} -> Los Angeles | C14: {=_xlfn.XLOOKUP( A14, 'CMFA-CSCDA Grants'!A:A, 'CMFA-CSCDA Grants'!B:B)} -> The Waterloo Apartments | D14: 5402028023 | F14: FALSE | G14: 5402-028-023 | H14: 801 WATERLOO ST LOS ANGELES CA 90026 | I14: LOS ANGELES CA | J14: 90026-4039 | K14: 801-809 Waterloo Street, Los Angeles, CA | L14: The Waterloo Apartments | N14: manual_verified | O14: Five or more apartments | P14: Residential | Q14: 500 | R14: 1917 | S14: 4 | T14: 4 | U14: 4 | V14: 3838 | W14: 2025 | X14: 985000 | Y14: 375000 | Z14: =SUM(X14:Y14) -> 1360000 | AA14: 2025 | AB14: 2025 | AC14: 0 | AD14: 13 | AE14: LOS ANGELES | AF14: 34.075819 | AG14: -118.26849 | AH14: WATERLOO TRACT LOT 12 BLK 1 | AJ14: {=_xlfn.XLOOKUP( A14, 'CMFA-CSCDA Grants'!A:A, 'CMFA-CSCDA Grants'!O:O)} -> 154 | AK14: {=_xlfn.XLOOKUP( A14, 'CMFA-CSCDA Grants'!A:A, 'CMFA-CSCDA Grants'!P:P)} -> 154 | AL14: {=_xlfn.XLOOKUP( AD14, 'Tax Rates'!A:A, 'Tax Rates'!B:B)} -> 0.0118738
A15: 13 | B15: {=_xlfn.XLOOKUP( A15, 'CMFA-CSCDA Grants'!A:A, 'CMFA-CSCDA Grants'!E:E)} -> San Francisco | C15: {=_xlfn.XLOOKUP( A15, 'CMFA-CSCDA Grants'!A:A, 'CMFA-CSCDA Grants'!B:B)} -> 275 Turk Street Apartments | D15: 344007 | F15: FALSE | H15: 275 TURK ST SAN FRANCISCO CA 94102-3831 | X15: - | Y15: - | Z15: 17116303 | AD15: San Francisco | AJ15: {=_xlfn.XLOOKUP( A15, 'CMFA-CSCDA Grants'!A:A, 'CMFA-CSCDA Grants'!O:O)} -> 66 | AK15: {=_xlfn.XLOOKUP( A15, 'CMFA-CSCDA Grants'!A:A, 'CMFA-CSCDA Grants'!P:P)} -> 27 | AL15: {=_xlfn.XLOOKUP( AD15, 'Tax Rates'!A:A, 'Tax Rates'!B:B)} -> 0.012
A16: 14 | B16: {=_xlfn.XLOOKUP( A16, 'CMFA-CSCDA Grants'!A:A, 'CMFA-CSCDA Grants'!E:E)} -> Alameda | C16: {=_xlfn.XLOOKUP( A16, 'CMFA-CSCDA Grants'!A:A, 'CMFA-CSCDA Grants'!B:B)} -> Electric Lofts Apartments | D16: 867281 | F16: FALSE | G16: 8-672-8-1 | H16: 2415 VALDEZ ST OAKLAND CA 94612-3600 | X16: 3128977 | Y16: 21128180 | Z16: =sum(X16:Y16) -> 24257157 | AD16: Oakland | AJ16: {=_xlfn.XLOOKUP( A16, 'CMFA-CSCDA Grants'!A:A, 'CMFA-CSCDA Grants'!O:O)} -> 89 | AK16: {=_xlfn.XLOOKUP( A16, 'CMFA-CSCDA Grants'!A:A, 'CMFA-CSCDA Grants'!P:P)} -> 40 | AL16: {=_xlfn.XLOOKUP( AD16, 'Tax Rates'!A:A, 'Tax Rates'!B:B)} -> 0.012779
A17: 15 | B17: {=_xlfn.XLOOKUP( A17, 'CMFA-CSCDA Grants'!A:A, 'CMFA-CSCDA Grants'!E:E)} -> Los Angeles | C17: {=_xlfn.XLOOKUP( A17, 'CMFA-CSCDA Grants'!A:A, 'CMFA-CSCDA Grants'!B:B)} -> Premiere Hollywood Apartments | D17: 5547013021 | F17: FALSE | G17: 5547-013-021 | H17: 6762 HAWTHORN AVE LOS ANGELES CA 90028 | I17: LOS ANGELES CA | J17: 90028-6108 | K17: 6762 Hawthorn Ave, Los Angeles, CA 90028 | L17: Premiere Hollywood Apartments | N17: manual_verified | O17: Five or more apartments | P17: Residential | Q17: 500 | R17: 2022 | S17: 69 | T17: 0 | U17: 69 | V17: 34696 | W17: 2025 | X17: 4462074 | Y17: 4244683 | Z17: =SUM(X17:Y17) -> 8706757 | AA17: 2021 | AB17: 2022 | AC17: 0 | AD17: 200 | AE17: LOS ANGELES | AF17: 34.100403 | AG17: -118.33729 | AH17: G F STEVENSON TR LOT 13 | AJ17: {=_xlfn.XLOOKUP( A17, 'CMFA-CSCDA Grants'!A:A, 'CMFA-CSCDA Grants'!O:O)} -> 69 | AK17: {=_xlfn.XLOOKUP( A17, 'CMFA-CSCDA Grants'!A:A, 'CMFA-CSCDA Grants'!P:P)} -> 69 | AL17: {=_xlfn.XLOOKUP( AD17, 'Tax Rates'!A:A, 'Tax Rates'!B:B)} -> 0.0118738
A18: 17 | B18: {=_xlfn.XLOOKUP( A18, 'CMFA-CSCDA Grants'!A:A, 'CMFA-CSCDA Grants'!E:E)} -> Los Angeles | C18: {=_xlfn.XLOOKUP( A18, 'CMFA-CSCDA Grants'!A:A, 'CMFA-CSCDA Grants'!B:B)} -> 4252 Crenshaw Apartments | D18: 5024017036 | F18: FALSE | G18: 5024-017-036 | H18: 4252 S CRENSHAW BLVD LOS ANGELES CA 90008 | I18: LOS ANGELES CA | J18: 90008 | K18: 4252 S CRENSHAW BLVD LOS ANGELES CA 90008 | L18: 4252 Crenshaw Apartments | N18: manual_verified | O18: Five or more apartments | P18: Residential | Q18: 504 | R18: 2019 | S18: 111 | T18: 99 | U18: 99 | V18: 49252 | W18: 2025 | X18: 4167019 | Y18: 22747841 | Z18: =SUM(X18:Y18) -> 26914860 | AA18: 2019 | AB18: 2020 | AC18: 26914860 | AD18: 8841 | AE18: LOS ANGELES | AF18: 34.006453 | AG18: -118.33416 | AH18: TR=10023 LOTS 93, 94, 95, 96, 97 AND 98 | AJ18: {=_xlfn.XLOOKUP( A18, 'CMFA-CSCDA Grants'!A:A, 'CMFA-CSCDA Grants'!O:O)} -> 111 | AK18: {=_xlfn.XLOOKUP( A18, 'CMFA-CSCDA Grants'!A:A, 'CMFA-CSCDA Grants'!P:P)} -> 111 | AL18: {=_xlfn.XLOOKUP( AD18, 'Tax Rates'!A:A, 'Tax Rates'!B:B)} -> 0.0118738
A19: 18 | B19: {=_xlfn.XLOOKUP( A19, 'CMFA-CSCDA Grants'!A:A, 'CMFA-CSCDA Grants'!E:E)} -> San Diego | C19: {=_xlfn.XLOOKUP( A19, 'CMFA-CSCDA Grants'!A:A, 'CMFA-CSCDA Grants'!B:B)} -> Fallbrook Trail Apartments | D19: 1043514700 | F19: FALSE | H19: 1735.0 S MISSION RD FALLBROOK CA 92028-4548 | X19: - | Y19: - | Z19: 32460480 | AD19: Carlsbad | AJ19: {=_xlfn.XLOOKUP( A19, 'CMFA-CSCDA Grants'!A:A, 'CMFA-CSCDA Grants'!O:O)} -> 103 | AK19: {=_xlfn.XLOOKUP( A19, 'CMFA-CSCDA Grants'!A:A, 'CMFA-CSCDA Grants'!P:P)} -> 102 | AL19: {=_xlfn.XLOOKUP( AD19, 'Tax Rates'!A:A, 'Tax Rates'!B:B)} -> 0.010783
A20: 19 | B20: {=_xlfn.XLOOKUP( A20, 'CMFA-CSCDA Grants'!A:A, 'CMFA-CSCDA Grants'!E:E)} -> Orange | C20: {=_xlfn.XLOOKUP( A20, 'CMFA-CSCDA Grants'!A:A, 'CMFA-CSCDA Grants'!B:B)} -> The Arbors Apartments | D20: 39612209 | F20: FALSE | H20: 1100.0 FAIRHAVEN AVE SANTA ANA CA 92705-6754 | X20: - | Y20: - | Z20: 18340000 | AD20: Santa Ana | AJ20: {=_xlfn.XLOOKUP( A20, 'CMFA-CSCDA Grants'!A:A, 'CMFA-CSCDA Grants'!O:O)} -> 160 | AK20: {=_xlfn.XLOOKUP( A20, 'CMFA-CSCDA Grants'!A:A, 'CMFA-CSCDA Grants'!P:P)} -> 160 | AL20: {=_xlfn.XLOOKUP( AD20, 'Tax Rates'!A:A, 'Tax Rates'!B:B)} -> 0.011195
A21: 19 | B21: {=_xlfn.XLOOKUP( A21, 'CMFA-CSCDA Grants'!A:A, 'CMFA-CSCDA Grants'!E:E)} -> Orange | C21: {=_xlfn.XLOOKUP( A21, 'CMFA-CSCDA Grants'!A:A, 'CMFA-CSCDA Grants'!B:B)} -> The Arbors Apartments | D21: 39612130 | F21: FALSE | H21: 1200 FAIRHAVEN AVE SANTA ANA CA 92705-6754 | X21: - | Y21: - | Z21: 22410000 | AD21: Santa Ana | AJ21: {=_xlfn.XLOOKUP( A21, 'CMFA-CSCDA Grants'!A:A, 'CMFA-CSCDA Grants'!O:O)} -> 160 | AK21: {=_xlfn.XLOOKUP( A21, 'CMFA-CSCDA Grants'!A:A, 'CMFA-CSCDA Grants'!P:P)} -> 160 | AL21: {=_xlfn.XLOOKUP( AD21, 'Tax Rates'!A:A, 'Tax Rates'!B:B)} -> 0.011195
A22: 20 | B22: {=_xlfn.XLOOKUP( A22, 'CMFA-CSCDA Grants'!A:A, 'CMFA-CSCDA Grants'!E:E)} -> Los Angeles | C22: {=_xlfn.XLOOKUP( A22, 'CMFA-CSCDA Grants'!A:A, 'CMFA-CSCDA Grants'!B:B)} -> Pinetree Terrace Apartments | D22: 2102015045 | F22: FALSE | G22: 2102-015-045 | H22: 7940 RESEDA BLVD LOS ANGELES CA 91335 | I22: LOS ANGELES CA | J22: 91335-1927 | K22: 7940 Reseda Boulevard, Reseda, CA | L22: Pinetree Terrace Apartments | N22: manual_verified | O22: Five or more apartments | P22: Residential | Q22: 501 | R22: 1978 | S22: 58 | T22: 8 | U22: 8 | V22: 63362 | W22: 2025 | X22: 7140000 | Y22: 10812000 | Z22: =SUM(X22:Y22) -> 17952000 | AA22: 2024 | AB22: 2024 | AC22: 15786989 | AD22: 8852 | AE22: LOS ANGELES | AF22: 34.215148 | AG22: -118.53554 | AH22: *TR=32921 LOT 1 | AJ22: {=_xlfn.XLOOKUP( A22, 'CMFA-CSCDA Grants'!A:A, 'CMFA-CSCDA Grants'!O:O)} -> 58 | AK22: {=_xlfn.XLOOKUP( A22, 'CMFA-CSCDA Grants'!A:A, 'CMFA-CSCDA Grants'!P:P)} -> 58 | AL22: {=_xlfn.XLOOKUP( AD22, 'Tax Rates'!A:A, 'Tax Rates'!B:B)} -> 0.0118738
A23: 21 | B23: {=_xlfn.XLOOKUP( A23, 'CMFA-CSCDA Grants'!A:A, 'CMFA-CSCDA Grants'!E:E)} -> Los Angeles | C23: {=_xlfn.XLOOKUP( A23, 'CMFA-CSCDA Grants'!A:A, 'CMFA-CSCDA Grants'!B:B)} -> Windmere Court Apartments | D23: 2119001222 | F23: FALSE | G23: 2119-001-222 | H23: 18325 SATICOY ST LOS ANGELES CA 91335 | I23: LOS ANGELES CA | J23: 91335-2965 | K23: 18325 Saticoy St, Reseda, CA 91335 | L23: Windmere Court Apartments | N23: manual_verified | O23: Five or more apartments | P23: Residential | Q23: 501 | R23: 1989 | S23: 52 | T23: 99 | U23: 99 | V23: 53440 | W23: 2025 | X23: 7140000 | Y23: 9486000 | Z23: =SUM(X23:Y23) -> 16626000 | AA23: 2024 | AB23: 2024 | AC23: 16306781 | AD23: 8852 | AE23: LOS ANGELES | AF23: 34.208888 | AG23: -118.53263 | AH23: TR=9035 POR OF LOT 32 AND ALL OF LOT 31 | AJ23: {=_xlfn.XLOOKUP( A23, 'CMFA-CSCDA Grants'!A:A, 'CMFA-CSCDA Grants'!O:O)} -> 52 | AK23: {=_xlfn.XLOOKUP( A23, 'CMFA-CSCDA Grants'!A:A, 'CMFA-CSCDA Grants'!P:P)} -> 52 | AL23: {=_xlfn.XLOOKUP( AD23, 'Tax Rates'!A:A, 'Tax Rates'!B:B)} -> 0.0118738
A24: 22 | B24: {=_xlfn.XLOOKUP( A24, 'CMFA-CSCDA Grants'!A:A, 'CMFA-CSCDA Grants'!E:E)} -> Los Angeles | C24: {=_xlfn.XLOOKUP( A24, 'CMFA-CSCDA Grants'!A:A, 'CMFA-CSCDA Grants'!B:B)} -> Seville Gardens Apartments | D24: 6320011041 | F24: FALSE | G24: 6320-011-041 | H24: 2701 RANDOLPH ST HUNTINGTON PARK CA 90255 | I24: HUNTINGTON PARK CA | J24: 90255-3076 | K24: 2701 Randolph St., Huntington Park, CA | L24: Seville Gardens Apartments | N24: manual_verified | O24: Five or more apartments | P24: Residential | Q24: 550 | R24: 1989 | S24: 255 | T24: 0 | U24: 0 | V24: 121632 | W24: 2025 | X24: 6885000 | Y24: 27540000 | Z24: =SUM(X24:Y24) -> 34425000 | AA24: 2024 | AB24: 2024 | AC24: 31825913 | AD24: 594 | AE24: HUNTINGTON PARK | AF24: 33.9855 | AG24: -118.22199 | AH24: TR=45269 LOT 1 | AJ24: {=_xlfn.XLOOKUP( A24, 'CMFA-CSCDA Grants'!A:A, 'CMFA-CSCDA Grants'!O:O)} -> 225 | AK24: {=_xlfn.XLOOKUP( A24, 'CMFA-CSCDA Grants'!A:A, 'CMFA-CSCDA Grants'!P:P)} -> 225 | AL24: {=_xlfn.XLOOKUP( AD24, 'Tax Rates'!A:A, 'Tax Rates'!B:B)} -> 0.01385148
A25: 23 | B25: {=_xlfn.XLOOKUP( A25, 'CMFA-CSCDA Grants'!A:A, 'CMFA-CSCDA Grants'!E:E)} -> Los Angeles | C25: {=_xlfn.XLOOKUP( A25, 'CMFA-CSCDA Grants'!A:A, 'CMFA-CSCDA Grants'!B:B)} -> Harbour Residences Apartments | D25: 7418014021 | F25: FALSE | G25: 7418-014-021 | H25: 445 N AVALON BLVD LOS ANGELES CA 90744 | I25: LOS ANGELES CA | J25: 90744-5803 | K25: 445 N. Avalon Boulevard, Los Angeles, CA | L25: Harbour Residences Apartments | N25: manual_verified | O25: Stores | P25: Commercial | Q25: 1100 | W25: 2025 | X25: 3203998 | Y25: 5695680 | Z25: =SUM(X25:Y25) -> 8899678 | AA25: 2021 | AB25: 2024 | AC25: 0 | AD25: 400 | AE25: LOS ANGELES | AF25: 33.775354 | AG25: -118.26245 | AH25: WILMINGTON RANGE 5 EX OF ST LOT 2 AND ALL OF LOT 6 BLK 12 | AJ25: {=_xlfn.XLOOKUP( A25, 'CMFA-CSCDA Grants'!A:A, 'CMFA-CSCDA Grants'!O:O)} -> 74 | AK25: {=_xlfn.XLOOKUP( A25, 'CMFA-CSCDA Grants'!A:A, 'CMFA-CSCDA Grants'!P:P)} -> 74 | AL25: {=_xlfn.XLOOKUP( AD25, 'Tax Rates'!A:A, 'Tax Rates'!B:B)} -> 0.0118738
A26: 24 | B26: {=_xlfn.XLOOKUP( A26, 'CMFA-CSCDA Grants'!A:A, 'CMFA-CSCDA Grants'!E:E)} -> Los Angeles | C26: {=_xlfn.XLOOKUP( A26, 'CMFA-CSCDA Grants'!A:A, 'CMFA-CSCDA Grants'!B:B)} -> 4209 Western Avenue Apartments | D26: 5021028002 | F26: FALSE | G26: 5021-028-002 | H26: 4209 S WESTERN AVE LOS ANGELES CA 90062 | I26: LOS ANGELES CA | J26: 90062-1643 | K26: 4209 S Western Ave, Los Angeles, CA 90062 | L26: 4209 Western Avenue Apartments | N26: manual_verified | O26: Store Combination | P26: Commercial | Q26: 1210 | R26: 2022 | S26: 25 | T26: 11 | U26: 25 | V26: 21557 | W26: 2025 | X26: 6242400 | Y26: 4681800 | Z26: =SUM(X26:Y26) -> 10924200 | AA26: 2023 | AB26: 2023 | AC26: 10903361 | AD26: 68 | AE26: LOS ANGELES | AF26: 34.006965 | AG26: -118.30926 | AH26: VERMONT AVE SQUARE LOT 2 BLK 65 | AJ26: {=_xlfn.XLOOKUP( A26, 'CMFA-CSCDA Grants'!A:A, 'CMFA-CSCDA Grants'!O:O)} -> 25 | AK26: {=_xlfn.XLOOKUP( A26, 'CMFA-CSCDA Grants'!A:A, 'CMFA-CSCDA Grants'!P:P)} -> 24 | AL26: {=_xlfn.XLOOKUP( AD26, 'Tax Rates'!A:A, 'Tax Rates'!B:B)} -> 0.0118738
A27: 25 | B27: {=_xlfn.XLOOKUP( A27, 'CMFA-CSCDA Grants'!A:A, 'CMFA-CSCDA Grants'!E:E)} -> Los Angeles | C27: {=_xlfn.XLOOKUP( A27, 'CMFA-CSCDA Grants'!A:A, 'CMFA-CSCDA Grants'!B:B)} -> 1130 Martin Luther King Jr. Blvd Apartments | D27: 5020017007 | F27: FALSE | G27: 5020-017-007 | H27: 1130 W MARTIN LUTHER KING JR BLVD LOS ANGELES CA 90037 | I27: LOS ANGELES CA | J27: 90037-1810 | K27: 1130 W Martin Luther King Jr Blvd, Los Angeles, CA 90037 | L27: 1130 Martin Luther King Jr. Blvd Apartments | N27: manual_verified | O27: Store Combination | P27: Commercial | Q27: 1210 | R27: 2021 | S27: 29 | T27: 22 | U27: 29 | V27: 15451 | W27: 2025 | X27: 9155520 | Y27: 3641400 | Z27: =SUM(X27:Y27) -> 12796920 | AA27: 2023 | AB27: 2023 | AC27: 12776081 | AD27: 212 | AE27: LOS ANGELES | AF27: 34.010524 | AG27: -118.29526 | AH27: WEST PARK TRACT NO 2 LOT 10 BLK G | AJ27: {=_xlfn.XLOOKUP( A27, 'CMFA-CSCDA Grants'!A:A, 'CMFA-CSCDA Grants'!O:O)} -> 29 | AK27: {=_xlfn.XLOOKUP( A27, 'CMFA-CSCDA Grants'!A:A, 'CMFA-CSCDA Grants'!P:P)} -> 28 | AL27: {=_xlfn.XLOOKUP( AD27, 'Tax Rates'!A:A, 'Tax Rates'!B:B)} -> 0.0118738
A28: 26 | B28: {=_xlfn.XLOOKUP( A28, 'CMFA-CSCDA Grants'!A:A, 'CMFA-CSCDA Grants'!E:E)} -> Los Angeles | C28: {=_xlfn.XLOOKUP( A28, 'CMFA-CSCDA Grants'!A:A, 'CMFA-CSCDA Grants'!B:B)} -> Harbor Terrace Apartments | D28: 7455002027 | F28: FALSE | G28: 7455-002-027 | H28: 441 W 3RD ST LOS ANGELES CA 90731 | I28: LOS ANGELES CA | J28: 90731-2650 | K28: 441 W 3rd St, San Pedro, CA 90731 | L28: Harbor Terrace Apartments | N28: manual_verified | O28: Five or more apartments | P28: Residential | Q28: 500 | R28: 1987 | S28: 93 | T28: 78 | U28: 93 | V28: 55726 | W28: 2025 | X28: 2860000 | Y28: 21390000 | Z28: =SUM(X28:Y28) -> 24250000 | AA28: 2025 | AB28: 2025 | AC28: 16429375 | AD28: 13245 | AE28: LOS ANGELES | AF28: 33.741017 | AG28: -118.28695 | AH28: LOT A P M 179-44-45 AND E 130 FT OF LOT 2 BLK 4 TOWN OF SAN PEDRO | AJ28: {=_xlfn.XLOOKUP( A28, 'CMFA-CSCDA Grants'!A:A, 'CMFA-CSCDA Grants'!O:O)} -> 93 | AK28: {=_xlfn.XLOOKUP( A28, 'CMFA-CSCDA Grants'!A:A, 'CMFA-CSCDA Grants'!P:P)} -> 93 | AL28: {=_xlfn.XLOOKUP( AD28, 'Tax Rates'!A:A, 'Tax Rates'!B:B)} -> 0.0118738
A29: 27 | B29: {=_xlfn.XLOOKUP( A29, 'CMFA-CSCDA Grants'!A:A, 'CMFA-CSCDA Grants'!E:E)} -> Los Angeles | C29: {=_xlfn.XLOOKUP( A29, 'CMFA-CSCDA Grants'!A:A, 'CMFA-CSCDA Grants'!B:B)} -> Santa Monica Portfolio A Apartments | D29: 4291019007 | F29: FALSE | G29: 4291-019-007 | H29: 1428 6TH ST SANTA MONICA CA 90401 | I29: SANTA MONICA CA | J29: 90401-2592 | K29: 1422-1428 6th St., Santa Monica, CA | L29: Santa Monica Portfolio A Apartments | N29: manual_verified_multi | O29: Five or more apartments | P29: Residential | Q29: 500 | R29: 1998 | S29: 24 | T29: 30 | U29: 36 | V29: 20272 | W29: 2025 | X29: 2850000 | Y29: 5670000 | Z29: =SUM(X29:Y29) -> 8520000 | AA29: 2025 | AB29: 2025 | AC29: 1937646 | AD29: 8004 | AE29: SANTA MONICA | AF29: 34.01711 | AG29: -118.49281 | AH29: SANTA MON1CA LOT F BLK 169 | AI29: Multi-parcel (2) | AJ29: {=_xlfn.XLOOKUP( A29, 'CMFA-CSCDA Grants'!A:A, 'CMFA-CSCDA Grants'!O:O)} -> 52 | AK29: {=_xlfn.XLOOKUP( A29, 'CMFA-CSCDA Grants'!A:A, 'CMFA-CSCDA Grants'!P:P)} -> 32 | AL29: {=_xlfn.XLOOKUP( AD29, 'Tax Rates'!A:A, 'Tax Rates'!B:B)} -> 0.01203757
A30: 27 | B30: {=_xlfn.XLOOKUP( A30, 'CMFA-CSCDA Grants'!A:A, 'CMFA-CSCDA Grants'!E:E)} -> Los Angeles | C30: {=_xlfn.XLOOKUP( A30, 'CMFA-CSCDA Grants'!A:A, 'CMFA-CSCDA Grants'!B:B)} -> Santa Monica Portfolio A Apartments | D30: 4291019006 | F30: FALSE | G30: 4291-019-006 | H30: 1422 6TH ST SANTA MONICA CA 90401 | I30: SANTA MONICA CA | J30: 90401-2542 | K30: 1422-1428 6th St., Santa Monica, CA | L30: Santa Monica Portfolio A Apartments | N30: manual_verified_multi | O30: Store Combination | P30: Commercial | Q30: 1210 | R30: 1997 | S30: 28 | T30: 26 | U30: 28 | V30: 20618 | W30: 2025 | X30: 2850000 | Y30: 5800000 | Z30: =SUM(X30:Y30) -> 8650000 | AA30: 2025 | AB30: 2025 | AC30: 2125161 | AD30: 8004 | AE30: SANTA MONICA | AF30: 34.017208 | AG30: -118.49292 | AH30: SANTA MON1CA LOT E BLK 169 | AI30: Multi-parcel (2) | AJ30: {=_xlfn.XLOOKUP( A30, 'CMFA-CSCDA Grants'!A:A, 'CMFA-CSCDA Grants'!O:O)} -> 52 | AK30: {=_xlfn.XLOOKUP( A30, 'CMFA-CSCDA Grants'!A:A, 'CMFA-CSCDA Grants'!P:P)} -> 32 | AL30: {=_xlfn.XLOOKUP( AD30, 'Tax Rates'!A:A, 'Tax Rates'!B:B)} -> 0.01203757
A31: 28 | B31: {=_xlfn.XLOOKUP( A31, 'CMFA-CSCDA Grants'!A:A, 'CMFA-CSCDA Grants'!E:E)} -> Los Angeles | C31: {=_xlfn.XLOOKUP( A31, 'CMFA-CSCDA Grants'!A:A, 'CMFA-CSCDA Grants'!B:B)} -> Santa Monica Portfolio B Apartments | D31: 4291020005 | F31: FALSE | G31: 4291-020-005 | H31: 1422 7TH ST SANTA MONICA CA 90401 | I31: SANTA MONICA CA | J31: 90401-2653 | K31: 1422-1432 7th, Santa Monica, CA | L31: Santa Monica Portfolio B Apartments | N31: manual_verified_multi | O31: Five or more apartments | P31: Residential | Q31: 500 | R31: 1996 | S31: 28 | T31: 28 | U31: 28 | V31: 21437 | W31: 2025 | X31: 3000000 | Y31: 4650000 | Z31: =SUM(X31:Y31) -> 7650000 | AA31: 2025 | AB31: 2025 | AC31: 3491875 | AD31: 8004 | AE31: SANTA MONICA | AF31: 34.017975 | AG31: -118.49198 | AH31: SANTA MON1CA LOT E BLK 168 | AI31: Multi-parcel (3) | AJ31: {=_xlfn.XLOOKUP( A31, 'CMFA-CSCDA Grants'!A:A, 'CMFA-CSCDA Grants'!O:O)} -> 72 | AK31: {=_xlfn.XLOOKUP( A31, 'CMFA-CSCDA Grants'!A:A, 'CMFA-CSCDA Grants'!P:P)} -> 49 | AL31: {=_xlfn.XLOOKUP( AD31, 'Tax Rates'!A:A, 'Tax Rates'!B:B)} -> 0.01203757
A32: 28 | B32: {=_xlfn.XLOOKUP( A32, 'CMFA-CSCDA Grants'!A:A, 'CMFA-CSCDA Grants'!E:E)} -> Los Angeles | C32: {=_xlfn.XLOOKUP( A32, 'CMFA-CSCDA Grants'!A:A, 'CMFA-CSCDA Grants'!B:B)} -> Santa Monica Portfolio B Apartments | D32: 4291020006 | F32: FALSE | G32: 4291-020-006 | H32: 1430 7TH ST SANTA MONICA CA 90401 | I32: SANTA MONICA CA | J32: 90401-2600 | K32: 1422-1432 7th, Santa Monica, CA | L32: Santa Monica Portfolio B Apartments | N32: manual_verified_multi | O32: Five or more apartments | P32: Residential | Q32: 500 | R32: 1996 | S32: 28 | T32: 28 | U32: 28 | V32: 21437 | W32: 2025 | X32: 3000000 | Y32: 4650000 | Z32: =SUM(X32:Y32) -> 7650000 | AA32: 2025 | AB32: 2025 | AC32: 3491875 | AD32: 8004 | AE32: SANTA MONICA | AF32: 34.017876 | AG32: -118.49186 | AH32: SANTA MON1CA LOT F BLK 168 | AI32: Multi-parcel (3) | AJ32: {=_xlfn.XLOOKUP( A32, 'CMFA-CSCDA Grants'!A:A, 'CMFA-CSCDA Grants'!O:O)} -> 72 | AK32: {=_xlfn.XLOOKUP( A32, 'CMFA-CSCDA Grants'!A:A, 'CMFA-CSCDA Grants'!P:P)} -> 49 | AL32: {=_xlfn.XLOOKUP( AD32, 'Tax Rates'!A:A, 'Tax Rates'!B:B)} -> 0.01203757
A33: 28 | B33: {=_xlfn.XLOOKUP( A33, 'CMFA-CSCDA Grants'!A:A, 'CMFA-CSCDA Grants'!E:E)} -> Los Angeles | C33: {=_xlfn.XLOOKUP( A33, 'CMFA-CSCDA Grants'!A:A, 'CMFA-CSCDA Grants'!B:B)} -> Santa Monica Portfolio B Apartments | D33: 4291020007 | F33: FALSE | G33: 4291-020-007 | H33: 1432 7TH ST SANTA MONICA CA 90401 | I33: SANTA MONICA CA | J33: 90401-2612 | K33: 1422-1432 7th, Santa Monica, CA | L33: Santa Monica Portfolio B Apartments | N33: manual_verified_multi | O33: Five or more apartments | P33: Residential | Q33: 500 | R33: 2000 | S33: 26 | T33: 30 | U33: 26 | V33: 21878 | W33: 2025 | X33: 3000000 | Y33: 4770000 | Z33: =SUM(X33:Y33) -> 7770000 | AA33: 2025 | AB33: 2025 | AC33: 3594576 | AD33: 8004 | AE33: SANTA MONICA | AF33: 34.017778 | AG33: -118.49175 | AH33: SANTA MON1CA LOT G BLK 168 | AI33: Multi-parcel (3) | AJ33: {=_xlfn.XLOOKUP( A33, 'CMFA-CSCDA Grants'!A:A, 'CMFA-CSCDA Grants'!O:O)} -> 72 | AK33: {=_xlfn.XLOOKUP( A33, 'CMFA-CSCDA Grants'!A:A, 'CMFA-CSCDA Grants'!P:P)} -> 49 | AL33: {=_xlfn.XLOOKUP( AD33, 'Tax Rates'!A:A, 'Tax Rates'!B:B)} -> 0.01203757
A34: 29 | B34: {=_xlfn.XLOOKUP( A34, 'CMFA-CSCDA Grants'!A:A, 'CMFA-CSCDA Grants'!E:E)} -> Los Angeles | C34: {=_xlfn.XLOOKUP( A34, 'CMFA-CSCDA Grants'!A:A, 'CMFA-CSCDA Grants'!B:B)} -> Santa Monica Portfolio C Apartments | D34: 4291020018 | F34: FALSE | G34: 4291-020-018 | H34: 1425 6TH ST SANTA MONICA CA 90401 | I34: SANTA MONICA CA | J34: 90401-2558 | K34: 1423-1425 6th, Santa Monica, CA | L34: Santa Monica Portfolio C Apartments | N34: manual_verified_multi | O34: Five or more apartments | P34: Residential | Q34: 500 | R34: 1998 | S34: 24 | T34: 33 | U34: 30 | V34: 20100 | W34: 2025 | X34: 6300000 | Y34: 4150000 | Z34: =SUM(X34:Y34) -> 10450000 | AA34: 2025 | AB34: 2025 | AC34: 5443405 | AD34: 8004 | AE34: SANTA MONICA | AF34: 34.017551 | AG34: -118.49226 | AH34: SANTA MON1CA LOT S BLK 168 | AI34: Multi-parcel (2) | AJ34: {=_xlfn.XLOOKUP( A34, 'CMFA-CSCDA Grants'!A:A, 'CMFA-CSCDA Grants'!O:O)} -> 48 | AK34: {=_xlfn.XLOOKUP( A34, 'CMFA-CSCDA Grants'!A:A, 'CMFA-CSCDA Grants'!P:P)} -> 29 | AL34: {=_xlfn.XLOOKUP( AD34, 'Tax Rates'!A:A, 'Tax Rates'!B:B)} -> 0.01203757
A35: 29 | B35: {=_xlfn.XLOOKUP( A35, 'CMFA-CSCDA Grants'!A:A, 'CMFA-CSCDA Grants'!E:E)} -> Los Angeles | C35: {=_xlfn.XLOOKUP( A35, 'CMFA-CSCDA Grants'!A:A, 'CMFA-CSCDA Grants'!B:B)} -> Santa Monica Portfolio C Apartments | D35: 4291020019 | F35: FALSE | G35: 4291-020-019 | H35: 1423 6TH ST SANTA MONICA CA 90401 | I35: SANTA MONICA CA | J35: 90401-2593 | K35: 1423-1425 6th, Santa Monica, CA | L35: Santa Monica Portfolio C Apartments | N35: manual_verified_multi | O35: Five or more apartments | P35: Residential | Q35: 500 | R35: 1998 | S35: 24 | T35: 0 | U35: 0 | V35: 20100 | W35: 2025 | X35: 6300000 | Y35: 4150000 | Z35: =SUM(X35:Y35) -> 10450000 | AA35: 2025 | AB35: 2025 | AC35: 5443405 | AD35: 8004 | AE35: SANTA MONICA | AF35: 34.017649 | AG35: -118.49238 | AH35: SANTA MON1CA LOT T BLK 168 | AI35: Multi-parcel (2) | AJ35: {=_xlfn.XLOOKUP( A35, 'CMFA-CSCDA Grants'!A:A, 'CMFA-CSCDA Grants'!O:O)} -> 48 | AK35: {=_xlfn.XLOOKUP( A35, 'CMFA-CSCDA Grants'!A:A, 'CMFA-CSCDA Grants'!P:P)} -> 29 | AL35: {=_xlfn.XLOOKUP( AD35, 'Tax Rates'!A:A, 'Tax Rates'!B:B)} -> 0.01203757
A36: 30 | B36: {=_xlfn.XLOOKUP( A36, 'CMFA-CSCDA Grants'!A:A, 'CMFA-CSCDA Grants'!E:E)} -> Los Angeles | C36: {=_xlfn.XLOOKUP( A36, 'CMFA-CSCDA Grants'!A:A, 'CMFA-CSCDA Grants'!B:B)} -> Santa Monica Portfolio D Apartments | D36: 4291024007 | F36: FALSE | G36: 4291-024-007 | H36: 1522 6TH ST SANTA MONICA CA 90401 | I36: SANTA MONICA CA | J36: 90401-2548 | K36: 1522 6th St, Santa Monica, CA | L36: Santa Monica Portfolio D Apartments | N36: manual_verified | O36: Five or more apartments | P36: Residential | Q36: 550 | R36: 2004 | S36: 26 | T36: 29 | U36: 26 | V36: 24573 | W36: 2025 | X36: 3600000 | Y36: 3450000 | Z36: =SUM(X36:Y36) -> 7050000 | AA36: 2025 | AB36: 2025 | AC36: 3659058 | AD36: 8004 | AE36: SANTA MONICA | AF36: 34.01587 | AG36: -118.49136 | AH36: SANTA MONICA LOT E BLK 194 | AJ36: {=_xlfn.XLOOKUP( A36, 'CMFA-CSCDA Grants'!A:A, 'CMFA-CSCDA Grants'!O:O)} -> 26 | AK36: {=_xlfn.XLOOKUP( A36, 'CMFA-CSCDA Grants'!A:A, 'CMFA-CSCDA Grants'!P:P)} -> 25 | AL36: {=_xlfn.XLOOKUP( AD36, 'Tax Rates'!A:A, 'Tax Rates'!B:B)} -> 0.01203757
A37: 31 | B37: {=_xlfn.XLOOKUP( A37, 'CMFA-CSCDA Grants'!A:A, 'CMFA-CSCDA Grants'!E:E)} -> Los Angeles | C37: {=_xlfn.XLOOKUP( A37, 'CMFA-CSCDA Grants'!A:A, 'CMFA-CSCDA Grants'!B:B)} -> Santa Monica Portfolio E Apartments | D37: 4291022015 | F37: FALSE | G37: 4291-022-015 | H37: 1537 7TH ST SANTA MONICA CA 90401 | I37: SANTA MONICA CA | J37: 90401-2672 | K37: 1537 7th, Santa Monica, CA | L37: Santa Monica Portfolio E Apartments | N37: manual_verified | O37: Five or more apartments | P37: Residential | Q37: 540 | R37: 2003 | S37: 36 | T37: 0 | U37: 0 | V37: 24738 | W37: 2025 | X37: 3600000 | Y37: 2980000 | Z37: =SUM(X37:Y37) -> 6580000 | AA37: 2025 | AB37: 2025 | AC37: 4088045 | AD37: 8004 | AE37: SANTA MONICA | AF37: 34.016781 | AG37: -118.48952 | AH37: SANTA MON1CA LOT Q BLK 192 | AJ37: {=_xlfn.XLOOKUP( A37, 'CMFA-CSCDA Grants'!A:A, 'CMFA-CSCDA Grants'!O:O)} -> 26 | AK37: {=_xlfn.XLOOKUP( A37, 'CMFA-CSCDA Grants'!A:A, 'CMFA-CSCDA Grants'!P:P)} -> 25 | AL37: {=_xlfn.XLOOKUP( AD37, 'Tax Rates'!A:A, 'Tax Rates'!B:B)} -> 0.01203757
A38: 32 | B38: {=_xlfn.XLOOKUP( A38, 'CMFA-CSCDA Grants'!A:A, 'CMFA-CSCDA Grants'!E:E)} -> Los Angeles | C38: {=_xlfn.XLOOKUP( A38, 'CMFA-CSCDA Grants'!A:A, 'CMFA-CSCDA Grants'!B:B)} -> Santa Monica Portfolio F Apartments | D38: 4275024005 | F38: FALSE | G38: 4275-024-005 | H38: 2001 OLYMPIC BLVD SANTA MONICA CA 90404 | I38: SANTA MONICA CA | J38: 90404-3942 | K38: 2001-2029 Olympic Blvd, Santa Monica | L38: Santa Monica Portfolio F Apartments | N38: manual_verified_multi | O38: Five or more apartments | P38: Residential | Q38: 500 | R38: 2008 | S38: 100 | T38: 0 | U38: 99 | V38: 51033 | W38: 2025 | X38: 2130000 | Y38: 6860000 | Z38: =SUM(X38:Y38) -> 8990000 | AA38: 2025 | AB38: 2025 | AC38: 8990000 | AD38: 8004 | AE38: SANTA MONICA | AF38: 34.025001 | AG38: -118.47522 | AH38: ERKENBRECHER SYNDICATE SANTA MONICA TRACT EX OF ST LOT 6 BLK 20 | AI38: Multi-parcel (2) | AJ38: {=_xlfn.XLOOKUP( A38, 'CMFA-CSCDA Grants'!A:A, 'CMFA-CSCDA Grants'!O:O)} -> 165 | AK38: {=_xlfn.XLOOKUP( A38, 'CMFA-CSCDA Grants'!A:A, 'CMFA-CSCDA Grants'!P:P)} -> 98 | AL38: {=_xlfn.XLOOKUP( AD38, 'Tax Rates'!A:A, 'Tax Rates'!B:B)} -> 0.01203757
A39: 32 | B39: {=_xlfn.XLOOKUP( A39, 'CMFA-CSCDA Grants'!A:A, 'CMFA-CSCDA Grants'!E:E)} -> Los Angeles | C39: {=_xlfn.XLOOKUP( A39, 'CMFA-CSCDA Grants'!A:A, 'CMFA-CSCDA Grants'!B:B)} -> Santa Monica Portfolio F Apartments | D39: 4275024015 | F39: FALSE | G39: 4275-024-015 | H39: 2029 OLYMPIC BLVD SANTA MONICA CA 90404 | I39: SANTA MONICA CA | J39: 90404-3922 | K39: 2001-2029 Olympic Blvd, Santa Monica | L39: Santa Monica Portfolio F Apartments | N39: manual_verified_multi | O39: Five or more apartments | P39: Residential | Q39: 500 | R39: 2009 | S39: 29 | T39: 0 | U39: 29 | V39: 13940 | W39: 2025 | X39: 5418000 | Y39: 14942000 | Z39: =SUM(X39:Y39) -> 20360000 | AA39: 2025 | AB39: 2025 | AC39: 13362409 | AD39: 8004 | AE39: SANTA MONICA | AF39: 34.025231 | AG39: -118.47476 | AH39: MB 6-26-27 LOT 5 AND EX OF ST LOTS 7,9 AND 11 | AI39: Multi-parcel (2) | AJ39: {=_xlfn.XLOOKUP( A39, 'CMFA-CSCDA Grants'!A:A, 'CMFA-CSCDA Grants'!O:O)} -> 165 | AK39: {=_xlfn.XLOOKUP( A39, 'CMFA-CSCDA Grants'!A:A, 'CMFA-CSCDA Grants'!P:P)} -> 98 | AL39: {=_xlfn.XLOOKUP( AD39, 'Tax Rates'!A:A, 'Tax Rates'!B:B)} -> 0.01203757
A40: 33 | B40: {=_xlfn.XLOOKUP( A40, 'CMFA-CSCDA Grants'!A:A, 'CMFA-CSCDA Grants'!E:E)} -> Los Angeles | C40: {=_xlfn.XLOOKUP( A40, 'CMFA-CSCDA Grants'!A:A, 'CMFA-CSCDA Grants'!B:B)} -> 7524 S. Hoover St. Apartments | D40: 6020022027 | E40: 6020022025 | F40: TRUE | G40: 6020-022-027 | H40: 7524 S HOOVER ST | I40: LOS ANGELES CA | K40: 7518 S. Hoover, Los Angeles, CA | L40: 7524 S. Hoover St. Apartments | N40: parcel_in_transition | O40: Single Family Residence | P40: Residential | W40: 2025 | X40: 0 | Y40: 0 | Z40: =SUM(X40:Y40) -> 0 | AA40: 2024 | AB40: 2024 | AC40: 0 | AD40: 212 | AE40: LOS ANGELES | AF40: 33.971016 | AG40: -118.28679 | AI40: Legacy AIN 6020022025 no longer exists. New AIN 6020022027 has no data yet. | AJ40: {=_xlfn.XLOOKUP( A40, 'CMFA-CSCDA Grants'!A:A, 'CMFA-CSCDA Grants'!O:O)} -> 79 | AK40: {=_xlfn.XLOOKUP( A40, 'CMFA-CSCDA Grants'!A:A, 'CMFA-CSCDA Grants'!P:P)} -> 48 | AL40: {=_xlfn.XLOOKUP( AD40, 'Tax Rates'!A:A, 'Tax Rates'!B:B)} -> 0.0118738
A41: 34 | B41: {=_xlfn.XLOOKUP( A41, 'CMFA-CSCDA Grants'!A:A, 'CMFA-CSCDA Grants'!E:E)} -> Contra Costa | C41: {=_xlfn.XLOOKUP( A41, 'CMFA-CSCDA Grants'!A:A, 'CMFA-CSCDA Grants'!B:B)} -> Appian Terrace Apartments | D41: 4251100188 | F41: FALSE | H41: 4481.0 APPIAN WAY EL SOBRANTE CA 94803-2200 | X41: - | Y41: - | Z41: 9977564 | AC41: 0 | AD41: El Sobrante | AJ41: {=_xlfn.XLOOKUP( A41, 'CMFA-CSCDA Grants'!A:A, 'CMFA-CSCDA Grants'!O:O)} -> 41 | AK41: {=_xlfn.XLOOKUP( A41, 'CMFA-CSCDA Grants'!A:A, 'CMFA-CSCDA Grants'!P:P)} -> 41 | AL41: {=_xlfn.XLOOKUP( AD41, 'Tax Rates'!A:A, 'Tax Rates'!B:B)} -> 0.012792
A42: 35 | B42: {=_xlfn.XLOOKUP( A42, 'CMFA-CSCDA Grants'!A:A, 'CMFA-CSCDA Grants'!E:E)} -> Sacramento | C42: {=_xlfn.XLOOKUP( A42, 'CMFA-CSCDA Grants'!A:A, 'CMFA-CSCDA Grants'!B:B)} -> Sierra Park Apartments | D42: 22802520400000 | F42: FALSE | G42: 228-0252-040-0000 | H42: 4924 POLK ST NORTH HIGHLANDS CA 95660 | K42: 4930 POLK ST NORTH HIGHLANDS CA 95660 | X42: 2913120 | Y42: 22733780 | Z42: =sum(X42,Y42) -> 25646900 | AC42: 23179668 | AD42: North Highlands | AJ42: {=_xlfn.XLOOKUP( A42, 'CMFA-CSCDA Grants'!A:A, 'CMFA-CSCDA Grants'!O:O)} -> 104 | AK42: {=_xlfn.XLOOKUP( A42, 'CMFA-CSCDA Grants'!A:A, 'CMFA-CSCDA Grants'!P:P)} -> 104 | AL42: {=_xlfn.XLOOKUP( AD42, 'Tax Rates'!A:A, 'Tax Rates'!B:B)} -> 0.011785
A43: 36 | B43: {=_xlfn.XLOOKUP( A43, 'CMFA-CSCDA Grants'!A:A, 'CMFA-CSCDA Grants'!E:E)} -> Los Angeles | C43: {=_xlfn.XLOOKUP( A43, 'CMFA-CSCDA Grants'!A:A, 'CMFA-CSCDA Grants'!B:B)} -> Stadium Village Apartments | D43: 4025014001 | F43: FALSE | G43: 4025-014-001 | H43: 9301 CRENSHAW BLVD INGLEWOOD CA 90305 | I43: INGLEWOOD CA | J43: 90305-2943 | K43: 9301 – 9609 Crenshaw Blvd, Inglewood, CA | L43: Stadium Village Apartments | N43: manual_verified_multi | O43: Four Units (Any Combination) | P43: Residential | Q43: 400 | R43: 1955 | S43: 4 | T43: 8 | U43: 4 | V43: 4073 | W43: 2025 | X43: 770000 | Y43: 575000 | Z43: =SUM(X43:Y43) -> 1345000 | AA43: 2025 | AB43: 2025 | AC43: 0 | AD43: 4569 | AE43: INGLEWOOD | AF43: 33.952117 | AG43: -118.32698 | AH43: TRACT NO 16139 LOT 1 | AI43: Multi-parcel (20) | AJ43: {=_xlfn.XLOOKUP( A43, 'CMFA-CSCDA Grants'!A:A, 'CMFA-CSCDA Grants'!O:O)} -> 80 | AK43: {=_xlfn.XLOOKUP( A43, 'CMFA-CSCDA Grants'!A:A, 'CMFA-CSCDA Grants'!P:P)} -> 80 | AL43: {=_xlfn.XLOOKUP( AD43, 'Tax Rates'!A:A, 'Tax Rates'!B:B)} -> 0.01280765
A44: 36 | B44: {=_xlfn.XLOOKUP( A44, 'CMFA-CSCDA Grants'!A:A, 'CMFA-CSCDA Grants'!E:E)} -> Los Angeles | C44: {=_xlfn.XLOOKUP( A44, 'CMFA-CSCDA Grants'!A:A, 'CMFA-CSCDA Grants'!B:B)} -> Stadium Village Apartments | D44: 4025014002 | F44: FALSE | G44: 4025-014-002 | H44: 9309 CRENSHAW BLVD INGLEWOOD CA 90305 | I44: INGLEWOOD CA | J44: 90305-2951 | K44: 9301 – 9609 Crenshaw Blvd, Inglewood, CA | L44: Stadium Village Apartments | N44: manual_verified_multi | O44: Four Units (Any Combination) | P44: Residential | Q44: 400 | R44: 1955 | S44: 4 | T44: 8 | U44: 4 | V44: 4072 | W44: 2025 | X44: 770000 | Y44: 575000 | Z44: =SUM(X44:Y44) -> 1345000 | AA44: 2025 | AB44: 2025 | AC44: 0 | AD44: 4569 | AE44: INGLEWOOD | AF44: 33.951945 | AG44: -118.32697 | AH44: TRACT NO 16139 LOT 2 | AI44: Multi-parcel (20) | AJ44: {=_xlfn.XLOOKUP( A44, 'CMFA-CSCDA Grants'!A:A, 'CMFA-CSCDA Grants'!O:O)} -> 80 | AK44: {=_xlfn.XLOOKUP( A44, 'CMFA-CSCDA Grants'!A:A, 'CMFA-CSCDA Grants'!P:P)} -> 80 | AL44: {=_xlfn.XLOOKUP( AD44, 'Tax Rates'!A:A, 'Tax Rates'!B:B)} -> 0.01280765
A45: 36 | B45: {=_xlfn.XLOOKUP( A45, 'CMFA-CSCDA Grants'!A:A, 'CMFA-CSCDA Grants'!E:E)} -> Los Angeles | C45: {=_xlfn.XLOOKUP( A45, 'CMFA-CSCDA Grants'!A:A, 'CMFA-CSCDA Grants'!B:B)} -> Stadium Village Apartments | D45: 4025014003 | F45: FALSE | G45: 4025-014-003 | H45: 9317 CRENSHAW BLVD INGLEWOOD CA 90305 | I45: INGLEWOOD CA | J45: 90305-2959 | K45: 9301 – 9609 Crenshaw Blvd, Inglewood, CA | L45: Stadium Village Apartments | N45: manual_verified_multi | O45: Four Units (Any Combination) | P45: Residential | Q45: 400 | R45: 1955 | S45: 4 | T45: 8 | U45: 4 | V45: 4072 | W45: 2025 | X45: 770000 | Y45: 575000 | Z45: =SUM(X45:Y45) -> 1345000 | AA45: 2025 | AB45: 2025 | AC45: 0 | AD45: 4569 | AE45: INGLEWOOD | AF45: 33.95178 | AG45: -118.32697 | AH45: TRACT NO 16139 LOT 3 | AI45: Multi-parcel (20) | AJ45: {=_xlfn.XLOOKUP( A45, 'CMFA-CSCDA Grants'!A:A, 'CMFA-CSCDA Grants'!O:O)} -> 80 | AK45: {=_xlfn.XLOOKUP( A45, 'CMFA-CSCDA Grants'!A:A, 'CMFA-CSCDA Grants'!P:P)} -> 80 | AL45: {=_xlfn.XLOOKUP( AD45, 'Tax Rates'!A:A, 'Tax Rates'!B:B)} -> 0.01280765
A46: 36 | B46: {=_xlfn.XLOOKUP( A46, 'CMFA-CSCDA Grants'!A:A, 'CMFA-CSCDA Grants'!E:E)} -> Los Angeles | C46: {=_xlfn.XLOOKUP( A46, 'CMFA-CSCDA Grants'!A:A, 'CMFA-CSCDA Grants'!B:B)} -> Stadium Village Apartments | D46: 4025014004 | F46: FALSE | G46: 4025-014-004 | H46: 9325 CRENSHAW BLVD INGLEWOOD CA 90305 | I46: INGLEWOOD CA | J46: 90305-2964 | K46: 9301 – 9609 Crenshaw Blvd, Inglewood, CA | L46: Stadium Village Apartments | N46: manual_verified_multi | O46: Four Units (Any Combination) | P46: Residential | Q46: 400 | R46: 1955 | S46: 4 | T46: 8 | U46: 4 | V46: 4073 | W46: 2025 | X46: 770000 | Y46: 575000 | Z46: =SUM(X46:Y46) -> 1345000 | AA46: 2025 | AB46: 2025 | AC46: 0 | AD46: 4569 | AE46: INGLEWOOD | AF46: 33.951615 | AG46: -118.32697 | AH46: TRACT NO 16139 LOT 4 | AI46: Multi-parcel (20) | AJ46: {=_xlfn.XLOOKUP( A46, 'CMFA-CSCDA Grants'!A:A, 'CMFA-CSCDA Grants'!O:O)} -> 80 | AK46: {=_xlfn.XLOOKUP( A46, 'CMFA-CSCDA Grants'!A:A, 'CMFA-CSCDA Grants'!P:P)} -> 80 | AL46: {=_xlfn.XLOOKUP( AD46, 'Tax Rates'!A:A, 'Tax Rates'!B:B)} -> 0.01280765
A47: 36 | B47: {=_xlfn.XLOOKUP( A47, 'CMFA-CSCDA Grants'!A:A, 'CMFA-CSCDA Grants'!E:E)} -> Los Angeles | C47: {=_xlfn.XLOOKUP( A47, 'CMFA-CSCDA Grants'!A:A, 'CMFA-CSCDA Grants'!B:B)} -> Stadium Village Apartments | D47: 4025014005 | F47: FALSE | G47: 4025-014-005 | H47: 9333 CRENSHAW BLVD INGLEWOOD CA 90305 | I47: INGLEWOOD CA | J47: 90305-2969 | K47: 9301 – 9609 Crenshaw Blvd, Inglewood, CA | L47: Stadium Village Apartments | N47: manual_verified_multi | O47: Four Units (Any Combination) | P47: Residential | Q47: 400 | R47: 1955 | S47: 4 | T47: 8 | U47: 4 | V47: 4038 | W47: 2025 | X47: 770000 | Y47: 575000 | Z47: =SUM(X47:Y47) -> 1345000 | AA47: 2025 | AB47: 2025 | AC47: 0 | AD47: 4569 | AE47: INGLEWOOD | AF47: 33.951451 | AG47: -118.32697 | AH47: TRACT NO 16139 LOT 5 | AI47: Multi-parcel (20) | AJ47: {=_xlfn.XLOOKUP( A47, 'CMFA-CSCDA Grants'!A:A, 'CMFA-CSCDA Grants'!O:O)} -> 80 | AK47: {=_xlfn.XLOOKUP( A47, 'CMFA-CSCDA Grants'!A:A, 'CMFA-CSCDA Grants'!P:P)} -> 80 | AL47: {=_xlfn.XLOOKUP( AD47, 'Tax Rates'!A:A, 'Tax Rates'!B:B)} -> 0.01280765
A48: 36 | B48: {=_xlfn.XLOOKUP( A48, 'CMFA-CSCDA Grants'!A:A, 'CMFA-CSCDA Grants'!E:E)} -> Los Angeles | C48: {=_xlfn.XLOOKUP( A48, 'CMFA-CSCDA Grants'!A:A, 'CMFA-CSCDA Grants'!B:B)} -> Stadium Village Apartments | D48: 4025014006 | F48: FALSE | G48: 4025-014-006 | H48: 9341 CRENSHAW BLVD INGLEWOOD CA 90305 | I48: INGLEWOOD CA | J48: 90305-2970 | K48: 9301 – 9609 Crenshaw Blvd, Inglewood, CA | L48: Stadium Village Apartments | N48: manual_verified_multi | O48: Four Units (Any Combination) | P48: Residential | Q48: 400 | R48: 1955 | S48: 4 | T48: 8 | U48: 4 | V48: 4038 | W48: 2025 | X48: 770000 | Y48: 575000 | Z48: =SUM(X48:Y48) -> 1345000 | AA48: 2025 | AB48: 2025 | AC48: 0 | AD48: 4569 | AE48: INGLEWOOD | AF48: 33.951286 | AG48: -118.32697 | AH48: TRACT NO 16139 LOT 6 | AI48: Multi-parcel (20) | AJ48: {=_xlfn.XLOOKUP( A48, 'CMFA-CSCDA Grants'!A:A, 'CMFA-CSCDA Grants'!O:O)} -> 80 | AK48: {=_xlfn.XLOOKUP( A48, 'CMFA-CSCDA Grants'!A:A, 'CMFA-CSCDA Grants'!P:P)} -> 80 | AL48: {=_xlfn.XLOOKUP( AD48, 'Tax Rates'!A:A, 'Tax Rates'!B:B)} -> 0.01280765
A49: 36 | B49: {=_xlfn.XLOOKUP( A49, 'CMFA-CSCDA Grants'!A:A, 'CMFA-CSCDA Grants'!E:E)} -> Los Angeles | C49: {=_xlfn.XLOOKUP( A49, 'CMFA-CSCDA Grants'!A:A, 'CMFA-CSCDA Grants'!B:B)} -> Stadium Village Apartments | D49: 4025014007 | F49: FALSE | G49: 4025-014-007 | H49: 9401 CRENSHAW BLVD INGLEWOOD CA 90305 | I49: INGLEWOOD CA | J49: 90305-2979 | K49: 9301 – 9609 Crenshaw Blvd, Inglewood, CA | L49: Stadium Village Apartments | N49: manual_verified_multi | O49: Four Units (Any Combination) | P49: Residential | Q49: 400 | R49: 1955 | S49: 4 | T49: 8 | U49: 4 | V49: 4073 | W49: 2025 | X49: 770000 | Y49: 575000 | Z49: =SUM(X49:Y49) -> 1345000 | AA49: 2025 | AB49: 2025 | AC49: 0 | AD49: 4569 | AE49: INGLEWOOD | AF49: 33.951121 | AG49: -118.32697 | AH49: TRACT NO 16139 LOT 7 | AI49: Multi-parcel (20) | AJ49: {=_xlfn.XLOOKUP( A49, 'CMFA-CSCDA Grants'!A:A, 'CMFA-CSCDA Grants'!O:O)} -> 80 | AK49: {=_xlfn.XLOOKUP( A49, 'CMFA-CSCDA Grants'!A:A, 'CMFA-CSCDA Grants'!P:P)} -> 80 | AL49: {=_xlfn.XLOOKUP( AD49, 'Tax Rates'!A:A, 'Tax Rates'!B:B)} -> 0.01280765
A50: 36 | B50: {=_xlfn.XLOOKUP( A50, 'CMFA-CSCDA Grants'!A:A, 'CMFA-CSCDA Grants'!E:E)} -> Los Angeles | C50: {=_xlfn.XLOOKUP( A50, 'CMFA-CSCDA Grants'!A:A, 'CMFA-CSCDA Grants'!B:B)} -> Stadium Village Apartments | D50: 4025014008 | F50: FALSE | G50: 4025-014-008 | H50: 9409 CRENSHAW BLVD INGLEWOOD CA 90305 | I50: INGLEWOOD CA | J50: 90305-2980 | K50: 9301 – 9609 Crenshaw Blvd, Inglewood, CA | L50: Stadium Village Apartments | N50: manual_verified_multi | O50: Four Units (Any Combination) | P50: Residential | Q50: 400 | R50: 1955 | S50: 4 | T50: 8 | U50: 4 | V50: 4073 | W50: 2025 | X50: 770000 | Y50: 575000 | Z50: =SUM(X50:Y50) -> 1345000 | AA50: 2025 | AB50: 2025 | AC50: 0 | AD50: 4569 | AE50: INGLEWOOD | AF50: 33.950956 | AG50: -118.32697 | AH50: TRACT NO 16139 LOT 8 | AI50: Multi-parcel (20) | AJ50: {=_xlfn.XLOOKUP( A50, 'CMFA-CSCDA Grants'!A:A, 'CMFA-CSCDA Grants'!O:O)} -> 80 | AK50: {=_xlfn.XLOOKUP( A50, 'CMFA-CSCDA Grants'!A:A, 'CMFA-CSCDA Grants'!P:P)} -> 80 | AL50: {=_xlfn.XLOOKUP( AD50, 'Tax Rates'!A:A, 'Tax Rates'!B:B)} -> 0.01280765
A51: 36 | B51: {=_xlfn.XLOOKUP( A51, 'CMFA-CSCDA Grants'!A:A, 'CMFA-CSCDA Grants'!E:E)} -> Los Angeles | C51: {=_xlfn.XLOOKUP( A51, 'CMFA-CSCDA Grants'!A:A, 'CMFA-CSCDA Grants'!B:B)} -> Stadium Village Apartments | D51: 4025014009 | F51: FALSE | G51: 4025-014-009 | H51: 9417 CRENSHAW BLVD INGLEWOOD CA 90305 | I51: INGLEWOOD CA | J51: 90305-2981 | K51: 9301 – 9609 Crenshaw Blvd, Inglewood, CA | L51: Stadium Village Apartments | N51: manual_verified_multi | O51: Four Units (Any Combination) | P51: Residential | Q51: 400 | R51: 1955 | S51: 4 | T51: 8 | U51: 4 | V51: 4038 | W51: 2025 | X51: 770000 | Y51: 575000 | Z51: =SUM(X51:Y51) -> 1345000 | AA51: 2025 | AB51: 2025 | AC51: 0 | AD51: 4569 | AE51: INGLEWOOD | AF51: 33.950791 | AG51: -118.32697 | AH51: TRACT NO 16139 LOT 9 | AI51: Multi-parcel (20) | AJ51: {=_xlfn.XLOOKUP( A51, 'CMFA-CSCDA Grants'!A:A, 'CMFA-CSCDA Grants'!O:O)} -> 80 | AK51: {=_xlfn.XLOOKUP( A51, 'CMFA-CSCDA Grants'!A:A, 'CMFA-CSCDA Grants'!P:P)} -> 80 | AL51: {=_xlfn.XLOOKUP( AD51, 'Tax Rates'!A:A, 'Tax Rates'!B:B)} -> 0.01280765
A52: 36 | B52: {=_xlfn.XLOOKUP( A52, 'CMFA-CSCDA Grants'!A:A, 'CMFA-CSCDA Grants'!E:E)} -> Los Angeles | C52: {=_xlfn.XLOOKUP( A52, 'CMFA-CSCDA Grants'!A:A, 'CMFA-CSCDA Grants'!B:B)} -> Stadium Village Apartments | D52: 4025014010 | F52: FALSE | G52: 4025-014-010 | H52: 9425 CRENSHAW BLVD INGLEWOOD CA 90305 | I52: INGLEWOOD CA | J52: 90305-2982 | K52: 9301 – 9609 Crenshaw Blvd, Inglewood, CA | L52: Stadium Village Apartments | N52: manual_verified_multi | O52: Four Units (Any Combination) | P52: Residential | Q52: 400 | R52: 1955 | S52: 4 | T52: 8 | U52: 4 | V52: 4038 | W52: 2025 | X52: 770000 | Y52: 575000 | Z52: =SUM(X52:Y52) -> 1345000 | AA52: 2025 | AB52: 2025 | AC52: 0 | AD52: 4569 | AE52: INGLEWOOD | AF52: 33.950626 | AG52: -118.32697 | AH52: TRACT NO 16139 LOT 10 | AI52: Multi-parcel (20) | AJ52: {=_xlfn.XLOOKUP( A52, 'CMFA-CSCDA Grants'!A:A, 'CMFA-CSCDA Grants'!O:O)} -> 80 | AK52: {=_xlfn.XLOOKUP( A52, 'CMFA-CSCDA Grants'!A:A, 'CMFA-CSCDA Grants'!P:P)} -> 80 | AL52: {=_xlfn.XLOOKUP( AD52, 'Tax Rates'!A:A, 'Tax Rates'!B:B)} -> 0.01280765
A53: 36 | B53: {=_xlfn.XLOOKUP( A53, 'CMFA-CSCDA Grants'!A:A, 'CMFA-CSCDA Grants'!E:E)} -> Los Angeles | C53: {=_xlfn.XLOOKUP( A53, 'CMFA-CSCDA Grants'!A:A, 'CMFA-CSCDA Grants'!B:B)} -> Stadium Village Apartments | D53: 4025014011 | F53: FALSE | G53: 4025-014-011 | H53: 9433 CRENSHAW BLVD INGLEWOOD CA 90305 | I53: INGLEWOOD CA | J53: 90305-2983 | K53: 9301 – 9609 Crenshaw Blvd, Inglewood, CA | L53: Stadium Village Apartments | N53: manual_verified_multi | O53: Four Units (Any Combination) | P53: Residential | Q53: 400 | R53: 1955 | S53: 4 | T53: 8 | U53: 4 | V53: 4073 | W53: 2025 | X53: 770000 | Y53: 575000 | Z53: =SUM(X53:Y53) -> 1345000 | AA53: 2025 | AB53: 2025 | AC53: 0 | AD53: 4569 | AE53: INGLEWOOD | AF53: 33.950461 | AG53: -118.32697 | AH53: TRACT NO 16139 LOT 11 | AI53: Multi-parcel (20) | AJ53: {=_xlfn.XLOOKUP( A53, 'CMFA-CSCDA Grants'!A:A, 'CMFA-CSCDA Grants'!O:O)} -> 80 | AK53: {=_xlfn.XLOOKUP( A53, 'CMFA-CSCDA Grants'!A:A, 'CMFA-CSCDA Grants'!P:P)} -> 80 | AL53: {=_xlfn.XLOOKUP( AD53, 'Tax Rates'!A:A, 'Tax Rates'!B:B)} -> 0.01280765
A54: 36 | B54: {=_xlfn.XLOOKUP( A54, 'CMFA-CSCDA Grants'!A:A, 'CMFA-CSCDA Grants'!E:E)} -> Los Angeles | C54: {=_xlfn.XLOOKUP( A54, 'CMFA-CSCDA Grants'!A:A, 'CMFA-CSCDA Grants'!B:B)} -> Stadium Village Apartments | D54: 4025014012 | F54: FALSE | G54: 4025-014-012 | H54: 9441 CRENSHAW BLVD INGLEWOOD CA 90305 | I54: INGLEWOOD CA | J54: 90305-2984 | K54: 9301 – 9609 Crenshaw Blvd, Inglewood, CA | L54: Stadium Village Apartments | N54: manual_verified_multi | O54: Four Units (Any Combination) | P54: Residential | Q54: 400 | R54: 1955 | S54: 4 | T54: 8 | U54: 4 | V54: 4072 | W54: 2025 | X54: 770000 | Y54: 575000 | Z54: =SUM(X54:Y54) -> 1345000 | AA54: 2025 | AB54: 2025 | AC54: 0 | AD54: 4569 | AE54: INGLEWOOD | AF54: 33.950296 | AG54: -118.32697 | AH54: TRACT NO 16139 LOT 12 | AI54: Multi-parcel (20) | AJ54: {=_xlfn.XLOOKUP( A54, 'CMFA-CSCDA Grants'!A:A, 'CMFA-CSCDA Grants'!O:O)} -> 80 | AK54: {=_xlfn.XLOOKUP( A54, 'CMFA-CSCDA Grants'!A:A, 'CMFA-CSCDA Grants'!P:P)} -> 80 | AL54: {=_xlfn.XLOOKUP( AD54, 'Tax Rates'!A:A, 'Tax Rates'!B:B)} -> 0.01280765
... A62: 36 | B62: {=_xlfn.XLOOKUP( A62, 'CMFA-CSCDA Grants'!A:A, 'CMFA-CSCDA Grants'!E:E)} -> Los Angeles | C62: {=_xlfn.XLOOKUP( A62, 'CMFA-CSCDA Grants'!A:A, 'CMFA-CSCDA Grants'!B:B)} -> Stadium Village Apartments | D62: 4025015002 | F62: FALSE | G62: 4025-015-002 | H62: 9609 CRENSHAW BLVD INGLEWOOD CA 90305 | I62: INGLEWOOD CA | J62: 90305-3153 | K62: 9301 – 9609 Crenshaw Blvd, Inglewood, CA | L62: Stadium Village Apartments | N62: manual_verified_multi | O62: Four Units (Any Combination) | P62: Residential | Q62: 400 | R62: 1955 | S62: 4 | T62: 8 | U62: 4 | V62: 4072 | W62: 2025 | X62: 770000 | Y62: 575000 | Z62: =SUM(X62:Y62) -> 1345000 | AA62: 2025 | AB62: 2025 | AC62: 0 | AD62: 4569 | AE62: INGLEWOOD | AF62: 33.948817 | AG62: -118.32698 | AH62: TRACT NO 16139 LOT 20 | AI62: Multi-parcel (20) | AJ62: {=_xlfn.XLOOKUP( A62, 'CMFA-CSCDA Grants'!A:A, 'CMFA-CSCDA Grants'!O:O)} -> 80 | AK62: {=_xlfn.XLOOKUP( A62, 'CMFA-CSCDA Grants'!A:A, 'CMFA-CSCDA Grants'!P:P)} -> 80 | AL62: {=_xlfn.XLOOKUP( AD62, 'Tax Rates'!A:A, 'Tax Rates'!B:B)} -> 0.01280765
A63: 37 | B63: {=_xlfn.XLOOKUP( A63, 'CMFA-CSCDA Grants'!A:A, 'CMFA-CSCDA Grants'!E:E)} -> Los Angeles | C63: {=_xlfn.XLOOKUP( A63, 'CMFA-CSCDA Grants'!A:A, 'CMFA-CSCDA Grants'!B:B)} -> 2330 E. 3rd Street Apartments | D63: 5183013023 | E63: 5183013001 | F63: FALSE | G63: 5183-013-023 | H63: 2330 E 3RD ST | I63: LOS ANGELES CA | J63: 90033-4012 | K63: 2330 E. 3rd Street, Los Angeles, CA | L63: 2330 E. 3rd Street Apartments | N63: parcel_in_transition | O63: Vacant Land | W63: 2025 | X63: 1275000 | Y63: 0 | Z63: =SUM(X63:Y63) -> 1275000 | AA63: 2025 | AD63: 4 | AE63: LOS ANGELES | AF63: 34.041342 | AG63: -118.21156 | AI63: Legacy AIN 5183013001 consolidated to 5183013023 | AJ63: {=_xlfn.XLOOKUP( A63, 'CMFA-CSCDA Grants'!A:A, 'CMFA-CSCDA Grants'!O:O)} -> 53 | AK63: {=_xlfn.XLOOKUP( A63, 'CMFA-CSCDA Grants'!A:A, 'CMFA-CSCDA Grants'!P:P)} -> 53 | AL63: {=_xlfn.XLOOKUP( AD63, 'Tax Rates'!A:A, 'Tax Rates'!B:B)} -> 0.0118738
A64: 38 | B64: {=_xlfn.XLOOKUP( A64, 'CMFA-CSCDA Grants'!A:A, 'CMFA-CSCDA Grants'!E:E)} -> Los Angeles | C64: {=_xlfn.XLOOKUP( A64, 'CMFA-CSCDA Grants'!A:A, 'CMFA-CSCDA Grants'!B:B)} -> Marquee Apartments | D64: 2321001019 | F64: FALSE | G64: 2321-001-019 | H64: 12300 SHERMAN WAY LOS ANGELES CA 91605 | I64: LOS ANGELES CA | J64: 91605-5527 | K64: 12300 Sherman Way, North Hollywood, CA 91605 | L64: Marquee Apartments | N64: manual_verified | O64: Five or more apartments | P64: Residential | Q64: 501 | R64: 1965 | S64: 236 | T64: 99 | U64: 99 | V64: 135223 | W64: 2025 | X64: 29800000 | Y64: 14000000 | Z64: =SUM(X64:Y64) -> 43800000 | AA64: 2025 | AB64: 2025 | AC64: 0 | AD64: 13 | AE64: LOS ANGELES | AF64: 34.199945 | AG64: -118.40139 | AH64: LOT COM AT SW COR OF LOT 1 TR NO 28781 TH N 89¢56'39" W TO SE LINE OF HOLLYWOOD FRWY TH NE THEREON TO W LINE OF SD LOT TH N AND FOLLOWING BDRY LINE OF SD LOT TO BEG ALL OF LOT 1 TRACT NO 28781 AND PART OF LOT 7 TRACT NO 2514 AND PART OF LOT 14 TRACT NO 2198 | AJ64: {=_xlfn.XLOOKUP( A64, 'CMFA-CSCDA Grants'!A:A, 'CMFA-CSCDA Grants'!O:O)} -> 236 | AK64: {=_xlfn.XLOOKUP( A64, 'CMFA-CSCDA Grants'!A:A, 'CMFA-CSCDA Grants'!P:P)} -> 236 | AL64: {=_xlfn.XLOOKUP( AD64, 'Tax Rates'!A:A, 'Tax Rates'!B:B)} -> 0.0118738
A65: 39 | B65: {=_xlfn.XLOOKUP( A65, 'CMFA-CSCDA Grants'!A:A, 'CMFA-CSCDA Grants'!E:E)} -> Los Angeles | C65: {=_xlfn.XLOOKUP( A65, 'CMFA-CSCDA Grants'!A:A, 'CMFA-CSCDA Grants'!B:B)} -> 6200 S. Broadway Apartments | D65: 6005021032 | F65: FALSE | G65: 6005-021-032 | H65: 6200 S BROADWAY LOS ANGELES CA 90003 | I65: LOS ANGELES CA | J65: 90003-1430 | K65: 6200 S Broadway, Los Angeles, CA | L65: 6200 S. Broadway Apartments | N65: manual_verified | O65: Commercial | P65: Commercial | Q65: 100V | R65: 2012 | S65: 1 | T65: 0 | U65: 1 | V65: 1488 | W65: 2025 | X65: 1326510 | Y65: 0 | Z65: =SUM(X65:Y65) -> 1326510 | AA65: 2023 | AB65: 2023 | AC65: 0 | AD65: 6659 | AE65: LOS ANGELES | AF65: 33.983094 | AG65: -118.27793 | AH65: WALTERS' MAIN ST AND MONETA AVE TRACT NO 2 EX OF ST LOTS 181 AND LOT 182 | AJ65: {=_xlfn.XLOOKUP( A65, 'CMFA-CSCDA Grants'!A:A, 'CMFA-CSCDA Grants'!O:O)} -> 66 | AK65: {=_xlfn.XLOOKUP( A65, 'CMFA-CSCDA Grants'!A:A, 'CMFA-CSCDA Grants'!P:P)} -> 51 | AL65: {=_xlfn.XLOOKUP( AD65, 'Tax Rates'!A:A, 'Tax Rates'!B:B)} -> 0.0118738
A66: 40 | B66: {=_xlfn.XLOOKUP( A66, 'CMFA-CSCDA Grants'!A:A, 'CMFA-CSCDA Grants'!E:E)} -> Los Angeles | C66: {=_xlfn.XLOOKUP( A66, 'CMFA-CSCDA Grants'!A:A, 'CMFA-CSCDA Grants'!B:B)} -> 4228 Western Ave. Apartments | D66: 5021009036 | F66: FALSE | G66: 5021-009-036 | H66: 4238 S WESTERN AVE LOS ANGELES CA 90062 | I66: LOS ANGELES CA | J66: 90062-1642 | K66: 4228 Western Avenue, Los Angeles, CA | L66: 4228 Western Ave. Apartments | N66: manual_verified | O66: Stores | P66: Commercial | Q66: 1100 | R66: 2024 | S66: 68 | T66: 76 | U66: 76 | V66: 40081 | W66: 2025 | X66: 17790840 | Y66: 0 | Z66: =SUM(X66:Y66) -> 17790840 | AA66: 2023 | AB66: 2023 | AC66: 0 | AD66: 212 | AE66: LOS ANGELES | AF66: 34.006352 | AG66: -118.30857 | AH66: DARTMOUTH SQUARE LOTS 7, 8 AND 9 | AJ66: {=_xlfn.XLOOKUP( A66, 'CMFA-CSCDA Grants'!A:A, 'CMFA-CSCDA Grants'!O:O)} -> 68 | AK66: {=_xlfn.XLOOKUP( A66, 'CMFA-CSCDA Grants'!A:A, 'CMFA-CSCDA Grants'!P:P)} -> 14 | AL66: {=_xlfn.XLOOKUP( AD66, 'Tax Rates'!A:A, 'Tax Rates'!B:B)} -> 0.0118738
A67: 41 | B67: {=_xlfn.XLOOKUP( A67, 'CMFA-CSCDA Grants'!A:A, 'CMFA-CSCDA Grants'!E:E)} -> Los Angeles | C67: {=_xlfn.XLOOKUP( A67, 'CMFA-CSCDA Grants'!A:A, 'CMFA-CSCDA Grants'!B:B)} -> 4327 S. Vermont Apartments | D67: 5020025039 | F67: FALSE | G67: 5020-025-039 | H67: 4301 S VERMONT AVE LOS ANGELES CA 90037 | I67: LOS ANGELES CA | J67: 90037-2411 | K67: 4327 S Vermont, Los Angeles, CA | L67: 4327 S. Vermont Apartments | N67: manual_verified | O67: Stores | P67: Commercial | Q67: 1100 | R67: 1968 | S67: 11 | T67: 0 | U67: 0 | V67: 10486 | W67: 2025 | X67: 3529071 | Y67: 190487 | Z67: =SUM(X67:Y67) -> 3719558 | AA67: 2023 | AB67: 2023 | AC67: 0 | AD67: 6660 | AE67: LOS ANGELES | AF67: 34.004916 | AG67: -118.29205 | AH67: P.M.6-70 LOT B | AJ67: {=_xlfn.XLOOKUP( A67, 'CMFA-CSCDA Grants'!A:A, 'CMFA-CSCDA Grants'!O:O)} -> 188 | AK67: {=_xlfn.XLOOKUP( A67, 'CMFA-CSCDA Grants'!A:A, 'CMFA-CSCDA Grants'!P:P)} -> 111 | AL67: {=_xlfn.XLOOKUP( AD67, 'Tax Rates'!A:A, 'Tax Rates'!B:B)} -> 0.0118738
A68: 42 | B68: {=_xlfn.XLOOKUP( A68, 'CMFA-CSCDA Grants'!A:A, 'CMFA-CSCDA Grants'!E:E)} -> Los Angeles | C68: {=_xlfn.XLOOKUP( A68, 'CMFA-CSCDA Grants'!A:A, 'CMFA-CSCDA Grants'!B:B)} -> 2023 Imperial Apartments | D68: 6083001009 | F68: FALSE | G68: 6083-001-009 | H68: 110 E IMPERIAL HWY LOS ANGELES CA 90061 | I68: LOS ANGELES CA | J68: 90061-2543 | K68: 110 Imperial Highway, Los Angeles, CA | L68: 2023 Imperial Apartments | N68: manual_verified | O68: Lgt Manf.Sm. EQPT. Manuf Sm.Shps Instr.Manuf. Prnt Plnts | P68: Industrial | Q68: 3100 | R68: 1951 | S68: 0 | T68: 0 | U68: 0 | V68: 7675 | W68: 2025 | X68: 213261 | Y68: 216103 | Z68: =SUM(X68:Y68) -> 429364 | AA68: 2004 | AB68: 2004 | AC68: 0 | AD68: 6654 | AE68: LOS ANGELES | AF68: 33.930763 | AG68: -118.27311 | AH68: TRACT NO 3598 LOT COM AT MOST S COR OF LOT 9 TH N 54 DEG 17 M1N 2O SEC W 145.46 FT TH N ON A CURVE CONCAVE TO E RAD1US EQUALS 4O FT 37.51 FT TH N 44 DEG 38 M1N 56 SEC E 11.31 FT TH N 89 DEG 38 M1N 56 SEC E 126.42 FT TH S O DEG 33 M1N 3O SEC E 126.89 FT TO BEG PART OF LOT 9 | AJ68: {=_xlfn.XLOOKUP( A68, 'CMFA-CSCDA Grants'!A:A, 'CMFA-CSCDA Grants'!O:O)} -> 90 | AK68: {=_xlfn.XLOOKUP( A68, 'CMFA-CSCDA Grants'!A:A, 'CMFA-CSCDA Grants'!P:P)} -> 71 | AL68: {=_xlfn.XLOOKUP( AD68, 'Tax Rates'!A:A, 'Tax Rates'!B:B)} -> 0.0118738
